Workbook
Name q: [1]Metal!#REF!
Name REKAPBARANG: #REF!
Name REKAPBARANG: #REF!
Name REKAPMATERIAL: #REF!
Name REKAPMATERIAL: #REF!
Name tes: '[2]Costing T1'!#REF!
Name yds: [3]YDS!$A$1:$H$65536
Name yds: [3]YDS!$A$1:$H$65536
Name yds: [3]YDS!$A$1:$H$65536
Name yds: [3]YDS!$A$1:$H$65536
Name yds: [4]YDS!$A$1:$H$65536

Sheet DB_MOTOR
A2: PRICELIST MOTOR
B4: KW | C4: HP | D4: CLASS | E4: CMP | K4: ATT
E5: 2 Pole | F5: Disc 50% | G5: 4 Pole | H5: Disc 50% | I5: 6 Pole | J5: Disc 50% | K5: 2 Pole | L5: IDR | M5: 4 Pole | N5: IDR | O5: 6 Pole | P5: IDR | Q5: 8 Pole | R5: IDR
B6: 0.25 | C6: 0.35 | D6: IE1 | E6: ****** | G6: 1540008 | I6: ****** | K6: ******* | M6: ******* | O6: ******* | Q6: *******
B7: 0.37 | C7: 0.5 | E7: 1408243 | F7: =50%*E7 -> 704121.5 | G7: 1622362 | H7: =50%*G7 -> 811181 | I7: 2067070 | J7: =I7*50% -> 1033535 | K7: 67 | L7: =(K7+(1%*K7)-(5%*K7))*12299 -> 791071.68 | M7: 73 | N7: =(M7+(1%*M7)-(5%*M7))*12299 -> 861913.92 | O7: 95 | P7: =(O7+(1%*O7)-(5%*O7))*12299 -> 1121668.8 | Q7: 133 | R7: =(Q7+(1%*Q7)-(5%*Q7))*12299 -> 1570336.3
B8: 0.55 | C8: 0.75 | E8: 1589420 | F8: =50%*E8 -> 794710 | G8: 1918834 | H8: =50%*G8 -> 959417 | I8: 2330600 | J8: =I8*50% -> 1165300 | K8: 73 | L8: =(K8+(1%*K8)-(5%*K8))*12299 -> 861913.92 | M8: 97 | N8: =(M8+(1%*M8)-(5%*M8))*12299 -> 1145282.9 | O8: 106 | P8: =(O8+(1%*O8)-(5%*O8))*12299 -> 1251546.2 | Q8: 147 | R8: =(Q8+(1%*Q8)-(5%*Q8))*12299 -> 1735634.9
B9: 0.75 | C9: 1 | E9: 2034129 | F9: =50%*E9 -> 1017064.5 | G9: 2075306 | H9: =50%*G9 -> 1037653 | I9: 2610602 | J9: =I9*50% -> 1305301 | K9: 91 | L9: =(K9+(1%*K9)-(5%*K9))*12299 -> 1074440.6 | M9: 105 | N9: =(M9+(1%*M9)-(5%*M9))*12299 -> 1239739.2 | O9: 129 | P9: =(O9+(1%*O9)-(5%*O9))*12299 -> 1523108.2 | Q9: 168 | R9: =(Q9+(1%*Q9)-(5%*Q9))*12299 -> 1983582.7
B10: 1.1 | C10: 1.5 | E10: 2157658 | F10: =50%*E10 -> 1078829 | G10: 2610602 | H10: =50%*G10 -> 1305301 | I10: 3063546 | J10: =I10*50% -> 1531773 | K10: 102 | L10: =(K10+(1%*K10)-(5%*K10))*12299 -> 1204318.1 | M10: 120 | N10: =(M10+(1%*M10)-(5%*M10))*12299 -> 1416844.8 | O10: 148 | P10: =(O10+(1%*O10)-(5%*O10))*12299 -> 1747441.9 | Q10: 204 | R10: =(Q10+(1%*Q10)-(5%*Q10))*12299 -> 2408636.2
B11: 1.5 | C11: 2 | E11: 2610602 | F11: =50%*E11 -> 1305301 | G11: 3005899 | H11: =50%*G11 -> 1502949.5 | I11: 3755314 | J11: =I11*50% -> 1877657 | K11: 123 | L11: =(K11+(1%*K11)-(5%*K11))*12299 -> 1452265.9 | M11: 136 | N11: =(M11+(1%*M11)-(5%*M11))*12299 -> 1605757.4 | O11: 166 | P11: =(O11+(1%*O11)-(5%*O11))*12299 -> 1959968.6 | Q11: 251 | R11: =(Q11+(1%*Q11)-(5%*Q11))*12299 -> 2963567
B12: 2.2 | C12: 3 | E12: 3047075 | F12: =50%*E12 -> 1523537.5 | G12: 3804726 | H12: =50%*G12 -> 1902363 | I12: 5015321 | J12: =I12*50% -> 2507660.5 | K12: 141 | L12: =(K12+(1%*K12)-(5%*K12))*12299 -> 1664792.6 | M12: 170 | N12: =(M12+(1%*M12)-(5%*M12))*12299 -> 2007196.8 | O12: 216 | P12: =(O12+(1%*O12)-(5%*O12))*12299 -> 2550320.6 | Q12: 292 | R12: =(Q12+(1%*Q12)-(5%*Q12))*12299 -> 3447655.7
B13: 3 | C13: 4 | E13: 3944727 | F13: =50%*E13 -> 1972363.5 | G13: 4397670 | H13: =50%*G13 -> 2198835 | I13: 6374152 | J13: =I13*50% -> 3187076 | K13: 182 | L13: =(K13+(1%*K13)-(5%*K13))*12299 -> 2148881.3 | M13: 191 | N13: =(M13+(1%*M13)-(5%*M13))*12299 -> 2255144.6 | O13: 277 | P13: =(O13+(1%*O13)-(5%*O13))*12299 -> 3270550.1 | Q13: 326 | R13: =(Q13+(1%*Q13)-(5%*Q13))*12299 -> 3849095
B14: 4 | C14: 5.5 | E14: 4900026 | F14: =50%*E14 -> 2450013 | G14: 5624735 | H14: =50%*G14 -> 2812367.5 | I14: 7403569 | J14: =I14*50% -> 3701784.5 | K14: 216 | L14: =(K14+(1%*K14)-(5%*K14))*12299 -> 2550320.6 | M14: 245 | N14: =(M14+(1%*M14)-(5%*M14))*12299 -> 2892724.8 | O14: 322 | P14: =(O14+(1%*O14)-(5%*O14))*12299 -> 3801866.9 | Q14: 479 | R14: =(Q14+(1%*Q14)-(5%*Q14))*12299 -> 5655572.2
B15: 5.5 | C15: 7.5 | E15: 7082391 | F15: =50%*E15 -> 3541195.5 | G15: 7205920 | H15: =50%*G15 -> 3602960 | I15: 8836518 | J15: =I15*50% -> 4418259 | K15: 314 | L15: =(K15+(1%*K15)-(5%*K15))*12299 -> 3707410.6 | M15: 303 | N15: =(M15+(1%*M15)-(5%*M15))*12299 -> 3577533.1 | O15: 377 | P15: =(O15+(1%*O15)-(5%*O15))*12299 -> 4451254.1 | Q15: 527 | R15: =(Q15+(1%*Q15)-(5%*Q15))*12299 -> 6222310.1
B16: 7.5 | C16: 10 | E16: 7815336 | F16: =50%*E16 -> 3907668 | G16: 8581222 | H16: =50%*G16 -> 4290611 | I16: 12328301 | J16: =I16*50% -> 6164150.5 | K16: 339 | L16: =(K16+(1%*K16)-(5%*K16))*12299 -> 4002586.6 | M16: 362 | N16: =(M16+(1%*M16)-(5%*M16))*12299 -> 4274148.5 | O16: 512 | P16: =(O16+(1%*O16)-(5%*O16))*12299 -> 6045204.5 | Q16: 620 | R16: =(Q16+(1%*Q16)-(5%*Q16))*12299 -> 7320364.8
B17: 11 | C17: 15 | E17: 12649479 | F17: =50%*E17 -> 6324739.5 | G17: 13085952 | H17: =50%*G17 -> 6542976 | I17: 15218904 | J17: =I17*50% -> 7609452 | K17: 522 | L17: =(K17+(1%*K17)-(5%*K17))*12299 -> 6163274.9 | M17: 541 | N17: =(M17+(1%*M17)-(5%*M17))*12299 -> 6387608.6 | O17: 632 | P17: =(O17+(1%*O17)-(5%*O17))*12299 -> 7462049.3 | Q17: 837 | R17: =(Q17+(1%*Q17)-(5%*Q17))*12299 -> 9882492.5
B18: 15 | C18: 20 | E18: 13958898 | F18: =50%*E18 -> 6979449 | G18: 15433023 | H18: =50%*G18 -> 7716511.5 | I18: 19954223 | J18: =I18*50% -> 9977111.5 | K18: 578 | L18: =(K18+(1%*K18)-(5%*K18))*12299 -> 6824469.1 | M18: 645 | N18: =(M18+(1%*M18)-(5%*M18))*12299 -> 7615540.8 | O18: 856 | P18: =(O18+(1%*O18)-(5%*O18))*12299 -> 10106826 | Q18: 1081 | R18: =(Q18+(1%*Q18)-(5%*Q18))*12299 -> 12763410
B19: 18.5 | C19: 25 | E19: 16190674 | F19: =50%*E19 -> 8095337 | G19: 19740105 | H19: =50%*G19 -> 9870052.5 | I19: 24911897 | J19: =I19*50% -> 12455948 | K19: 639 | L19: =(K19+(1%*K19)-(5%*K19))*12299 -> 7544698.6 | M19: 819 | N19: =(M19+(1%*M19)-(5%*M19))*12299 -> 9669965.8 | O19: 1021 | P19: =(O19+(1%*O19)-(5%*O19))*12299 -> 12054988 | Q19: 1351 | R19: =(Q19+(1%*Q19)-(5%*Q19))*12299 -> 15951311
B20: 22 | C20: 30 | E20: 20810699 | F20: =50%*E20 -> 10405350 | G20: 21543644 | H20: =50%*G20 -> 10771822 | I20: 26756613 | J20: =I20*50% -> 13378306
B23: SELISIH CMP & ATT
B24: KW | C24: HP | D24: CLASS | E24: 2POLE | F24: (%) | G24: 4POLE | H24: (%) | I24: 6POLE | J24: (%)
B26: 0.25 | C26: 0.35 | D26: IE1
B27: 0.37 | C27: 0.5 | E27: =F7-L7 -> -86950.18 | F27: =E27/F7 -> -0.12348747 | G27: =H7-N7 -> -50732.92 | H27: =G27/H7 -> -0.062542047 | I27: =J7-P7 -> -88133.8 | J27: =I27/J7 -> -0.085274132
B28: 0.55 | C28: 0.75 | E28: =F8-L8 -> -67203.92 | F28: =E28/F8 -> -0.08456408 | G28: =H8-N8 -> -185865.88 | H28: =G28/H8 -> -0.19372794 | I28: =J8-P8 -> -86246.24 | J28: =I28/J8 -> -0.074012048
B29: 0.75 | C29: 1 | E29: =F9-L9 -> -57376.14 | F29: =E29/F9 -> -0.056413472 | G29: =H9-N9 -> -202086.2 | H29: =G29/H9 -> -0.19475316 | I29: =J9-P9 -> -217807.16 | J29: =I29/J9 -> -0.16686355
B30: 1.1 | C30: 1.5 | E30: =F10-L10 -> -125489.08 | F30: =E30/F10 -> -0.11631971 | G30: =H10-N10 -> -111543.8 | H30: =G30/H10 -> -0.085454466 | I30: =J10-P10 -> -215668.92 | J30: =I30/J10 -> -0.14079692
B31: 1.5 | C31: 2 | E31: =F11-L11 -> -146964.92 | F31: =E31/F11 -> -0.11259083 | G31: =H11-N11 -> -102807.94 | H31: =G31/H11 -> -0.068404121 | I31: =J11-P11 -> -82311.64 | J31: =I31/J11 -> -0.043837421
B32: 2.2 | C32: 3 | E32: =F12-L12 -> -141255.14 | F32: =E32/F12 -> -0.092715237 | G32: =H12-N12 -> -104833.8 | H32: =G32/H12 -> -0.055107148 | I32: =J12-P12 -> -42660.14 | J32: =I32/J12 -> -0.017011928
B33: 3 | C33: 4 | E33: =F13-L13 -> -176517.78 | F33: =E33/F13 -> -0.089495562 | G33: =H13-N13 -> -56309.64 | H33: =G33/H13 -> -0.025608852 | I33: =J13-P13 -> -83474.08 | J33: =I33/J13 -> -0.026191431
B34: 4 | C34: 5.5 | E34: =F14-L14 -> -100307.64 | F34: =E34/F14 -> -0.040941677 | G34: =H14-N14 -> -80357.3 | H34: =G34/H14 -> -0.028572831 | I34: =J14-P14 -> -100082.38 | J34: =I34/J14 -> -0.027036252
B35: 5.5 | C35: 7.5 | E35: =F15-L15 -> -166215.06 | F35: =E35/F15 -> -0.046937555 | G35: =H15-N15 -> 25426.88 | H35: =G35/H15 -> 0.0070572196 | I35: =J15-P15 -> -32995.08 | J35: =I35/J15 -> -0.0074678918
B36: 7.5 | C36: 10 | E36: =F16-L16 -> -94918.56 | F36: =E36/F16 -> -0.024290334 | G36: =H16-N16 -> 16462.52 | H36: =G36/H16 -> 0.0038368708 | I36: =J16-P16 -> 118946.02 | J36: =I36/J16 -> 0.019296417
B37: 11 | C37: 15 | E37: =F17-L17 -> 161464.62 | F37: =E37/F17 -> 0.025529055 | G37: =H17-N17 -> 155367.36 | H37: =G37/H17 -> 0.023745672 | I37: =J17-P17 -> 147402.72 | J37: =I37/J17 -> 0.019371003
B38: 15 | C38: 20 | E38: =F18-L18 -> 154979.88 | F38: =E38/F18 -> 0.022205174 | G38: =H18-N18 -> 100970.7 | H38: =G38/H18 -> 0.013085019 | I38: =J18-P18 -> -129714.74 | J38: =I38/J18 -> -0.013001232
B39: 18.5 | C39: 25 | E39: =F19-L19 -> 550638.44 | F39: =E39/F19 -> 0.068019212 | G39: =H19-N19 -> 200086.74 | H39: =G39/H19 -> 0.020272105 | I39: =J19-P19 -> 400960.66 | J39: =I39/J19 -> 0.032190295
B40: 22 | C40: 30

Sheet DB-SanMu Plug Fan
A1: xx
B2: SanMu EC Plug Fans
B3: Model | C3: Motor KW | D3: OSX(H) | E3: AHU(M) | F3: AHU(H) | G3: RTU(M) | H3: SBH(M) | I3: FOB China U/P | J3: USD
B4: ECF(K)6D280-PLHDAL1-RF | C4: 1.14 | E4: 1 | G4: 1 | H4: 1 | I4: 577.9 | J4: =I4*0.77 -> 444.983
B5: ECF(K)8D310-PLHDAL1-RF | C5: 1.65 | F5: 1 | I5: 712 | J5: =I5*0.77 -> 548.24
B6: ECF(K)8D310-PLHDAL5-RF | C6: 3.03 | F6: 1 | I6: 810.3 | J6: =I6*0.77 -> 623.931
B7: ECF(K)8D355-PLHDAL0-RF | C7: 2.56 | D7: 1 | E7: 1 | H7: 1 | I7: 911 | J7: =I7*0.77 -> 701.47
B8: ECF(K)8D355-PLHDAL11-RF | C8: 3.25 | F8: 1 | H8: 1 | I8: 1046.2 | J8: =I8*0.77 -> 805.574
B9: ECF(K)8D355-PLHDAL19A-RF | C9: 0.815 | E9: 1 | G9: 1 | H9: 1 | I9: 765 | J9: =I9*0.77 -> 589.05
B10: ECF(K)10D450-PLHDAL0-RF | C10: 5.7 | D10: 1 | F10: 1 | G10: 1 | I10: 1350 | J10: =I10*0.77 -> 1039.5
B11: ECF(K)8D500-PLHDAL7-RF | C11: 4.13 | H11: 1 | I11: 1150 | J11: =I11*0.77 -> 885.5
B12: ECF(K)8D560-PLHDAL10C-RF | C12: 4.8 | E12: 1 | G12: 1 | H12: 1 | I12: 1200 | J12: =I12*0.77 -> 924
B13: ECF(K)10D630-PLHDAL1-RF | C13: 6.85 | E13: 1 | F13: 1 | G13: 1 | H13: 1 | I13: 1950 | J13: =I13*0.77 -> 1501.5
B14: ECF(K)8D630-PLHDAL10Y-RF | C14: 3.45 | H14: 1 | I14: 1450 | J14: =I14*0.77 -> 1116.5

Sheet Master
A1: BUSH NG. | B1: List Price | F1: Motor | J1: Blower
B2: METRIC | C2: INCH | F2: Motor 0.18kW-2P | G2: 56.2 | P2: Pentapost | R2: Centerpost | T2: Cornerpiece | V2: Omega Joint | X2: Panel Clip | Z2: Tebal Panel
B3: Rupiah | C3: Rupiah | F3: Motor 0.37kW-2P | G3: 67 | O3: Type | P3: kG/m | Q3: Rp/m | R3: kG/m | S3: Rp/m | T3: kG/Pc | U3: Rp/Pc | V3: kG/Pc | W3: Rp/Pc | X3: kG/m | Y3: Rp/m | Z3: mm | AC3: Type | AD3: Cost | AE3: Irridiance
A4: Bush 1008 | B4: 160000 | C4: 320000 | F4: Motor 0.55kW-2P | G4: 73.5 | J4: TYPE | K4: Ex-work | N4: 1 | O4: 1520T(NA06) | P4: 0.316 | Q4: =0.316*75000 -> 23700 | R4: 0.336 | S4: =0.399*75000 -> 29925 | T4: 0.12 | U4: 15500 | V4: 0 | W4: 0 | X4: 0 | Y4: 0 | Z4: 15 | AC4: ESL 20W x 515mmL | AD4: 58 | AE4: 72uW/cm2
A5: Bush 1108 | B5: 180000 | C5: 360000 | F5: Motor 0.75kW-2P | G5: 89.1 | K5: (USD) | N5: 2 | O5: 1520T(NA20) | P5: 0.316 | Q5: =0.316*80000 -> 25280 | R5: 0.336 | S5: =0.336*80000 -> 26880 | T5: 0.12 | U5: 15500 | V5: 0 | W5: 0 | X5: 0 | Y5: 0 | Z5: 15 | AC5: ESL 40W x 910mmL | AD5: 59.9 | AE5: 145uW/cm2
A6: Bush 1210 | B6: 240000 | C6: 480000 | F6: Motor 1.1kW-2P | G6: 95.5 | N6: 3 | O6: 1540T(NA06) | P6: 0.832 | Q6: =0.832*75000 -> 62400 | R6: 0.539 | S6: =0.539*75000 -> 40425 | T6: 0.123886 | U6: 15500 | V6: 0 | W6: 0 | X6: 0 | Y6: 0 | Z6: 15 | AC6: ESL 60W x 550mmL | AD6: 39.8 | AE6: 165uW/cm2
A7: Bush 1215 | B7: 260000 | C7: 520000 | F7: Motor 1.5kW-2P | G7: 114.5 | N7: 4 | O7: 1540T(NA20) | P7: 0.832 | Q7: =0.832*80000 -> 66560 | R7: 0.539 | S7: =0.539*75000 -> 40425 | T7: 0.123886 | U7: 15500 | V7: 0 | W7: 0 | X7: 0 | Y7: 0 | Z7: 15 | AC7: ESL 80W x 843mmL | AD7: 40.9 | AE7: 245uW/cm2
A8: Bush 1610 | B8: 290000 | C8: 580000 | F8: Motor 2.2kW-2P | G8: 132.3 | J8: AT 07/07-S | K8: 74 | L8: 5 | N8: 5 | O8: 2540Y(NA06) | P8: 1.337 | Q8: =(0.694+0.376)*75000+12500*4 -> 130250 | R8: =0.378+0.517 -> 0.895 | S8: =(0.378+0.517)*75000+12500*4 -> 117125 | T8: 0.13427 | U8: =(1.5*2)*15000 -> 45000 | V8: 0.035 | W8: =(0.4*15000)*2 -> 12000 | X8: 0.202 | Y8: =X8*95000 -> 19190 | Z8: 25 | AC8: ESL 95W x 530mmL | AD8: 51.3 | AE8: 305uW/cm2
A9: Bush 1615 | B9: 300000 | C9: 600000 | F9: Motor 3kW-2P | G9: 167.4 | J9: AT 07/07-S C/W M/F | K9: 82 | L9: 5 | N9: 6 | O9: 2540Y(NA20) | P9: 1.337 | Q9: =(0.694+0.376)*80000+12500*4 -> 135600 | R9: 1.249 | S9: =(0.378+0.517)*80000+12500*4 -> 121600 | T9: 0.13427 | U9: =(1.5*2)*15000 -> 45000 | V9: 0.035 | W9: =(0.4*15000)*2 -> 12000 | X9: 0.202 | Y9: =X9*75000 -> 15150 | Z9: 25 | AC9: ESL 120W x 1148mmL | AD9: 53.5 | AE9: 340uW/cm2
A10: Bush 2012 | B10: 370000 | C10: 740000 | F10: Motor 4kW-2P | G10: 198.8 | J10: AT 09/07-S | K10: 54 | L10: 6.6 | N10: 7 | O10: 5060Y(NA06) | P10: 1.773 | Q10: =(1.083+0.376)*85000+12500*4 -> 174015 | R10: =0.576+0.517 -> 1.093 | S10: =(0.576+0.517)*75000+12500*4 -> 131975 | T10: 0.42476 | U10: =(2.8*2)*15000 -> 84000 | V10: 0.056628 | W10: 24000 | X10: 0.202 | Y10: =X10*75000 -> 15150 | Z10: 50 | AC10: ESL 150W x 1554mmL | AD10: 57.1 | AE10: 400uW/cm2
A11: Bush 2517 | B11: 660000 | C11: 1320000 | F11: Motor 5.5kW-2P | G11: 285.8 | J11: AT 09/07-S C/W M/F | K11: 59 | L11: 6.6 | N11: 8 | O11: 5060Y(NA20) | P11: 1.773 | Q11: =(1.083+0.376)*90000+12500*4 -> 181310 | R11: 1.428 | S11: =(0.576+0.517)*80000+12500*4 -> 137440 | T11: 0.42476 | U11: =(2.8*2)*15000 -> 84000 | V11: 0.056628 | W11: 24000 | X11: 0.202 | Y11: =X11*75000 -> 15150 | Z11: 50 | AC11: RLM 22" | AD11: =5300000/14000 -> 378.57143
A12: Bush 2525 | B12: 750000 | C12: 1500000 | F12: Motor 7.5kW-2P | G12: 338.6 | J12: AT 09/09-S | K12: 56 | L12: 7.9 | N12: 9 | O12: 5060N(NA06) | P12: 1.61207 | Q12: 126976.09 | R12: 1.2431 | S12: 95095.756 | T12: 0.21 | U12: 58597.98 | V12: 0.04 | W12: 17807.16 | X12: 0.17758621 | Y12: 11905.95 | Z12: 50 | AC12: RLM 33" | AD12: =6300000/14000 -> 450
A13: Bush 3020 | B13: 1060000 | C13: 2120000 | F13: Motor 11kW-2P | G13: 494.7 | J13: AT 09/09-S C/W M/F | K13: 62 | L13: 7.9 | M13: LB20 | N13: 10 | O13: 5060A(NA20) | P13: 1.9327586 | Q13: 183475.87 | R13: 1.5689655 | S13: 154397.74 | T13: 0.21 | U13: 58597.98 | V13: 0.04 | W13: 17807.16 | X13: 0.17758621 | Y13: 13769.49 | Z13: 50 | AC13: RLM 61" | AD13: =8500000/14000 -> 607.14286
A14: Bush 3030 | B14: 1420000 | C14: 2840000 | F14: Motor 15kW-2P | G14: 609.7 | J14: AT 10/08-S | K14: 59 | L14: 8.3 | N14: 11 | O14: 2550T(304) | P14: 4.969 | Q14: =P14*65000 -> 322985 | R14: 4.225 | S14: =R14*65000 -> 274625 | T14: 0.772 | U14: 31390 | V14: 0.062 | W14: 3719 | X14: 0 | Y14: 0 | Z14: 25
A15: Bush 3525 | B15: 1750000 | C15: 3500000 | F15: Motor 18.5kW-2P | G15: 710.1 | J15: AT 10/08-S C/W M/F | K15: 66 | L15: 8.3 | N15: 12 | O15: 2550T(316) | P15: 5.081 | Q15: =P15*80000 -> 406480 | R15: 4.317 | S15: =R15*80000 -> 345360 | T15: 0.792 | U15: 47203 | V15: 0.064 | W15: 3814 | X15: 0 | Y15: 0 | Z15: 25
A16: Bush 3535 | B16: 2290000 | C16: 4580000 | F16: Motor 22kW-2P | G16: 901.8 | J16: AT 10/10-S | K16: 65 | L16: 9.3 | N16: 13 | O16: 5070T(304) | P16: 6.147 | Q16: =P16*65000 -> 399555 | R16: 5.005 | S16: =R16*65000 -> 325325 | T16: 1.914 | U16: 77809 | V16: 0.094 | W16: 3805 | X16: 0 | Y16: 0 | Z16: 50 | AC16: DPG MagRFHelic | AD16: =675000/15000 -> 45
A17: Bush 4030 | B17: 3100000 | C17: 5600000 | F17: Motor 30kW-2P | G17: 1169.1 | J17: AT 10/10-S C/W M/F | K17: 72 | L17: 9.3 | N17: 14 | O17: 5070T(316) | P17: 6.291 | Q17: =P17*80000 -> 503280 | R17: 5.117 | S17: =R17*80000 -> 409360 | T17: 1.963 | U17: 117007 | V17: 0.096 | W17: 5722 | X17: 0 | Y17: 0 | Z17: 50 | AC17: DPG Magnehelic | AD17: =1600000/15000 -> 106.66667
A18: Bush 4040 | B18: 3700000 | C18: 6700000 | F18: Motor 37kW-2P | G18: 1379.7 | J18: AT 12/09-S | K18: 86 | L18: 12.7 | N18: 15 | O18: 2540A(304) | P18: 2.074 | Q18: 745100 | R18: 1.897 | S18: 792400 | T18: 0.31 | U18: 740100 | V18: 0.094 | W18: 176300 | X18: 0 | Y18: 0 | Z18: 25
A19: Bush 4535 | B19: 4100000 | C19: 7400000 | F19: Motor 45kW-2P | G19: 1714.5 | J19: AT 12/09-S C/W M/F | K19: 98 | L19: 12.7 | N19: 16 | O19: 2540A(316) | P19: 2.074 | Q19: 875200 | R19: 1.897 | S19: 922500 | T19: 0.31 | U19: 740100 | V19: 0.094 | W19: 176300 | X19: 0 | Y19: 0 | Z19: 25
A20: Bush 4545 | B20: 5100000 | C20: 8700000 | F20: Motor 55kW-2P | G20: 2134.7 | J20: AT 12/12-S | K20: 92 | L20: 15.2 | N20: 17 | O20: 4550A(304) | P20: 2.63 | Q20: 875200 | R20: 2.61 | S20: 863300 | T20: 0.494 | U20: 775300 | V20: 0.15 | W20: 176300 | X20: 0 | Y20: 0 | Z20: 45
A21: Bush 5040 | B21: 5800000 | C21: 8700000 | F21: Motor 75kW-2P | G21: 2780 | J21: AT 12/12-S C/W M/F | K21: 104 | L21: 15.2 | N21: 18 | O21: 4550A(316) | P21: 2.63 | Q21: 898800 | R21: 2.61 | S21: 887000 | T21: 0.494 | U21: 775300 | V21: 0.15 | W21: 176300 | X21: 0 | Y21: 0 | Z21: 45
A22: Bush 5050 | B22: 6800000 | C22: 10200000 | F22: Motor 90kW-2P | G22: 3529.5 | J22: AT 15/11-S | K22: 107 | L22: 17.7
A23: Bush 6050 | B23: 26000000 | C23: 39000000 | F23: Motor 110kW-2P | G23: 4286.6 | J23: AT 15/11-S C/W M/F | K23: 130 | L23: 17.7 | P23: T | Q23: L | R23: P | S23: M
A24: Bush 7060 | B24: 32000000 | C24: 48000000 | F24: Motor 0.18kW-4P | G24: =57.3 -> 57.3 | J24: AT 15/15-S | K24: 115 | L24: 20.6 | O24: DS 25 | P24: 2 | Q24: 185 | R24: 1000 | S24: =8000*P24*Q24*R24/1000000000 -> 2.96
A25: Pulley | C25: 48000000 | F25: Motor 0.37kW-4P | G25: =73.5 -> 73.5 | J25: AT 15/15-S C/W M/F | K25: 137 | L25: 20.6 | O25: DS 50 | P25: 2 | Q25: 273 | R25: 1000 | S25: =8000*P25*Q25*R25/1000000000 -> 4.368
F26: Motor 0.55kW-4P | G26: =85.4 -> 85.4 | J26: AT 18/13-S | K26: 150 | L26: 27
A27: Pitch Dia. | B27: Price | F27: Motor 0.75kW-4P | G27: =90.8 -> 90.8 | J27: AT 18/13-S C/W F | K27: 180 | L27: 27
F28: Motor 1.1kW-4P | G28: =107.5 -> 107.5 | J28: AT 18/18-S | K28: 166 | L28: 32.5
A29: 1SPZ50 | B29: 470000 | F29: Motor 1.5kW-4P | G29: =118.8 -> 118.8 | J29: AT 18/18-S C/W F | K29: 196 | L29: 32.5
A30: 1SPZ56 | B30: 510000 | F30: Motor 2.2kW-4P | G30: =142.6 -> 142.6 | J30: AT 22/22-S | K30: 430 | L30: 82.5
A31: 1SPZ60 | B31: 570000 | F31: Motor 3kW-4P | G31: =169.1 -> 169.1 | J31: AT 09/09-AR | K31: 101 | L31: 9.5
A32: 1SPZ63 | B32: 240000 | F32: Motor 4kW-4P | G32: =208.5 -> 208.5 | J32: AT 09/07-AR | K32: 98 | L32: 8.3
A33: 1SPZ67 | B33: 250000 | F33: Motor 5.5kW-4P | G33: =290 -> 290 | J33: AT 10/10-AR | K33: 100 | L33: 11
A34: 1SPZ71 | B34: 260000 | F34: Motor 7.5kW-4P | G34: =362.9 -> 362.9 | J34: AT 10/08-AR | K34: 99 | L34: 9.8
A35: 1SPZ75 | B35: 320000 | F35: Motor 11kW-4P | G35: =507.6 -> 507.6 | J35: AT 12/12-AR | K35: 128 | L35: 18.4
A36: 1SPZ80 | B36: 330000 | F36: Motor 15kW-4P | G36: =639.4 -> 639.4 | J36: AT 12/12-AR | K36: 141 | L36: 18.4
A37: 1SPZ85 | B37: 350000 | F37: Motor 18.5kW-4P | G37: =810.6 -> 810.6 | J37: AT 12/12-AR | K37: 121 | L37: 18.4
A38: 1SPZ90 | B38: 350000 | F38: Motor 22kW-4P | G38: =911.6 -> 911.6 | J38: AT 12/09-AR | K38: 117 | L38: 16
A39: 1SPZ95 | B39: 360000 | F39: Motor 30kW-4P | G39: =1252.8 -> 1252.8 | J39: AT 15/15-AR | K39: 146 | L39: 24.5
A40: 1SPZ100 | B40: 390000 | F40: Motor 37kW-4P | G40: =1400.3 -> 1400.3 | J40: AT 15/15-AR | K40: 186 | L40: 24.5
A41: 1SPZ106 | B41: 420000 | F41: Motor 45kW-4P | G41: =1723.2 -> 1723.2 | J41: AT 15/11-AR | K41: 180 | L41: 20.9
A42: 1SPZ112 | B42: 440000 | F42: Motor 55kW-4P | G42: =2210.3 -> 2210.3 | J42: AT 18/18-AR | K42: 215 | L42: 38.2
A43: 1SPZ118 | B43: 410000 | F43: Motor 75kW-4P | G43: =2827.5 -> 2827.5 | J43: AT 18/18-AR | K43: 239 | L43: 38.2
A44: 1SPZ125 | B44: 510000 | F44: Motor 90kW-4P | G44: =3411.8 -> 3411.8 | J44: AT 18/13-AR | K44: 202 | L44: 33
A45: 1SPZ132 | B45: 550000 | F45: Motor 110kW-4P | G45: =4286.6 -> 4286.6 | J45: AT 18/13-AR | K45: 225 | L45: 33
A46: 1SPZ140 | B46: 600000 | F46: Motor 0.18kW-6P | G46: 78.9 | J46: AT 07/07-SC | K46: 83 | L46: 6
A47: 1SPZ150 | B47: 620000 | F47: Motor 0.37kW-6P | G47: 88.6 | J47: AT 09/07-SC | K47: 64 | L47: 8.3
A48: 1SPZ160 | B48: 730000 | F48: Motor 0.55kW-6P | G48: 97.2 | J48: AT 09/09-SC | K48: 66 | L48: 9.5
A49: 1SPZ170 | B49: 850000 | F49: Motor 0.75kW-6P | G49: 115.6 | J49: AT 10/08-SC | K49: 69 | L49: 9.8
A50: 1SPZ180 | B50: 850000 | F50: Motor 1.1kW-6P | G50: 134.5 | J50: AT 10/10-SC | K50: 75 | L50: 11
A51: 1SPZ190 | B51: 920000 | F51: Motor 1.5kW-6P | G51: 163.7 | J51: AT 12/09-SC | K51: 96 | L51: 16
A52: 1SPZ200 | B52: 1030000 | F52: Motor 2.2kW-6P | G52: 193.4 | J52: AT 12/12-SC | K52: 102 | L52: 18.4
A53: 1SPZ212 | B53: 1200000 | F53: Motor 3kW-6P | G53: 258.2 | J53: AT 15/11-SC | K53: 112 | L53: 20.9
A54: 1SPZ224 | B54: 1200000 | F54: Motor 4kW-6P | G54: 337.5 | J54: AT 15/15-SC | K54: 118 | L54: 24.5
A55: 1SPZ236 | B55: 1470000 | F55: Motor 5.5kW-6P | G55: 405 | J55: AT 18/13-SC | K55: 164 | L55: 33
A56: 1SPZ250 | B56: 1500000 | F56: Motor 7.5kW-6P | G56: 533 | J56: AT 18/18-SC | K56: 178 | L56: 38.2
A57: 1SPZ280 | B57: 1900000 | F57: Motor 11kW-6P | G57: 696.6 | J57: AT 20/15-TIC | K57: 372 | L57: 71
... A67: 2SPZ67 | B67: 280000 | F67: Motor 110kW-6P | G67: 6110.1 | J67: AT 09/07-G2L C/W M/F | K67: 135 | L67: 14.9
A68: 2SPZ71 | B68: 310000 | J68: AT 09/09-G2L C/W M/F | K68: 137 | L68: 18.1
A69: 2SPZ75 | B69: 380000 | J69: AT 10/08-G2L C/W M/F | K69: 141 | L69: 18.5
A70: 2SPZ80 | B70: 390000 | J70: AT 10/10-G2L C/W M/F | K70: 146 | L70: 21.1
A71: 2SPZ85 | B71: 400000 | J71: AT 12/09-G2L C/W M/F | K71: 190 | L71: 28.2
A72: 2SPZ90 | B72: 430000 | J72: AT 12/12-G2L C/W M/F | K72: 207 | L72: 33.8
A73: 2SPZ95 | B73: 450000 | J73: AT 15/11-G2L C/W M/F | K73: 252 | L73: 39.7
A74: 2SPZ100 | B74: 460000 | J74: AT 15/15-G2L C/W M/F | K74: 273 | L74: 45.3
A75: 2SPZ106 | B75: 480000 | J75: AT 18/13-G2L C/W M/F | K75: 329 | L75: 57.8
A76: 2SPZ112 | B76: 500000 | J76: AT 18/18-G2L C/W M/F | K76: 391 | L76: 70.5
A77: 2SPZ118 | B77: 5770000 | J77: ADH 180 R | K77: 135 | L77: 7.8
A78: 2SPZ125 | B78: 620000 | J78: ADH 200 R | K78: 137 | L78: 9.1
A79: 2SPZ132 | B79: 680000 | J79: ADH 225 R | K79: 138 | L79: 10.7
... A159: 1SPA300 | B159: 2060000 | J159: RDH 1000 K2 | K159: 3010 | L159: 450.3
A160: 1SPA315 | B160: 2160000 | J160: SYT 09/07-L | K160: 78 | L160: 8 | M160: 54
A161: 1SPA335 | B161: 2300000 | J161: SYT 09/09-L | K161: 77 | L161: 9.5 | M161: 56
A162: 1SPA355 | B162: 2880000 | J162: SYT 10/10-L | K162: 92 | L162: 11 | M162: 63
A163: 1SPA375 | B163: 2900000 | J163: SYT 12/09-L | K163: 101 | L163: 15.2 | M163: 79
A164: 1SPA400 | B164: 2920000 | J164: SYT 12/12-L | K164: 111 | L164: 18.2 | M164: 83
A165: 1SPA425 | B165: 3220000 | J165: SYT 15/11-LK | K165: 171 | L165: 24.5 | M165: 113
A166: 1SPA450 | B166: 3420000 | J166: SYT 15/15-LK | K166: 152 | L166: 28.2 | M166: 122
A167: 1SPA475 | B167: 3890000 | J167: SYT 18/13-LK | K167: 197 | L167: 38.6 | M167: 148
A168: 1SPA500 | B168: 4360000 | J168: SYT 18/18-LK | K168: 213 | L168: 45.8 | M168: 155
A169: 1SPA530 | B169: 4630000 | J169: SYT 09/07-L2 | K169: 91 | L169: 17.9 | M169: 91
A170: 1SPA560 | B170: 5800000 | J170: SYT 09/09-L2 | K170: 98 | L170: 21.7 | M170: 98
A171: 1SPA630 | B171: 7000000 | J171: SYT 10/10-L2 | K171: 110 | L171: 25.3 | M171: 110
... A177: 2SPA85 | B177: 410000 | J177: SYT 18/18-L2 | K177: 283 | L177: 84.6 | M177: 283
A178: 2SPA90 | B178: 440000 | J178: SYD 160 R | K178: 64 | L178: 6.3 | M178: 47 | O178: =K178/M178 -> 1.3617021
A179: 2SPA95 | B179: 450000 | J179: SYD 180 R | K179: 68 | L179: 7.4 | M179: 50 | O179: =K179/M179 -> 1.36
A180: 2SPA100 | B180: 430000 | J180: SYD 200 R | K180: 68 | L180: 9.4 | M180: 54 | O180: =K180/M180 -> 1.2592593
A181: 2SPA106 | B181: 480000 | J181: SYD 225 R | K181: 73 | L181: 10.8 | M181: 58 | O181: =K181/M181 -> 1.2586207
A182: 2SPA112 | B182: 520000 | J182: SYD 250 R | K182: 95 | L182: 13 | M182: 70 | O182: =K182/M182 -> 1.3571429
A183: 2SPA118 | B183: 580000 | J183: SYD 280 R | K183: 98 | L183: 19 | M183: 85 | O183: =K183/M183 -> 1.1529412
A184: 2SPA125 | B184: 630000 | J184: SYD 315 R | K184: 115 | L184: 25 | M184: 101 | O184: =K184/M184 -> 1.1386139
A185: 2SPA132 | B185: 700000 | J185: SYD 355 R | K185: 157 | L185: 36 | M185: 127 | O185: =K185/M185 -> 1.2362205
A186: 2SPA140 | B186: 800000 | J186: SYD 400 R | K186: 191 | L186: 44 | M186: 160 | O186: =K186/M186 -> 1.19375
A187: 2SPA150 | B187: 910000 | J187: SYD 450 R | K187: 257 | L187: 57 | M187: 217 | O187: =K187/M187 -> 1.1843318
A188: 2SPA160 | B188: 1010000 | J188: SYD 500 R | K188: 306 | L188: 71.5 | M188: 258 | O188: =K188/M188 -> 1.1860465
A189: 2SPA170 | B189: 1210000 | J189: SYD 560 R | K189: 397 | L189: 131 | M189: 353 | O189: =K189/M189 -> 1.1246459
... A262: 1SPB140 | B262: 620000 | J262: SYH 1000 Z | K262: 2289 | L262: 535 | M262: 1524 | O262: =K262/M262 -> 1.5019685
A263: 1SPB150 | B263: 670000 | J263: EC-PDF190 | K263: 75 | L263: 10
A264: 1SPB160 | B264: 770000 | J264: EC-PDF225 | K264: 100 | L264: 12
A265: 1SPB170 | B265: 870000 | J265: EC-PDF315 | K265: 350 | L265: 33
...

Sheet SCU75M1
A1: X | C1: 1 | D1: 2 | E1: 3 | F1: 4 | G1: 5 | H1: 6 | I1: 7 | J1: 8 | K1: 9 | L1: 10 | M1: 11 | N1: 12 | O1: 13 | P1: 14 | Q1: 15 | R1: 16 | S1: 17 | T1: 18 | U1: 19 | V1: 20 | W1: 21 | X1: 22 | Y1: 23 | Z1: 24 | AA1: XXXXXXXX | AB1: X | AC1: XXXXXXXX | AD1: XXXXXXXX | AE1: XXXXXXXX | AF1: XXXXXXXX | AG1: X | AH1: X | AI1: X | AN1: X | AO1: X | AP1: X | AU1: X | AV1: X | AW1: X | BE1: X | BF1: X | BG1: X | BP1: X | BY1: X | CH1: X | CI1: X
B2: Casing Spec: SCU- | U2: =+B73 -> SCU75M1 | Y2: =+Y646 -> 177.79686 | Z2: =+Z646 -> 878.4747 | AA2: SCU75M1 | AC2: SCU75M1 | AD2: SCU100M1 | AE2: SCU125M1 | AF2: SCU150M1
B3: Specification Casing | D3: Frame | E3: Ambient | F3: Coat(Frm) | G3: Liner 1 (mmT) | I3: Liner 2 (mmT) | K3: Coat(Liner) | L3: Insulation | M3: Panel | N3: Coat(Pnl) | O3: Structure | P3: Coat(Skd) | Q3: Coat(Str) | R3: DrainPan | S3: Coat(DP)
B4: Entry==> | D4: 1540T(NA06) | E4: SA | F4: 1 | G4: GI | H4: 0 | I4: 0 | J4: 0 | K4: 1 | L4: 0 | M4: SGCC | N4: 1 | O4: SGCC | P4: 1 | Q4: 0 | R4: SUS316L | S4: 0
B5: Specification Coil | D5: Fin (DXC/CWC) | F5: Tube (DXC/CWC) | H5: EP (DXC/CWC) | J5: Header | K5: AGC | L5: VR514 | M5: UC5504
B6: Entry==> | D6: Al1100 | E6: 0.11 | F6: Cu | G6: 0.33 | H6: SGCC | I6: 1.5 | J6: Copper | K6: 1 | L6: 1 | M6: 0
B7: Specification Component | D7: Compressor | E7: Blower | F7: Axial Fan | G7: Enclosure | H7: LCS | I7: Rfg PT | J7: Rfg PG | K7: CC Heater | L7: S. Accum. | M7: FD/SG | N7: Ball Valve | O7: Cable | U7: Skid Rpt | V7: WPS | W7: MPT | X7: Load Test | Y7: FAT | Z7: ATEX
B8: Entry==> | D8: Copeland | E8: NA | F8: WeiGuang | G8: Std IP44 | H8: 0 | I8: 0 | J8: 0 | K8: 0 | L8: 0 | M8: 0 | N8: 0 | O8: 1 Core | U8: 0 | V8: 0 | W8: 0 | X8: 0 | Y8: 0 | Z8: 0
B9: Structure & Coating | D9: Casing Structure | G9: DrainPan | J9: Nylon-Coat | L9: Frame-Coat | N9: Liner-Coat | P9: Panel-Coat | R9: Skid-Hot Dip | T9: Structure-Coat | V9: DrainPan-Coat | Y9: Rp/USD | Z9: =+Z17 -> 14654
D10: Type | E10: kG/m3 | F10: Rp/kG | G10: Type | H10: kG/m3 | I10: Rp/kG | J10: kG/m2 | K10: Rp/m2 | L10: kG/m2 | M10: Rp/m2 | N10: kG/m2 | O10: Rp/m2 | P10: kG/m2 | Q10: Rp/kG | R10: kG/m2 | S10: Rp/kG | T10: kG/m2 | U10: Rp/m2 | V10: kG/m2 | W10: Rp/m2
D11: =+O4 -> SGCC | E11: =VLOOKUP($D11,$D$12:$F$18,2,FALSE) -> 8030 | F11: =VLOOKUP($D11,$D$12:$F$18,3,FALSE) -> 22500 | G11: =+R4 -> SUS316L | H11: =VLOOKUP($G11,$G$12:$I$18,2,FALSE) -> 8000 | I11: =VLOOKUP($G11,$G$12:$I$18,3,FALSE) -> 80000 | J11: =SUM(J12:J18)*F4 -> 0.372 | K11: =SUM(K12:K18)*F4 -> 105216.78 | L11: =SUM(L12:L18)*F4 -> 0.25 | M11: =SUM(M12:M18)*F4 -> 65000 | N11: =SUM(N12:N18)*K4 -> 0.25 | O11: =SUM(O12:O18)*K4 -> 65000 | P11: =SUM(P12:P18)*N4 -> 0.25 | Q11: =SUM(Q12:Q18)*N4 -> 65000 | R11: =SUM(R12:R18)*P4 -> 0.4284 | S11: =SUM(S12:S18)*P4 -> 9000 | T11: =SUM(T12:T18)*Q4 -> 0 | U11: =SUM(U12:U18)*Q4 -> 0 | V11: =SUM(V12:V18)*S4 -> 0 | W11: =SUM(W12:W18)*S4 -> 0
D12: SGCC | E12: 8030 | F12: 22500 | G12: SGCC | H12: 8030 | I12: 22500 | J12: 0.372 | K12: =7.25632959950898*14500 -> 105216.78 | L12: 0.25 | M12: 65000 | N12: 0.25 | O12: 65000 | P12: 0.25 | Q12: 65000 | R12: =60/1000000*7140 -> 0.4284 | S12: 9000 | T12: 0.25 | U12: 65000 | V12: 0.25 | W12: 65000 | Y12: USD | Z12: 1
D13: SPHC | E13: 7700 | F13: 18000 | G13: SPHC | H13: 7700 | I13: 18000 | Y13: Euro | Z13: 0.882
D14: SUS304 | E14: 7800 | F14: 65000 | G14: SUS304 | H14: 7800 | I14: 65000 | Y14: SGP | Z14: 1.375
D15: SUS316L | E15: 8000 | F15: 80000 | G15: SUS316L | H15: 8000 | I15: 80000 | Y15: RM | Z15: 4.186
D16: Al6063 | E16: 2720 | F16: =83085+(65000-54000) -> 94085 | G16: Al6063 | H16: 2720 | I16: =83085+(65000-54000) -> 94085 | Y16: Rmb | Z16: 6.935
D17: Copper | E17: 8900 | F17: 207000 | G17: Copper | H17: 8900 | I17: 207000 | Y17: Rp | Z17: 14654
Y18: Rs | Z18: 71.907
B19: Frame | D19: Pentapost | F19: Centerpost | H19: Cornerpiece | J19: Omega Joint | L19: Panel Clip | N19: Coating Area | R19: Cutting Allowance
C20: Type | D20: kG/m | E20: Rp/m | F20: kG/m | G20: Rp/m | H20: kG/Pc | I20: Rp/Pc | J20: kG/Pc | K20: Rp/Pc | L20: kG/m | M20: Rp/m | N20: Corner | O20: PP | P20: CP | Q20: CLIP | R20: PP | S20: CP | T20: Insert | U20: Gsk | V20: Clip L | W20: Clip H | X20: Pnl PP | Y20: Pnl CP
C21: =+D$4 -> 1540T(NA06) | D21: =VLOOKUP($C21,$C$22:$Y$40,2,FALSE) -> 0.711 | E21: =VLOOKUP($C21,$C$22:$Y$40,3,FALSE) -> 46215 | F21: =VLOOKUP($C21,$C$22:$Y$40,4,FALSE) -> 0.539 | G21: =VLOOKUP($C21,$C$22:$Y$40,5,FALSE) -> 35035 | H21: =VLOOKUP($C21,$C$22:$Y$40,6,FALSE) -> 0.123886 | I21: =VLOOKUP($C21,$C$22:$Y$40,7,FALSE) -> 7000 | J21: =VLOOKUP($C21,$C$22:$Y$40,8,FALSE) -> 0 | K21: =VLOOKUP($C21,$C$22:$Y$40,9,FALSE) -> 0 | L21: =VLOOKUP($C21,$C$22:$Y$40,10,FALSE) -> 0 | M21: =VLOOKUP($C21,$C$22:$Y$40,11,FALSE) -> 0 | N21: =VLOOKUP($C21,$C$22:$X$40,12,FALSE) -> 115 | O21: =VLOOKUP($C21,$C$22:$X$40,13,FALSE) -> 198 | P21: =VLOOKUP($C21,$C$22:$X$40,14,FALSE) -> 198 | Q21: =VLOOKUP($C21,$C$22:$X$40,15,FALSE) -> 0 | R21: =VLOOKUP($C21,$C$22:$Y$40,16,FALSE) -> 60 | S21: =VLOOKUP($C21,$C$22:$Y$40,17,FALSE) -> 40 | T21: =VLOOKUP($C21,$C$22:$Y$40,18,FALSE) -> 0 | U21: =VLOOKUP($C21,$C$22:$Y$40,19,FALSE) -> 40 | V21: =VLOOKUP($C21,$C$22:$Y$40,20,FALSE) -> 0 | W21: =VLOOKUP($C21,$C$22:$Y$40,21,FALSE) -> 0 | X21: =VLOOKUP($C21,$C$22:$Y$40,22,FALSE) -> 40 | Y21: =VLOOKUP($C21,$C$22:$Y$40,23,FALSE) -> 40
C22: No Frame | D22: 0 | E22: 0 | F22: 0 | G22: 0 | H22: 0 | I22: 0 | J22: 0 | K22: 0 | L22: 0 | M22: =L22*(IF($E$4="NA6",54000,59500)) -> 0 | N22: 0 | O22: 0 | P22: 0 | Q22: 0 | R22: 0 | S22: 0 | T22: 0 | U22: 0 | V22: 0 | W22: 0 | X22: 0 | Y22: 0
C23: 1520T(NA06) | D23: 0.316 | E23: =0.316*65000 -> 20540 | F23: 0.3986 | G23: =0.399*65000 -> 25935 | H23: 0.12 | I23: 7000 | J23: 0 | K23: 0 | L23: 0 | M23: =L23*(IF($E$4="NA6",54000,59500)) -> 0 | N23: 84 | O23: 136 | P23: 136 | Q23: 0 | R23: 35 | S23: 20 | T23: 0 | U23: 20 | V23: 0 | W23: 0 | X23: 20 | Y23: 20
C24: 1520T(NA20) | D24: 0.316 | E24: =0.316*70500 -> 22278 | F24: 0.3986 | G24: =0.399*70500 -> 28129.5 | H24: 0.12 | I24: 7000 | J24: 0 | K24: 0 | L24: 0 | M24: =L24*(IF($E$4="NA6",54000,59500)) -> 0 | N24: 84 | O24: 136 | P24: 136 | Q24: 0 | R24: 35 | S24: 20 | T24: 0 | U24: 20 | V24: 0 | W24: 0 | X24: 20 | Y24: 20
C25: 1540T(NA06) | D25: 0.711 | E25: =0.711*65000 -> 46215 | F25: 0.539 | G25: =0.539*65000 -> 35035 | H25: 0.123886 | I25: 7000 | J25: 0 | K25: 0 | L25: 0 | M25: =L25*(IF($E$4="NA6",54000,59500)) -> 0 | N25: 115 | O25: 198 | P25: 198 | Q25: 0 | R25: 60 | S25: 40 | T25: 0 | U25: 40 | V25: 0 | W25: 0 | X25: 40 | Y25: 40
C26: 1540T(NA20) | D26: 0.711 | E26: =0.711*70500 -> 50125.5 | F26: 0.539 | G26: =0.539*70500 -> 37999.5 | H26: 0.123886 | I26: 7000 | J26: 0 | K26: 0 | L26: 0 | M26: =L26*(IF($E$4="NA6",54000,59500)) -> 0 | N26: 115 | O26: 198 | P26: 198 | Q26: 0 | R26: 60 | S26: 40 | T26: 0 | U26: 40 | V26: 0 | W26: 0 | X26: 40 | Y26: 40
C27: 2540Y(NA06) | D27: =0.647+0.354+0.168*2 -> 1.337 | E27: =(0.647+0.354)*65000+7000*2 -> 79065 | F27: =0.392+0.521+0.168*2 -> 1.249 | G27: =(0.392+0.521)*65000+7000*2 -> 73345 | H27: 0.13427 | I27: =12/6.3*1.16*14700 -> 32480 | J27: 0.035 | K27: 4000 | L27: 0.179 | M27: =0.179*65000 -> 11635 | N27: 95 | O27: 244 | P27: 201 | Q27: 14 | R27: 84 | S27: 84 | T27: 26 | U27: 40 | V27: 60 | W27: 75 | X27: 56 | Y27: 34
C28: 2540Y(NA20) | D28: =0.647+0.354+0.168*2 -> 1.337 | E28: =(0.647+0.354)*70500+7000*2 -> 84570.5 | F28: =0.392+0.521+0.168*2 -> 1.249 | G28: =(0.392+0.521)*70500+7000*2 -> 78366.5 | H28: 0.13427 | I28: =12/6.3*1.16*14700 -> 32480 | J28: 0.035 | K28: 4000 | L28: 0.179 | M28: =0.179*70500 -> 12619.5 | N28: 95 | O28: 244 | P28: 201 | Q28: 14 | R28: 84 | S28: 84 | T28: 26 | U28: 40 | V28: 60 | W28: 75 | X28: 56 | Y28: 34
C29: 5060Y(NA06) | D29: =1.083+0.354+0.168*2 -> 1.773 | E29: =(1.083+0.354)*85000+7000*2 -> 136145 | F29: =0.571+0.521+0.168*2 -> 1.428 | G29: =(0.571+0.52)*85000+7000*2 -> 106735 | H29: 0.42476 | I29: =2.8*1.16*14700 -> 47745.6 | J29: 0.056628 | K29: =5/6.3*1.16*14700 -> 13533.333 | L29: 0.179 | M29: =0.179*65000 -> 11635 | N29: 140 | O29: 334 | P29: 240 | Q29: 14 | R29: 58 | S29: 58 | T29: 52 | U29: 67 | V29: 28 | W29: 58 | X29: 82 | Y29: 34
C30: 5060Y(NA20) | D30: =1.083+0.354+0.168*2 -> 1.773 | E30: =(1.083+0.354)*85000+7000*2 -> 136145 | F30: =0.571+0.521+0.168*2 -> 1.428 | G30: =(0.571+0.52)*85000+7000*2 -> 106735 | H30: 0.42476 | I30: =2.8*1.16*14700 -> 47745.6 | J30: 0.056628 | K30: =5/6.3*1.16*14700 -> 13533.333 | L30: 0.179 | M30: =0.179*70500 -> 12619.5 | N30: 140 | O30: 334 | P30: 240 | Q30: 14 | R30: 58 | S30: 58 | T30: 52 | U30: 67 | V30: 28 | W30: 58 | X30: 82 | Y30: 34
C31: 5060N(NA06) | D31: 1.61207 | E31: =IF($E$4="NA6",154.6/6,183.97/6)*1.16*3570 -> 126976.09 | F31: 1.2431 | G31: =IF($E$4="NA6",119.15/6,137.78/6)*1.16*3570 -> 95095.756 | H31: 0.21 | I31: =14.15*1.16*3570 -> 58597.98 | J31: 0.04 | K31: =4.3*1.16*3570 -> 17807.16 | L31: 0.17758621 | M31: =17.25/6*1.16*3570 -> 11905.95 | N31: 140 | O31: 334 | P31: 240 | Q31: 14 | R31: 80 | S31: 80 | T31: 0 | U31: 80 | V31: 80 | W31: 80 | X31: 62 | Y31: 42
C32: 5060A(NA20) | D32: 1.9327586 | E32: =IF($E$4="NA6",223.3/6,265.83/6)*1.16*3570 -> 183475.87 | F32: 1.5689655 | G32: =IF($E$4="NA6",193.45/6,223.7/6)*1.16*3570 -> 154397.74 | H32: 0.21 | I32: =14.15*1.16*3570 -> 58597.98 | J32: 0.04 | K32: =4.3*1.16*3570 -> 17807.16 | L32: 0.17758621 | M32: =19.95/6*1.16*3570 -> 13769.49 | N32: 140 | O32: 334 | P32: 240 | Q32: 14 | R32: 80 | S32: 80 | T32: 0 | U32: 80 | V32: 80 | W32: 80 | X32: 62 | Y32: 42
C33: 2550T(304) | D33: 4.969 | E33: 182255 | F33: 4.225 | G33: 150824 | H33: 0.772 | I33: 31390 | J33: 0.062 | K33: 3719 | L33: 0 | M33: 0 | N33: 0 | O33: 0 | P33: 0 | Q33: 0 | R33: 50 | S33: 50 | T33: 0 | U33: 50 | V33: 0 | W33: 0 | X33: 50 | Y33: 50
C34: 2550T(316) | D34: 5.081 | E34: 271704 | F34: 4.317 | G34: 224300 | H34: 0.792 | I34: 47203 | J34: 0.064 | K34: 3814 | L34: 0 | M34: 0 | N34: 0 | O34: 0 | P34: 0 | Q34: 0 | R34: 50 | S34: 50 | T34: 0 | U34: 50 | V34: 0 | W34: 0 | X34: 50 | Y34: 50
C35: 5070T(304) | D35: 6.147 | E35: 232434 | F35: 5.005 | G35: 182531 | H35: 1.914 | I35: 77809 | J35: 0.094 | K35: 3805 | L35: 0 | M35: 0 | N35: 0 | O35: 0 | P35: 0 | Q35: 0 | R35: 70 | S35: 50 | T35: 0 | U35: 70 | V35: 0 | W35: 0 | X35: 70 | Y35: 50
C36: 5070T(316) | D36: 6.291 | E36: 347439 | F36: 5.117 | G36: 271980 | H36: 1.963 | I36: 117007 | J36: 0.096 | K36: 5722 | L36: 0 | M36: 0 | N36: 0 | O36: 0 | P36: 0 | Q36: 0 | R36: 70 | S36: 50 | T36: 0 | U36: 70 | V36: 0 | W36: 0 | X36: 70 | Y36: 50
C37: 2540A(304) | D37: 2.074 | E37: 745100 | F37: 1.897 | G37: 792400 | H37: 0.31 | I37: 740100 | J37: 0.094 | K37: 176300 | L37: 0 | M37: 0 | N37: 0 | O37: 0 | P37: 0 | Q37: 0 | R37: 60 | S37: 60 | T37: 0 | U37: 40 | V37: 0 | W37: 0 | X37: 60 | Y37: 60
C38: 2540A(316) | D38: 2.074 | E38: 875200 | F38: 1.897 | G38: 922500 | H38: 0.31 | I38: 740100 | J38: 0.094 | K38: 176300 | L38: 0 | M38: 0 | N38: 0 | O38: 0 | P38: 0 | Q38: 0 | R38: 60 | S38: 60 | T38: 0 | U38: 40 | V38: 0 | W38: 0 | X38: 40 | Y38: 40
C39: 4550A(304) | D39: 2.63 | E39: 875200 | F39: 2.61 | G39: 863300 | H39: 0.494 | I39: 775300 | J39: 0.15 | K39: 176300 | L39: 0 | M39: 0 | N39: 0 | O39: 0 | P39: 0 | Q39: 0 | R39: 70 | S39: 70 | T39: 0 | U39: 50 | V39: 0 | W39: 0 | X39: 50 | Y39: 50
C40: 4550A(316) | D40: 2.63 | E40: 898800 | F40: 2.61 | G40: 887000 | H40: 0.494 | I40: 775300 | J40: 0.15 | K40: 176300 | L40: 0 | M40: 0 | N40: 0 | O40: 0 | P40: 0 | Q40: 0 | R40: 70 | S40: 70 | T40: 0 | U40: 50 | V40: 0 | W40: 0 | X40: 50 | Y40: 50
B41: Panel & Insulation | D41: Panel Insulation | H41: Profile Insulation | N41: Insert | P41: Gasket | R41: Outer Liner | V41: Inner Liner
C42: Type | D42: mmT | E42: Type | F42: kG/m3 | G42: Rp/kG | H42: Type | I42: mmT | J42: mmW(PP) | K42: mmW(CP) | L42: kG/m3 | M42: Rp/kG | N42: kG/m | O42: Rp/m | P42: kG/m | Q42: Rp/m | R42: Type | S42: kG/m3 | T42: Rp/kG | U42: mmT | V42: Type | W42: kG/m3 | X42: Rp/kG | Y42: mmT
C43: =+D4 -> 1540T(NA06) | D43: =VLOOKUP($C43,$C$44:$Q$62,2,FALSE) -> 15 | E43: =+L4 -> 0 | F43: =VLOOKUP($E43,$E$44:$Q$62,2,FALSE) -> 0 | G43: =VLOOKUP($E43,$E$44:$Q$62,3,FALSE) -> 0 | H43: =VLOOKUP($C43,$C$44:$Q$62,6,FALSE) -> PE3 | I43: =VLOOKUP($C43,$C$44:$Q$62,7,FALSE) -> 3 | J43: =VLOOKUP($C43,$C$44:$Q$62,8,FALSE) -> 80 | K43: =VLOOKUP($C43,$C$44:$Q$62,9,FALSE) -> 80 | L43: =VLOOKUP($C43,$C$44:$Q$62,10,FALSE) -> 24.506433 | M43: =VLOOKUP($C43,$C$44:$Q$62,11,FALSE) -> 132531.77 | N43: =VLOOKUP($C43,$C$44:$Q$62,12,FALSE) -> 0 | O43: =VLOOKUP($C43,$C$44:$Q$62,13,FALSE) -> 0 | P43: =VLOOKUP($C43,$C$44:$Q$62,14,FALSE) -> 0.00139 | Q43: =VLOOKUP($C43,$C$44:$Q$62,15,FALSE) -> 2116.6133 | R43: =+G4 -> GI | S43: =VLOOKUP($R43,$R$44:$U$62,2,FALSE) -> 8030 | T43: =VLOOKUP($R43,$R$44:$U$62,3,FALSE) -> 22500 | U43: =IF(H4>=0,(VLOOKUP($R43,$R$44:$U$62,4,FALSE)),H4) -> 0.4 | V43: =+I4 -> 0 | W43: =VLOOKUP($V43,$V$44:$Y$62,2,FALSE) -> 0 | X43: =VLOOKUP($V43,$V$44:$Y$62,3,FALSE) -> 0 | Y43: =VLOOKUP($V43,$V$44:$Y$62,4,FALSE) -> 0
C44: No Frame | D44: 0 | E44: 0 | F44: 0 | G44: 0 | H44: 0 | I44: 0 | J44: 0 | K44: 0 | L44: 0 | M44: 0 | N44: 0 | O44: 0 | P44: 0 | Q44: 0 | R44: 0 | S44: 0 | T44: 0 | U44: 0 | V44: 0 | W44: 0 | X44: 0 | Y44: 0
C45: 1520T(NA06) | D45: =IF(E$56="PE",10,15) -> 15 | E45: PE | F45: 24.506433 | G45: 132531.77 | H45: PE3 | I45: 3 | J45: 30 | K45: =15+20+15 -> 50 | L45: 24.506433 | M45: 132531.77 | N45: 0 | O45: 0 | P45: 0.00139 | Q45: 2116.6133 | R45: 0 | S45: 0 | T45: 0 | U45: 0 | V45: 0 | W45: 0 | X45: 0 | Y45: 0
C46: 1520T(NA20) | D46: =IF(E$56="PE",10,15) -> 15 | E46: B2 | F46: 48 | G46: 55000 | H46: PE3 | I46: 3 | J46: 30 | K46: =15+20+15 -> 50 | L46: 24.506433 | M46: 132531.77 | N46: 0 | O46: 0 | P46: 0.00139 | Q46: 2116.6133 | R46: GI | S46: 8030 | T46: 22500 | U46: 0.4 | V46: GI | W46: 8030 | X46: 22500 | Y46: 0.4
C47: 1540T(NA06) | D47: =IF(E$56="PE",10,15) -> 15 | E47: B3 | F47: 48 | G47: 52000 | H47: PE3 | I47: 3 | J47: 80 | K47: =40+20+20 -> 80 | L47: 24.506433 | M47: 132531.77 | N47: 0 | O47: 0 | P47: 0.00139 | Q47: 2116.6133 | R47: CB | S47: 8360 | T47: 30500 | U47: 0.45 | V47: CB | W47: 8360 | X47: 30200 | Y47: 0.45
C48: 1540T(NA20) | D48: =IF(E$56="PE",10,15) -> 15 | E48: MF60 | F48: 60 | G48: =134.87*14500 -> 1955615 | H48: PE3 | I48: 3 | J48: 80 | K48: =40+20+20 -> 80 | L48: 24.506433 | M48: 132531.77 | N48: 0 | O48: 0 | P48: 0.00139 | Q48: 2116.6133 | R48: FO | S48: 1400 | T48: 37250 | U48: 0.7 | V48: FO | W48: 1400 | X48: 37250 | Y48: 0.7
C49: 2540Y(NA06) | D49: 24 | E49: MF80 | F49: 80 | G49: =177.26*14500 -> 2570270 | H49: TB | I49: 0 | J49: 0 | K49: 0 | L49: 0 | M49: 0 | N49: 0.04 | O49: 4275 | P49: 0.06 | Q49: 6935 | R49: SUS304 | S49: 7800 | T49: 65000 | U49: 0.5 | V49: SUS304 | W49: 7800 | X49: 65000 | Y49: 0.5
C50: 2540Y(NA20) | D50: 24 | E50: MF100 | F50: 100 | G50: =223.51*14500 -> 3240895 | H50: TB | I50: 0 | J50: 0 | K50: 0 | L50: 0 | M50: 0 | N50: 0.04 | O50: 4275 | P50: 0.06 | Q50: 6935 | R50: SUS316L | S50: 8000 | T50: 80000 | U50: 0.5 | V50: SUS316L | W50: 8000 | X50: 80000 | Y50: 0.5
C51: 5060Y(NA06) | D51: 47 | H51: TB | I51: 0 | J51: 0 | K51: 0 | L51: 0 | M51: 0 | N51: 0.04 | O51: 4275 | P51: 0.06 | Q51: 6935 | R51: Copper | S51: 8900 | T51: 207000 | U51: 0.5 | V51: Copper | W51: 8900 | X51: 207000 | Y51: 0.5
C52: 5060Y(NA20) | D52: 47 | H52: TB | I52: 0 | J52: 0 | K52: 0 | L52: 0 | M52: 0 | N52: 0.04 | O52: 4275 | P52: 0.06 | Q52: 6935
C53: 5060N(NA06) | D53: 50 | H53: PE3 | I53: 3 | J53: 120 | K53: =20+40+20 -> 80 | L53: 24.506433 | M53: 132531.77 | N53: 0 | O53: 0 | P53: 0.00139 | Q53: 2116.6133
C54: 5060A(NA20) | D54: 50 | H54: TB | I54: 0 | J54: 0 | K54: 0 | L54: 0 | M54: 0 | N54: 0 | O54: 0 | P54: 0.00139 | Q54: 2116.6133
C55: 2550T(304) | D55: 24 | H55: PE5 | I55: 5 | J55: 90 | K55: 90 | L55: 24.506433 | M55: 132531.77 | N55: 0 | O55: 0 | P55: 0.00139 | Q55: 2116.6133
C56: 2550T(316) | D56: 24 | H56: PE5 | I56: 5 | J56: 90 | K56: 90 | L56: 24.506433 | M56: 132531.77 | N56: 0 | O56: 0 | P56: 0.00139 | Q56: 2116.6133
C57: 5070T(304) | D57: 47 | H57: PE5 | I57: 5 | J57: 80 | K57: 90 | L57: 24.506433 | M57: 132531.77 | N57: 0 | O57: 0 | P57: 0.00139 | Q57: 2116.6133
C58: 5070T(316) | D58: 47 | H58: PE5 | I58: 5 | J58: 80 | K58: 90 | L58: 24.506433 | M58: 132531.77 | N58: 0 | O58: 0 | P58: 0.00139 | Q58: 2116.6133
C59: 2540A(304) | D59: 25 | H59: PE5 | I59: 5 | J59: 64 | K59: 80 | L59: 24.506433 | M59: 132531.77 | N59: 0 | O59: 0 | P59: 0.00139 | Q59: 2116.6133
C60: 2540A(316) | D60: 25 | H60: PE5 | I60: 5 | J60: 64 | K60: 80 | L60: 24.506433 | M60: 132531.77 | N60: 0 | O60: 0 | P60: 0.00139 | Q60: 2116.6133
C61: 4550A(304) | D61: 45 | H61: PE5 | I61: 5 | J61: 40 | K61: 90 | L61: 24.506433 | M61: 132531.77 | N61: 0 | O61: 0 | P61: 0.00139 | Q61: 2116.6133
C62: 4550A(316) | D62: 45 | H62: PE5 | I62: 5 | J62: 40 | K62: 90 | L62: 24.506433 | M62: 132531.77 | N62: 0 | O62: 0 | P62: 0.00139 | Q62: 2116.6133
B63: ACC Coil & Header | D63: Coil ACC | G63: UB (ACC) | I63: AGC (ACC) | K63: Fin (ACC) | N63: Tube (ACC) | Q63: EP (ACC) | T63: Header (ACC)
C64: OD | D64: Type | E64: Sx | F64: Sy | G64: kG/pc | H64: Rp/pc | I64: kG/pc | J64: Rp/pc | K64: Type | L64: kG/m3 | M64: Rp/kG | N64: Type | O64: kG/m3 | P64: Rp/kG | Q64: Type | R64: kG/m3 | S64: Rp/kG | T64: Type | U64: kG/m3 | V64: Rp/kG
C65: =+I79 -> 9.525 | D65: =VLOOKUP($C65,$C66:$J71,2,FALSE) -> 3/8 | E65: =VLOOKUP($C65,$C66:$J71,3,FALSE) -> 21.65 | F65: =VLOOKUP($C65,$C66:$J71,4,FALSE) -> 25 | G65: =VLOOKUP($C65,$C66:$J71,5,FALSE) -> 0.0066573082 | H65: =VLOOKUP($C65,$C66:$J71,6,FALSE) -> 2250 | I65: =VLOOKUP($C65,$C66:$J71,7,FALSE) -> 0.000825 | J65: =VLOOKUP($C65,$C66:$J71,8,FALSE) -> 900 | K65: =+D6 -> Al1100 | L65: =VLOOKUP($K65,$K66:$M71,2,FALSE) -> 2700 | M65: =VLOOKUP($K65,$K66:$M71,3,FALSE) -> 70500 | N65: =+F6 -> Cu | O65: =VLOOKUP($N65,$N66:$P71,2,FALSE) -> 8900 | P65: =VLOOKUP($N65,$N66:$P71,3,FALSE) -> 207000 | Q65: =+H6 -> SGCC | R65: =VLOOKUP($Q65,$Q66:$S71,2,FALSE) -> 7860 | S65: =VLOOKUP($Q65,$Q66:$S71,3,FALSE) -> 22500 | T65: =+J6 -> Copper | U65: =VLOOKUP($T65,$T66:$V71,2,FALSE) -> 8900 | V65: =VLOOKUP($T65,$T66:$V71,3,FALSE) -> 207000
C66: 7 | D66: 2/7 | E66: 20 | F66: 22 | G66: 0.0038250095 | H66: 1165 | I66: 0 | J66: 0 | K66: Al1100 | L66: 2700 | M66: 70500 | N66: Al | O66: 2700 | P66: 70500 | Q66: Aluminium | R66: 2700 | S66: 70500 | T66: Copper | U66: 8900 | V66: 207000
C67: 9.525 | D67: 3/8 | E67: 21.65 | F67: 25 | G67: 0.0066573082 | H67: 2250 | I67: 0.000825 | J67: 900 | K67: BF1100 | L67: 2700 | M67: =60000+15805 -> 75805 | N67: Cu | O67: 8900 | P67: 207000 | Q67: Copper | R67: 8900 | S67: 207000 | T67: Sch40 | U67: 7860 | V67: 21500
C68: 12.7 | D68: 1/2 | E68: 27.5 | F68: 31.75 | G68: 0.013338433 | H68: 7200 | I68: 0.0012 | J68: 1100 | K68: GF1100 | L68: 2700 | M68: =60000+15805+4060 -> 79865 | N68: Cu-IG | O68: 8900 | P68: =178000+4000 -> 182000 | Q68: SGCC | R68: 7860 | S68: 22500 | T68: SUS304 | U68: 7800 | V68: 65000
C69: 15.875 | D69: 5/8 | E69: 33 | F69: 38.1 | G69: 0.020097476 | H69: =0.0201/0.0133*6800 -> 10276.692 | I69: 0.0017454545 | J69: 1450 | K69: Cu1020 | L69: 8900 | M69: 207000 | N69: Cu-HA | O69: 8900 | P69: =178000+4000-7975 -> 174025 | Q69: Brass | R69: 8400 | S69: =1875000/(1.2/1000*1.219*2.438*7800)+30510 -> 97914.364 | T69: SUS316L | U69: 8000 | V69: 80000
C70: 16 | D70: 0.625 | E70: 32.9 | F70: 38 | G70: 0.032057143 | H70: =60000*G70 -> 1923.4286 | I70: 0 | J70: 0 | K70: SUS304 | L70: 7800 | M70: 65000 | N70: SUS304 | O70: 7800 | P70: 65000 | Q70: SUS304 | R70: 7800 | S70: 65000
K71: SUS316L | L71: 8000 | M71: 80000 | N71: SUS316L | O71: 8000 | P71: 80000 | Q71: SUS316L | R71: 8000 | S71: 80000
C72: SCU | D72: kBH | E72: KW | F72: CMH | G72: ESP | H72: Skid | I72: H | J72: W | K72: D | L72: Frame | M72: Ref | N72: Fan | O72: N(Fan) | AA72: =+AA$2 -> SCU75M1 | AC72: =+AC$2 -> SCU75M1 | AD72: =+AD$2 -> SCU100M1 | AE72: =+AE$2 -> SCU125M1 | AF72: =+AF$2 -> SCU150M1
B73: =C$72&D73&"M1" -> SCU75M1 | C73: 1 | D73: =VLOOKUP($C73,$C74:$Z77,2,FALSE) -> 75 | E73: =VLOOKUP($C73,$C74:$Z77,3,FALSE) -> 22 | F73: =VLOOKUP($C73,$C74:$Z77,4,FALSE) -> 11350 | G73: =VLOOKUP($C73,$C74:$Z77,5,FALSE) -> 32.4 | H73: =VLOOKUP($C73,$C74:$Z77,6,FALSE) -> 0 | I73: =VLOOKUP($C73,$C74:$Z77,7,FALSE) -> 950 | J73: =VLOOKUP($C73,$C74:$Z77,8,FALSE) -> 875 | K73: =VLOOKUP($C73,$C74:$Z77,9,FALSE) -> 1188 | L73: =+D4 -> 1540T(NA06) | M73: X407 | N73: =VLOOKUP($C73,$C74:$Z77,12,FALSE) -> 630 | O73: =VLOOKUP($C73,$C74:$Z77,13,FALSE) -> 1 | AA73: 1 | AC73: 1 | AD73: 1 | AE73: 1 | AF73: 1
B74: =C$72&D74&"M1" -> SCU75M1 | C74: =+AA74 -> 1 | D74: 75 | E74: =ROUND(D74/3.412,0) -> 22 | F74: 11350 | G74: =+G80+15 -> 32.4 | H74: 0 | I74: 950 | J74: 875 | K74: 1188 | L74: =+L$73 -> 1540T(NA06) | M74: =M$73 -> X407 | N74: 630 | O74: 1 | AA74: 1 | AC74: 1
B75: =C$72&D75&"M1" -> SCU100M1 | C75: =+AA75 -> 0 | D75: 100 | E75: =ROUND(D75/3.412,0) -> 29 | F75: 11100 | G75: =+G81+15 -> 40.5 | H75: 0 | I75: 950 | J75: 875 | K75: 1188 | L75: =+L$73 -> 1540T(NA06) | M75: =M$73 -> X407 | N75: 630 | O75: 1 | AD75: 1
B76: =C$72&D76&"M1" -> SCU125M1 | C76: =+AA76 -> 0 | D76: 125 | E76: =ROUND(D76/3.412,0) -> 37 | F76: 14200 | G76: =+G82+15 -> 54 | H76: 0 | I76: 950 | J76: 875 | K76: 1188 | L76: =+L$73 -> 1540T(NA06) | M76: =M$73 -> X407 | N76: 710 | O76: 1 | AE76: 1
B77: =C$72&D77&"M1" -> SCU150M1 | C77: =+AA77 -> 0 | D77: 150 | E77: =ROUND(D77/3.412,0) -> 44 | F77: 14800 | G77: =+G83+15 -> 42.2 | H77: 0 | I77: 950 | J77: 1077 | K77: 1140 | L77: =+L$73 -> 1540T(NA06) | M77: =M$73 -> X407 | N77: 710 | O77: 1 | AF77: 1
C78: SCU | D78: kBtu/h | E78: kW | F78: cfm | G78: PD | H78: Type | I78: OD | J78: Row | K78: FPI | L78: TH | M78: FL | N78: C | O78: FW | P78: FH | Q78: Hdr | S78: Suction | U78: Discharge | W78: Liquid | Y78: RC | AA78: =+AA$2 -> SCU75M1 | AC78: =+AC$2 -> SCU75M1 | AD78: =+AD$2 -> SCU100M1 | AE78: =+AE$2 -> SCU125M1 | AF78: =+AF$2 -> SCU150M1
B79: =C$78&"-"&H79&"M1" -> SCU-ACC75M1 | C79: =+AA79 -> 2 | D79: =VLOOKUP($C79,$C80:$Z83,2,FALSE) -> 75 | E79: =VLOOKUP($C79,$C80:$Z83,3,FALSE) -> 22 | F79: =VLOOKUP($C79,$C80:$Z83,4,FALSE) -> 11350 | G79: =VLOOKUP($C79,$C80:$Z83,5,FALSE) -> 17.4 | H79: =VLOOKUP($C79,$C80:$Z83,6,FALSE) -> ACC75 | I79: =VLOOKUP($C79,$C80:$Z83,7,FALSE) -> 9.525 | J79: =VLOOKUP($C79,$C80:$Z83,8,FALSE) -> 2 | K79: =VLOOKUP($C79,$C80:$Z83,9,FALSE) -> 10 | L79: =VLOOKUP($C79,$C80:$Z83,10,FALSE) -> 36 | M79: =VLOOKUP($C79,$C80:$Z83,11,FALSE) -> 965 | N79: =VLOOKUP($C79,$C80:$Z83,12,FALSE) -> 3 | O79: =VLOOKUP($C79,$C80:$Z83,13,FALSE) -> 43.3 | P79: =VLOOKUP($C79,$C80:$Z83,14,FALSE) -> 900 | Q79: =VLOOKUP($C79,$C80:$Z83,15,FALSE) -> 0.625 | R79: =VLOOKUP($C79,$C80:$Z83,16,FALSE) -> 0.8 | S79: =VLOOKUP($C79,$C80:$Z83,17,FALSE) -> 1.125 | T79: =VLOOKUP($C79,$C80:$Z83,18,FALSE) -> 1.2 | U79: =VLOOKUP($C79,$C80:$Z83,17,FALSE) -> 1.125 | V79: =VLOOKUP($C79,$C80:$Z83,18,FALSE) -> 1.2 | W79: =VLOOKUP($C79,$C80:$Z83,17,FALSE) -> 1.125 | X79: =VLOOKUP($C79,$C80:$Z83,18,FALSE) -> 1.2 | Y79: =VLOOKUP($C79,$C80:$Z83,19,FALSE) -> 0.875 | AA79: 2 | AC79: 2 | AD79: 2 | AE79: 2 | AF79: 2
B80: =C$78&"-"&H80&"M1" -> SCU-ACC75M1 | C80: =+AA80 -> 2 | D80: 75 | E80: =ROUND(D80/3.412,0) -> 22 | F80: 11350 | G80: 17.4 | H80: ACC75 | I80: =3/8*25.4 -> 9.525 | J80: 2 | K80: 10 | L80: 36 | M80: 965 | N80: 3 | O80: =+J80*21.65 -> 43.3 | P80: =+L80*25 -> 900 | Q80: 0.625 | R80: 0.8 | S80: 1.125 | T80: 1.2 | U80: 0.875 | V80: 0.9 | W80: 0.5 | X80: 0.8 | Y80: 1 | AA80: 2 | AC80: 2
B81: =C$78&"-"&H81&"M1" -> SCU-ACC100M1 | C81: =+AA81 -> 0 | D81: 100 | E81: =ROUND(D81/3.412,0) -> 29 | F81: 11100 | G81: 25.5 | H81: ACC100 | I81: =3/8*25.4 -> 9.525 | J81: 2 | K81: 14 | L81: 36 | M81: 965 | N81: 3 | O81: =+J81*21.65 -> 43.3 | P81: =+L81*25 -> 900 | Q81: 0.625 | R81: 0.8 | S81: 1.375 | T81: 1.2 | U81: 0.875 | V81: 0.9 | W81: 0.625 | X81: 0.8 | Y81: 1 | AD81: 2
B82: =C$78&"-"&H82&"M1" -> SCU-ACC125M1 | C82: =+AA82 -> 0 | D82: 125 | E82: =ROUND(D82/3.412,0) -> 37 | F82: 14200 | G82: 39 | H82: ACC125 | I82: =3/8*25.4 -> 9.525 | J82: 2 | K82: 14 | L82: 36 | M82: 965 | N82: 4 | O82: =+J82*21.65 -> 43.3 | P82: =+L82*25 -> 900 | Q82: 0.625 | R82: 0.8 | S82: 1.375 | T82: 1.2 | U82: 0.875 | V82: 0.9 | W82: 0.75 | X82: 0.8 | Y82: 1 | AE82: 2
B83: =C$78&"-"&H83&"M1" -> SCU-ACC150M1 | C83: =+AA83 -> 0 | D83: 150 | E83: =ROUND(D83/3.412,0) -> 44 | F83: 14800 | G83: 27.2 | H83: ACC150 | I83: =3/8*25.4 -> 9.525 | J83: 2 | K83: 16 | L83: 36 | M83: 1377 | N83: 6 | O83: =+J83*21.65 -> 43.3 | P83: =+L83*25 -> 900 | Q83: 0.75 | R83: 0.8 | S83: 1.375 | T83: 1.2 | U83: 0.875 | V83: 0.9 | W83: 0.625 | X83: 0.8 | Y83: 1 | AF83: 2
B84: Item | C84: Part Master Item Description | D84: Layout | G84: Adj | H84: Size | M84: Usage | R84: Opt | S84: Gross | T84: Unit Cost | X84: Wt(kG) | Z84: Total ($) | AA84: =+AA$2 -> SCU75M1 | AC84: =+AC$2 -> SCU75M1 | AD84: =+AD$2 -> SCU100M1 | AE84: =+AE$2 -> SCU125M1 | AF84: =+AF$2 -> SCU150M1 | AJ84: U/W | AL84: U/C
B85: CASING: Skid Assy | C85: H x W x D | D85: =+I$73 -> 950 | E85: =+J$73 -> 875 | F85: =+K$73 -> 1188 | H85: Uom | I85: Ø | J85: T | K85: L | L85: W | M85: CF | N85: V/A/L | O85: n | P85: UF | Q85: WF | R85: 1 | S85: Qty | T85: Fx | U85: U/P | V85: EF | W85: LF | Y85: =SUM(Y86:Y89) -> 11.785174 | Z85: =SUM(Z86:Z89) -> 30.016115 | AA85: =+AA$2 -> SCU75M1 | AC85: =+AC$2 -> SCU75M1 | AD85: =+AD$2 -> SCU100M1 | AE85: =+AE$2 -> SCU125M1 | AF85: =+AF$2 -> SCU150M1 | AK85: =SUM(AJ86:AJ89) -> 11.785174 | AM85: =SUM(AL86:AL89) -> 30.016115
B86: Leg Assy: Leg, L/R (W) | C86: =+O$4 -> SGCC | E86: =+E85 -> 875 | F86: 50 | H86: kG | J86: 1.5 | K86: =+E86+50*2 -> 975 | L86: =15+25+F86+25+15 -> 130 | M86: =+E$11 -> 8030 | N86: =IF(I86>0,22/28*((I86/1000)^2-(I86/1000-2*J86/1000)^2)*K86/1000,IF(J86>0,J86/1000*K86/1000*L86/1000, IF(K86>0,K86/1000*L86/1000, IF(L86=0,1,L86/1000)))) -> 0.000190125 | O86: 2 | P86: =M86*N86*O86 -> 3.0534075 | Q86: 1.2 | R86: =+R$85 -> 1 | S86: =P86*AA86*Q86*R86 -> 7.328178 | T86: Rp | U86: =+F$11 -> 22500 | V86: =1/VLOOKUP(T86,Y$12:Z$18,2,FALSE) -> 6.8240753e-05 | W86: 1 | X86: 1 | Y86: =+P86*R86*AA86*X86 -> 6.106815 | Z86: =S86*U86*V86*W86 -> 11.251809 | AA86: 2 | AC86: 2 | AD86: 2 | AE86: 2 | AF86: 2 | AJ86: =+Y86 -> 6.106815 | AL86: =+Z86 -> 11.251809
B87: - Panel Painting | C87: =IF(N$4=1,"Panel Powder Coating", "Panel No Coating") -> Panel Powder Coating | H87: m2 | K87: =+K86 -> 975 | L87: =+L86 -> 130 | M87: 2 | N87: =IF(I87>0,22/28*((I87/1000)^2-(I87/1000-2*J87/1000)^2)*K87/1000,IF(J87>0,J87/1000*K87/1000*L87/1000, IF(K87>0,K87/1000*L87/1000, IF(L87=0,1,L87/1000)))) -> 0.12675 | O87: =+O86 -> 2 | P87: =M87*N87*O87 -> 0.507 | Q87: 1.1 | R87: =+R$85 -> 1 | S87: =P87*AA87*Q87*R87 -> 1.1154 | T87: Rp | U87: =+Q$11 -> 65000 | V87: =1/VLOOKUP(T87,Y$12:Z$18,2,FALSE) -> 6.8240753e-05 | W87: 1 | X87: =+P$11 -> 0.25 | Y87: =+P87*R87*AA87*X87 -> 0.2535 | Z87: =S87*U87*V87*W87 -> 4.9475229 | AA87: =+AA86 -> 2 | AC87: =+AC86 -> 2 | AD87: =+AD86 -> 2 | AE87: =+AE86 -> 2 | AF87: =+AF86 -> 2 | AJ87: =+Y87 -> 0.2535 | AL87: =+Z87 -> 4.9475229
B88: Leg Assy: Leg Center | C88: =+O$4 -> SGCC | E88: =+F85 -> 1188 | F88: 50 | H88: kG | J88: 1.5 | K88: =+E88*0.7 -> 831.6 | L88: =15+25+F88+25+15 -> 130 | M88: =+E$11 -> 8030 | N88: =IF(I88>0,22/28*((I88/1000)^2-(I88/1000-2*J88/1000)^2)*K88/1000,IF(J88>0,J88/1000*K88/1000*L88/1000, IF(K88>0,K88/1000*L88/1000, IF(L88=0,1,L88/1000)))) -> 0.000162162 | O88: 2 | P88: =M88*N88*O88 -> 2.6043217 | Q88: 1.2 | R88: =+R$85 -> 1 | S88: =P88*AA88*Q88*R88 -> 6.2503721 | T88: Rp | U88: =+F$11 -> 22500 | V88: =1/VLOOKUP(T88,Y$12:Z$18,2,FALSE) -> 6.8240753e-05 | W88: 1 | X88: 1 | Y88: =+P88*R88*AA88*X88 -> 5.2086434 | Z88: =S88*U88*V88*W88 -> 9.5969273 | AA88: 2 | AC88: 2 | AD88: 2 | AE88: 2 | AF88: 2 | AJ88: =+Y88 -> 5.2086434 | AL88: =+Z88 -> 9.5969273
B89: - Panel Painting | C89: =IF(N$4=1,"Panel Powder Coating", "Panel No Coating") -> Panel Powder Coating | H89: m2 | K89: =+K88 -> 831.6 | L89: =+L88 -> 130 | M89: 2 | N89: =IF(I89>0,22/28*((I89/1000)^2-(I89/1000-2*J89/1000)^2)*K89/1000,IF(J89>0,J89/1000*K89/1000*L89/1000, IF(K89>0,K89/1000*L89/1000, IF(L89=0,1,L89/1000)))) -> 0.108108 | O89: =+O88 -> 2 | P89: =M89*N89*O89 -> 0.432432 | Q89: 1.1 | R89: =+R$85 -> 1 | S89: =P89*AA89*Q89*R89 -> 0.9513504 | T89: Rp | U89: =+Q$11 -> 65000 | V89: =1/VLOOKUP(T89,Y$12:Z$18,2,FALSE) -> 6.8240753e-05 | W89: 1 | X89: =+P$11 -> 0.25 | Y89: =+P89*R89*AA89*X89 -> 0.216216 | Z89: =S89*U89*V89*W89 -> 4.2198564 | AA89: =+AA88 -> 2 | AC89: =+AC88 -> 2 | AD89: =+AD88 -> 2 | AE89: =+AE88 -> 2 | AF89: =+AF88 -> 2 | AJ89: =+Y89 -> 0.216216 | AL89: =+Z89 -> 4.2198564
B90: CASING: Panel Assy | C90: H x W x D | D90: =+I$73 -> 950 | E90: =+J$73 -> 875 | F90: =+K$73 -> 1188 | H90: Uom | I90: Ø | J90: T | K90: L | L90: W | M90: CF | N90: V/A/L | O90: n | P90: UF | Q90: WF | R90: 1 | S90: Qty | T90: Fx | U90: U/P | V90: EF | W90: LF | Y90: =SUM(Y91:Y112) -> 43.167671 | Z90: =SUM(Z91:Z112) -> 116.97126 | AA90: =+AA$2 -> SCU75M1 | AC90: =+AC$2 -> SCU75M1 | AD90: =+AD$2 -> SCU100M1 | AE90: =+AE$2 -> SCU125M1 | AF90: =+AF$2 -> SCU150M1 | AK90: =SUM(AJ91:AJ112) -> 43.167671 | AM90: =SUM(AL91:AL112) -> 116.97126
B91: Panel Assy: Base Tray Panel 75/100/125/150 (W x D) | C91: =+G$4 -> GI | E91: =+E90-2*G91 -> 795 | F91: =+F90-G91*2 -> 1108 | G91: =+X$21 -> 40 | H91: kG | J91: 1.5 | K91: =E91+$D$43*2 -> 825 | L91: =F91+$D$43*2 -> 1138 | M91: =+S$43 -> 8030 | N91: =IF(I91>0,22/28*((I91/1000)^2-(I91/1000-2*J91/1000)^2)*K91/1000,IF(J91>0,J91/1000*K91/1000*L91/1000, IF(K91>0,K91/1000*L91/1000, IF(L91=0,1,L91/1000)))) -> 0.001408275 | O91: 1 | P91: =M91*N91*O91 -> 11.308448 | Q91: 1.2 | R91: =+R$90 -> 1 | S91: =P91*AA91*Q91*R91 -> 13.570138 | T91: Rp | U91: =+T$43 -> 22500 | V91: =1/VLOOKUP(T91,Y$12:Z$18,2,FALSE) -> 6.8240753e-05 | W91: 1 | X91: 1 | Y91: =+P91*R91*AA91*X91 -> 11.308448 | Z91: =S91*U91*V91*W91 -> 20.83582 | AA91: 1 | AC91: 1 | AD91: 1 | AE91: 1 | AF91: 1 | AJ91: =+Y91 -> 11.308448 | AL91: =+Z91 -> 20.83582
B92: - Panel Painting | C92: =IF(N$4=1,"Panel Powder Coating", "Panel No Coating") -> Panel Powder Coating | H92: m2 | K92: =+K91 -> 825 | L92: =+L91 -> 1138 | M92: 2 | N92: =IF(I92>0,22/28*((I92/1000)^2-(I92/1000-2*J92/1000)^2)*K92/1000,IF(J92>0,J92/1000*K92/1000*L92/1000, IF(K92>0,K92/1000*L92/1000, IF(L92=0,1,L92/1000)))) -> 0.93885 | O92: =+O91 -> 1 | P92: =M92*N92*O92 -> 1.8777 | Q92: 1.1 | R92: =+R$85 -> 1 | S92: =P92*AA92*Q92*R92 -> 2.06547 | T92: Rp | U92: =+Q$11 -> 65000 | V92: =1/VLOOKUP(T92,Y$12:Z$18,2,FALSE) -> 6.8240753e-05 | W92: 1 | X92: =+P$11 -> 0.25 | Y92: =+P92*R92*AA92*X92 -> 0.469425 | Z92: =S92*U92*V92*W92 -> 9.1616999 | AA92: =+AA91 -> 1 | AC92: =+AC91 -> 1 | AD92: =+AD91 -> 1 | AE92: =+AE91 -> 1 | AF92: =+AF91 -> 1 | AJ92: =+Y92 -> 0.469425 | AL92: =+Z92 -> 9.1616999
B93: Panel Assy: Top/Orifice Panel 75/100/125 (H x W) | C93: =+G$4 -> GI | E93: =+D90-G93*2 -> 870 | F93: =+E90-G93*2 -> 795 | G93: =+X$21 -> 40 | H93: kG | J93: 1.5 | K93: =E93+$D$43*2+20*2 -> 940 | L93: =F93+$D$43*2+20*2 -> 865 | M93: =+S$43 -> 8030 | N93: =IF(I93>0,22/28*((I93/1000)^2-(I93/1000-2*J93/1000)^2)*K93/1000,IF(J93>0,J93/1000*K93/1000*L93/1000, IF(K93>0,K93/1000*L93/1000, IF(L93=0,1,L93/1000)))) -> 0.00121965 | O93: 1 | P93: =M93*N93*O93 -> 9.7937895 | Q93: 1.2 | R93: =+R$90 -> 1 | S93: =P93*AA93*Q93*R93 -> 11.752547 | T93: Rp | U93: =+T$43 -> 22500 | V93: =1/VLOOKUP(T93,Y$12:Z$18,2,FALSE) -> 6.8240753e-05 | W93: 1 | X93: 1 | Y93: =+P93*R93*AA93*X93 -> 9.7937895 | Z93: =S93*U93*V93*W93 -> 18.04506 | AA93: 1 | AC93: 1 | AD93: 1 | AE93: 1 | AJ93: =+Y93 -> 9.7937895 | AL93: =+Z93 -> 18.04506
B94: - Panel Painting | C94: =IF(N$4=1,"Panel Powder Coating", "Panel No Coating") -> Panel Powder Coating | H94: m2 | K94: =+K93 -> 940 | L94: =+L93 -> 865 | M94: 2 | N94: =IF(I94>0,22/28*((I94/1000)^2-(I94/1000-2*J94/1000)^2)*K94/1000,IF(J94>0,J94/1000*K94/1000*L94/1000, IF(K94>0,K94/1000*L94/1000, IF(L94=0,1,L94/1000)))) -> 0.8131 | O94: =+O93 -> 1 | P94: =M94*N94*O94 -> 1.6262 | Q94: 1.1 | R94: =+R$85 -> 1 | S94: =P94*AA94*Q94*R94 -> 1.78882 | T94: Rp | U94: =+Q$11 -> 65000 | V94: =1/VLOOKUP(T94,Y$12:Z$18,2,FALSE) -> 6.8240753e-05 | W94: 1 | X94: =+P$11 -> 0.25 | Y94: =+P94*R94*AA94*X94 -> 0.40655 | Z94: =S94*U94*V94*W94 -> 7.9345776 | AA94: =+AA93 -> 1 | AC94: =+AC93 -> 1 | AD94: =+AD93 -> 1 | AE94: =+AE93 -> 1 | AJ94: =+Y94 -> 0.40655 | AL94: =+Z94 -> 7.9345776
B95: Panel Assy: Top/Orifice Panel 150 (D x W) | C95: =+G$4 -> GI | E95: =+F90-G95*2 -> 1108 | F95: =+E90-G95*2 -> 795 | G95: =+X$21 -> 40 | H95: kG | J95: 1.5 | K95: =E95+$D$43*2+20*2 -> 1178 | L95: =F95+$D$43*2+20*2 -> 865 | M95: =+S$43 -> 8030 | N95: =IF(I95>0,22/28*((I95/1000)^2-(I95/1000-2*J95/1000)^2)*K95/1000,IF(J95>0,J95/1000*K95/1000*L95/1000, IF(K95>0,K95/1000*L95/1000, IF(L95=0,1,L95/1000)))) -> 0.001528455 | O95: 1 | P95: =M95*N95*O95 -> 12.273494 | Q95: 1.2 | R95: =+R$90 -> 1 | S95: =P95*AA95*Q95*R95 -> 0 | T95: Rp | U95: =+T$43 -> 22500 | V95: =1/VLOOKUP(T95,Y$12:Z$18,2,FALSE) -> 6.8240753e-05 | W95: 1 | X95: 1 | Y95: =+P95*R95*AA95*X95 -> 0 | Z95: =S95*U95*V95*W95 -> 0 | AF95: 1 | AJ95: =+Y95 -> 0 | AL95: =+Z95 -> 0
B96: - Panel Painting | C96: =IF(N$4=1,"Panel Powder Coating", "Panel No Coating") -> Panel Powder Coating | H96: m2 | K96: =+K95 -> 1178 | L96: =+L95 -> 865 | M96: 2 | N96: =IF(I96>0,22/28*((I96/1000)^2-(I96/1000-2*J96/1000)^2)*K96/1000,IF(J96>0,J96/1000*K96/1000*L96/1000, IF(K96>0,K96/1000*L96/1000, IF(L96=0,1,L96/1000)))) -> 1.01897 | O96: =+O95 -> 1 | P96: =M96*N96*O96 -> 2.03794 | Q96: 1.1 | R96: =+R$85 -> 1 | S96: =P96*AA96*Q96*R96 -> 0 | T96: Rp | U96: =+Q$11 -> 65000 | V96: =1/VLOOKUP(T96,Y$12:Z$18,2,FALSE) -> 6.8240753e-05 | W96: 1 | X96: =+P$11 -> 0.25 | Y96: =+P96*R96*AA96*X96 -> 0 | Z96: =S96*U96*V96*W96 -> 0 | AF96: =+AF95 -> 1 | AJ96: =+Y96 -> 0 | AL96: =+Z96 -> 0
B97: Panel Assy: Top Baffle Panel 75/100/125 (W x 238) | C97: =+G$4 -> GI | E97: =+E90-G97*2 -> 795 | F97: 238 | G97: =+X$21 -> 40 | H97: kG | J97: 1 | K97: =E97+$D$43*2+20*2 -> 865 | L97: =F97+$D$43*2+20*2 -> 308 | M97: =+S$43 -> 8030 | N97: =IF(I97>0,22/28*((I97/1000)^2-(I97/1000-2*J97/1000)^2)*K97/1000,IF(J97>0,J97/1000*K97/1000*L97/1000, IF(K97>0,K97/1000*L97/1000, IF(L97=0,1,L97/1000)))) -> 0.00026642 | O97: 1 | P97: =M97*N97*O97 -> 2.1393526 | Q97: 1.2 | R97: =+R$90 -> 1 | S97: =P97*AA97*Q97*R97 -> 2.5672231 | T97: Rp | U97: =+T$43 -> 22500 | V97: =1/VLOOKUP(T97,Y$12:Z$18,2,FALSE) -> 6.8240753e-05 | W97: 1 | X97: 1 | Y97: =+P97*R97*AA97*X97 -> 2.1393526 | Z97: =S97*U97*V97*W97 -> 3.9417579 | AA97: 1 | AC97: 1 | AD97: 1 | AE97: 1 | AJ97: =+Y97 -> 2.1393526 | AL97: =+Z97 -> 3.9417579
B98: - Panel Painting | C98: =IF(N$4=1,"Powder Coating", "No Coating") -> Powder Coating | H98: m2 | K98: =+K97 -> 865 | L98: =+L97 -> 308 | M98: 2 | N98: =IF(I98>0,22/28*((I98/1000)^2-(I98/1000-2*J98/1000)^2)*K98/1000,IF(J98>0,J98/1000*K98/1000*L98/1000, IF(K98>0,K98/1000*L98/1000, IF(L98=0,1,L98/1000)))) -> 0.26642 | O98: =+O97 -> 1 | P98: =M98*N98*O98 -> 0.53284 | Q98: 1.1 | R98: =+R$90 -> 1 | S98: =P98*AA98*Q98*R98 -> 0.586124 | T98: Rp | U98: =+Q$11 -> 65000 | V98: =1/VLOOKUP(T98,Y$12:Z$18,2,FALSE) -> 6.8240753e-05 | W98: 1 | X98: =+P$11 -> 0.25 | Y98: =+P98*R98*AA98*X98 -> 0.13321 | Z98: =S98*U98*V98*W98 -> 2.5998403 | AA98: =+AA97 -> 1 | AC98: =+AC97 -> 1 | AD98: =+AD97 -> 1 | AE98: =+AE97 -> 1 | AJ98: =+Y98 -> 0.13321 | AL98: =+Z98 -> 2.5998403
B99: Panel Assy: Back Panel 75/100/125 (H x W) | C99: =+G$4 -> GI | E99: =+D90-G99*2 -> 870 | F99: =+E90-G99*2 -> 795 | G99: =+X$21 -> 40 | H99: kG | J99: 1 | K99: =E99+$D$43*2+20*2 -> 940 | L99: =F99+$D$43*2+20*2 -> 865 | M99: =+S$43 -> 8030 | N99: =IF(I99>0,22/28*((I99/1000)^2-(I99/1000-2*J99/1000)^2)*K99/1000,IF(J99>0,J99/1000*K99/1000*L99/1000, IF(K99>0,K99/1000*L99/1000, IF(L99=0,1,L99/1000)))) -> 0.0008131 | O99: 1 | P99: =M99*N99*O99 -> 6.529193 | Q99: 1.2 | R99: =+R$90 -> 1 | S99: =P99*AA99*Q99*R99 -> 7.8350316 | T99: Rp | U99: =+T$43 -> 22500 | V99: =1/VLOOKUP(T99,Y$12:Z$18,2,FALSE) -> 6.8240753e-05 | W99: 1 | X99: 1 | Y99: =+P99*R99*AA99*X99 -> 6.529193 | Z99: =S99*U99*V99*W99 -> 12.03004 | AA99: 1 | AC99: 1 | AD99: 1 | AE99: 1 | AJ99: =+Y99 -> 6.529193 | AL99: =+Z99 -> 12.03004
B100: - Panel Painting | C100: =IF(N$4=1,"Panel Powder Coating", "Panel No Coating") -> Panel Powder Coating | H100: m2 | K100: =+K99 -> 940 | L100: =+L99 -> 865 | M100: 2 | N100: =IF(I100>0,22/28*((I100/1000)^2-(I100/1000-2*J100/1000)^2)*K100/1000,IF(J100>0,J100/1000*K100/1000*L100/1000, IF(K100>0,K100/1000*L100/1000, IF(L100=0,1,L100/1000)))) -> 0.8131 | O100: =+O99 -> 1 | P100: =M100*N100*O100 -> 1.6262 | Q100: 1.1 | R100: =+R$85 -> 1 | S100: =P100*AA100*Q100*R100 -> 1.78882 | T100: Rp | U100: =+Q$11 -> 65000 | V100: =1/VLOOKUP(T100,Y$12:Z$18,2,FALSE) -> 6.8240753e-05 | W100: 1 | X100: =+P$11 -> 0.25 | Y100: =+P100*R100*AA100*X100 -> 0.40655 | Z100: =S100*U100*V100*W100 -> 7.9345776 | AA100: =+AA99 -> 1 | AC100: =+AC99 -> 1 | AD100: =+AD99 -> 1 | AE100: =+AE99 -> 1 | AJ100: =+Y100 -> 0.40655 | AL100: =+Z100 -> 7.9345776
...

Sheet AHU IU1
D1: H | E1: D | F1: W | K1: Profile | L1: Section No.
D2: 1420 | E2: 3250 | F2: 1930 | G2: =E2/1000*F2/1000 -> 6.2725 | H2: 110 | J2: DS | K2: 5060Y(NA06) | L2: 2
D3: =ROUND((D2-100)/305,0) -> 4 | F3: =ROUND((F2-100)/305,0) -> 6 | H3: 1453.66 | I3: RM
B4: NO | C4: DESCRIPTION | D4: Unit Costing
D5: Usage | F5: Price (Fcy) | H5: Factors | K5: Cost (US$)
D6: Uom | E6: Qty | F6: U/P(Fcy) | H6: EF | I6: LF | J6: WF | K6: U/C | L6: Total | M6: Sub Total | Y6: t | Z6: h | AA6: w | AB6: @ | AC6: kg | AD6: qty | AE6: kg total | AF6: rp | AG6: Material | AH6: Bending | AI6: Total
H7: 17500 | X7: W | Y7: 2 | Z7: =F2 -> 1930 | AA7: 250 | AB7: 7860 | AC7: =AB7*AA7/1000*Z7/1000*Y7/1000 -> 7.5849 | AD7: 2 | AE7: =AC7*AD7 -> 15.1698 | AF7: 21500 | AG7: =AE7*AF7 -> 326150.7 | AH7: =8*3000 -> 24000 | AI7: =AG7+AH7 -> 350150.7
B8: FRAME | P8: PROFILE TYPE | Q8: H | R8: D | S8: W | X8: D | Y8: 2 | Z8: =E2 -> 3250 | AA8: 250 | AB8: 7860 | AC8: =AB8*AA8/1000*Z8/1000*Y8/1000 -> 12.7725 | AD8: 2 | AE8: =AC8*AD8 -> 25.545 | AF8: 21500 | AG8: =AE8*AF8 -> 549217.5 | AH8: =3*3000 -> 9000 | AI8: =AG8+AH8 -> 558217.5
B9: 1 | C9: ="PENTAPOST DS" &$K$2& "H" -> PENTAPOST DS5060Y(NA06)H | D9: M | E9: =VLOOKUP($K$2,'AHU IU1'!$P$9:$S$26,2,0) -> 10.016 | F9: RP | G9: =VLOOKUP($K$2,Master!$O$4:$Y$21,3,0) -> 174015 | H9: =IF(F9="Rp",1/$H$7,1) -> 5.7142857e-05 | I9: 1 | J9: 1.05 | K9: =+G9*H9*I9*J9 -> 10.4409 | L9: 0 | N9: =VLOOKUP($K$2,Master!$O$4:$Y$21,2,0)*E9 -> 17.758368 | P9: 1520T(NA06) | Q9: =(('AHU IU1'!$D$2-(35*2))*4/1000)*'AHU IU1'!$L$2 -> 10.8 | R9: =(('AHU IU1'!$E$2-(35*2))*4/1000)*'AHU IU1'!$L$2 -> 25.44 | S9: =(('AHU IU1'!$F$2-(35*2))*4/1000)*'AHU IU1'!$L$2 -> 14.88 | U9: 17064 | V9: 21524.4 | X9: H | Y9: 2 | Z9: =D2 -> 1420 | AA9: 200 | AB9: 7860 | AC9: =AB9*AA9/1000*Z9/1000*Y9/1000 -> 4.46448 | AD9: 2 | AE9: =AC9*AD9 -> 8.92896 | AF9: 21500 | AG9: =AE9*AF9 -> 191972.64 | AH9: =3*3000 -> 9000 | AI9: =AG9+AH9 -> 200972.64
B10: 2 | C10: ="PENTAPOST DS" &$K$2& "D" -> PENTAPOST DS5060Y(NA06)D | D10: M | E10: =VLOOKUP($K$2,'AHU IU1'!$P$9:$S$26,3,0) -> 24.656 | F10: RP | G10: =G9 -> 174015 | H10: =IF(F10="Rp",1/$H$7,1) -> 5.7142857e-05 | I10: 1 | J10: 1.05 | K10: =+G10*H10*I10*J10 -> 10.4409 | L10: 0 | N10: =VLOOKUP($K$2,Master!$O$4:$Y$21,2,0)*E10 -> 43.715088 | P10: 1520T(NA20) | Q10: =(('AHU IU1'!$D$2-(35*2))*4/1000)*'AHU IU1'!$L$2 -> 10.8 | R10: =(('AHU IU1'!$E$2-(35*2))*4/1000)*'AHU IU1'!$L$2 -> 25.44 | S10: =(('AHU IU1'!$F$2-(35*2))*4/1000)*'AHU IU1'!$L$2 -> 14.88 | U10: 38394 | V10: 29106 | X10: Support Blower | Y10: 2 | Z10: =Z7 -> 1930 | AA10: 300 | AB10: 7860 | AC10: =AB10*AA10/1000*Z10/1000*Y10/1000 -> 9.10188 | AD10: 2 | AE10: =AC10*AD10 -> 18.20376 | AF10: 21500 | AG10: =AE10*AF10 -> 391380.84 | AH10: =6*3000 -> 18000 | AI10: =AG10+AH10 -> 409380.84
B11: 3 | C11: ="PENTAPOST DS" &$K$2& "W" -> PENTAPOST DS5060Y(NA06)W | D11: M | E11: =VLOOKUP($K$2,'AHU IU1'!$P$9:$S$26,4,0) -> 14.096 | F11: RP | G11: =G9 -> 174015 | H11: =IF(F11="Rp",1/$H$7,1) -> 5.7142857e-05 | I11: 1 | J11: 1.05 | K11: =+G11*H11*I11*J11 -> 10.4409 | L11: 0 | N11: =VLOOKUP($K$2,Master!$O$4:$Y$21,2,0)*E11 -> 24.992208 | P11: 1540T(NA06) | Q11: =(('AHU IU1'!$D$2-(59*2))*4/1000)*'AHU IU1'!$L$2 -> 10.416 | R11: =(('AHU IU1'!$E$2-(59*2))*4/1000)*'AHU IU1'!$L$2 -> 25.056 | S11: =(('AHU IU1'!$F$2-(59*2))*4/1000)*'AHU IU1'!$L$2 -> 14.496 | U11: 67054 | V11: 62302 | X11: Channel Atas | Y11: 1.5 | Z11: =Z8/2 -> 1625 | AA11: 250 | AB11: 7860 | AC11: =AB11*AA11/1000*Z11/1000*Y11/1000 -> 4.7896875 | AD11: 4 | AE11: =AC11*AD11 -> 19.15875 | AF11: 16000 | AG11: =AE11*AF11 -> 306540
B12: 4 | C12: ="CENTERPOST DS" &$K$2& "H" -> CENTERPOST DS5060Y(NA06)H | D12: M | E12: =((D2-(35*2))/1000)*2 -> 2.7 | F12: RP | G12: =VLOOKUP($K$2,Master!$O$4:$Y$21,5,0) -> 131975 | H12: =IF(F12="Rp",1/$H$7,1) -> 5.7142857e-05 | I12: 1 | J12: 1.05 | K12: =+G12*H12*I12*J12 -> 7.9185 | L12: 0 | N12: =VLOOKUP($K$2,Master!$O$4:$Y$21,4,0)*E12 -> 2.9511 | P12: 1540T(NA20) | Q12: =(('AHU IU1'!$D$2-(59*2))*4/1000)*'AHU IU1'!$L$2 -> 10.416 | R12: =(('AHU IU1'!$E$2-(59*2))*4/1000)*'AHU IU1'!$L$2 -> 25.056 | S12: =(('AHU IU1'!$F$2-(59*2))*4/1000)*'AHU IU1'!$L$2 -> 14.496 | U12: 90598 | V12: 71914 | X12: Support | Y12: 1.5 | Z12: =E2 -> 3250 | AA12: 200 | AB12: 7860 | AC12: =AB12*AA12/1000*Z12/1000*Y12/1000 -> 7.6635 | AD12: 4 | AE12: =AC12*AD12 -> 30.654 | AF12: 16000 | AG12: =AE12*AF12 -> 490464
B13: 5 | C13: ="CENTERPOST DS" &$K$2& "D" -> CENTERPOST DS5060Y(NA06)D | D13: M | E13: =((E2-(35*2))/1000)*1 -> 3.18 | F13: RP | G13: =G12 -> 131975 | H13: =IF(F13="Rp",1/$H$7,1) -> 5.7142857e-05 | I13: 1 | J13: 1.05 | K13: =+G13*H13*I13*J13 -> 7.9185 | L13: 0 | N13: =VLOOKUP($K$2,Master!$O$4:$Y$21,4,0)*E13 -> 3.47574 | P13: 2540Y(NA06) | Q13: =(('AHU IU1'!$D$2-(58*2))*4/1000)*'AHU IU1'!$L$2 -> 10.432 | R13: =(('AHU IU1'!$E$2-(58*2))*4/1000)*'AHU IU1'!$L$2 -> 25.072 | S13: =(('AHU IU1'!$F$2-(58*2))*4/1000)*'AHU IU1'!$L$2 -> 14.512 | AE13: =SUM(AE7:AE12) -> 117.66027 | AG13: =SUM(AG7:AG12) -> 2255725.7 | AH13: =AG13/14500 -> 155.56729
B14: 6 | C14: ="CENTERPOST DS" &$K$2& "Door" -> CENTERPOST DS5060Y(NA06)Door | D14: M | E14: =(((E2/2)-(35*2))/1000)*2 -> 3.11 | F14: RP | G14: =G13 -> 131975 | H14: =IF(F14="Rp",1/$H$7,1) -> 5.7142857e-05 | I14: 1 | J14: 1.05 | K14: =+G14*H14*I14*J14 -> 7.9185 | L14: 0 | N14: =VLOOKUP($K$2,Master!$O$4:$Y$21,4,0)*E14 -> 3.39923 | P14: 2540Y(NA20) | Q14: =(('AHU IU1'!$D$2-(58*2))*4/1000)*'AHU IU1'!$L$2 -> 10.432 | R14: =(('AHU IU1'!$E$2-(58*2))*4/1000)*'AHU IU1'!$L$2 -> 25.072 | S14: =(('AHU IU1'!$F$2-(58*2))*4/1000)*'AHU IU1'!$L$2 -> 14.512 | U14: 35 | V14: 40
B15: 7 | C15: ="CENTERPOST DS" &$K$2& "W" -> CENTERPOST DS5060Y(NA06)W | D15: M | E15: =((F2-(35*2))/1000)*2 -> 3.72 | F15: RP | G15: =G12 -> 131975 | H15: =IF(F15="Rp",1/$H$7,1) -> 5.7142857e-05 | I15: 1 | J15: 1.05 | K15: =+G15*H15*I15*J15 -> 7.9185 | L15: 0 | N15: =VLOOKUP($K$2,Master!$O$4:$Y$21,4,0)*E15 -> 4.06596 | P15: 5060Y(NA06) | Q15: =(('AHU IU1'!$D$2-(84*2))*4/1000)*'AHU IU1'!$L$2 -> 10.016 | R15: =(('AHU IU1'!$E$2-(84*2))*4/1000)*'AHU IU1'!$L$2 -> 24.656 | S15: =(('AHU IU1'!$F$2-(84*2))*4/1000)*'AHU IU1'!$L$2 -> 14.096 | U15: 59 | V15: 80
B16: 8 | C16: PANEL CLIP BIG | D16: M | E16: =SUM(E9:E15)*2 -> 122.956 | F16: RP | G16: =VLOOKUP($K$2,Master!$O$4:$Y$21,11,0) -> 15150 | H16: =IF(F16="Rp",1/$H$7,1) -> 5.7142857e-05 | I16: 1 | J16: 1.05 | K16: =+G16*H16*I16*J16 -> 0.909 | L16: 0 | N16: =VLOOKUP($K$2,Master!$O$4:$Y$21,10,0)*E16 -> 24.837112 | P16: 5060Y(NA20) | Q16: =(('AHU IU1'!$D$2-(84*2))*4/1000)*'AHU IU1'!$L$2 -> 10.016 | R16: =(('AHU IU1'!$E$2-(84*2))*4/1000)*'AHU IU1'!$L$2 -> 24.656 | S16: =(('AHU IU1'!$F$2-(84*2))*4/1000)*'AHU IU1'!$L$2 -> 14.096 | U16: 58 | V16: 82
B17: 9 | C17: PANEL CLIP SMALL | D17: M | E17: =E16/4 -> 30.739 | F17: RP | G17: =G16 -> 15150 | H17: =IF(F17="Rp",1/$H$7,1) -> 5.7142857e-05 | I17: 1 | J17: 1.05 | K17: =+G17*H17*I17*J17 -> 0.909 | L17: 0 | N17: =VLOOKUP($K$2,Master!$O$4:$Y$21,10,0)*E17 -> 6.209278 | P17: 5060N(NA06) | Q17: =(('AHU IU1'!$D$2-(80*2))*4/1000)*'AHU IU1'!$L$2 -> 10.08 | R17: =(('AHU IU1'!$E$2-(80*2))*4/1000)*'AHU IU1'!$L$2 -> 24.72 | S17: =(('AHU IU1'!$F$2-(80*2))*4/1000)*'AHU IU1'!$L$2 -> 14.16 | U17: 84 | V17: 134
B18: 10 | C18: RUBBER INSERT | D18: M | E18: =SUM(E16:E17) -> 153.695 | F18: RP | G18: 10000 | H18: =IF(F18="Rp",1/$H$7,1) -> 5.7142857e-05 | I18: 1 | J18: 1.05 | K18: =+G18*H18*I18*J18 -> 0.6 | L18: 0 | P18: 5060A(NA20) | Q18: =(('AHU IU1'!$D$2-(80*2))*4/1000)*'AHU IU1'!$L$2 -> 10.08 | R18: =(('AHU IU1'!$E$2-(80*2))*4/1000)*'AHU IU1'!$L$2 -> 24.72 | S18: =(('AHU IU1'!$F$2-(80*2))*4/1000)*'AHU IU1'!$L$2 -> 14.16
B19: 11 | C19: GASKET | D19: M | E19: =E18 -> 153.695 | F19: RP | G19: 10000 | H19: =IF(F19="Rp",1/$H$7,1) -> 5.7142857e-05 | I19: 1 | J19: 1.05 | K19: =+G19*H19*I19*J19 -> 0.6 | L19: 0 | P19: 2550T(304) | Q19: =(('AHU IU1'!$D$2-(50*2))*4/1000)*'AHU IU1'!$L$2 -> 10.56 | R19: =(('AHU IU1'!$E$2)*4/1000)*'AHU IU1'!$L$2 -> 26 | S19: =(('AHU IU1'!$F$2)*4/1000)*'AHU IU1'!$L$2 -> 15.44
B20: 12 | C20: ="CORNERPIECE DS"&$K$2 -> CORNERPIECE DS5060Y(NA06) | D20: PCS | E20: =8*L2 -> 16 | F20: RP | G20: =VLOOKUP($K$2,Master!$O$4:$Y$21,7,0) -> 84000 | H20: =IF(F20="Rp",1/$H$7,1) -> 5.7142857e-05 | I20: 1 | J20: 1 | K20: =+G20*H20*I20*J20 -> 4.8 | L20: 0 | N20: =VLOOKUP($K$2,Master!$O$4:$Y$21,6,0)*E20 -> 6.79616 | P20: 2550T(316) | Q20: =(('AHU IU1'!$D$2-(50*2))*4/1000)*'AHU IU1'!$L$2 -> 10.56 | R20: =(('AHU IU1'!$E$2)*4/1000)*'AHU IU1'!$L$2 -> 26 | S20: =(('AHU IU1'!$F$2)*4/1000)*'AHU IU1'!$L$2 -> 15.44
B21: 13 | C21: ="OMEGA JOINT DS"&$K$2 -> OMEGA JOINT DS5060Y(NA06) | D21: PCS | E21: =2*((E12/((D2-(35*2))/1000))+(E13/((E2-(35*2))/1000))+(E14/(((E2/2)-(35*2))/1000))+(E15/((F2-(35*2))/1000))) -> 14 | F21: RP | G21: =VLOOKUP($K$2,Master!$O$4:$Y$21,9,0) -> 24000 | H21: =IF(F21="Rp",1/$H$7,1) -> 5.7142857e-05 | I21: 1 | J21: 1 | K21: =+G21*H21*I21*J21 -> 1.3714286 | L21: =M21/H7 -> 945.25369 | M21: ='2. AHU-Frame & Panel'!O96 -> 16541940 | N21: =VLOOKUP($K$2,Master!$O$4:$Y$21,8,0)*E21 -> 0.792792 | P21: 5070T(304) | Q21: =(('AHU IU1'!$D$2-(70*2))*4/1000)*'AHU IU1'!$L$2 -> 10.24 | R21: =(('AHU IU1'!$E$2)*4/1000)*'AHU IU1'!$L$2 -> 26 | S21: =(('AHU IU1'!$F$2)*4/1000)*'AHU IU1'!$L$2 -> 15.44
B22: LEG/SKID | P22: 5070T(316) | Q22: =(('AHU IU1'!$D$2-(70*2))*4/1000)*'AHU IU1'!$L$2 -> 10.24 | R22: =(('AHU IU1'!$E$2)*4/1000)*'AHU IU1'!$L$2 -> 26 | S22: =(('AHU IU1'!$F$2)*4/1000)*'AHU IU1'!$L$2 -> 15.44 | T22: 2584 | U22: 892
B23: 14 | C23: Leg | D23: kg | E23: =1.4*AE13 -> 164.72438 | F23: RP | G23: 30000 | H23: =IF(F23="Rp",1/$H$7,1) -> 5.7142857e-05 | I23: 1 | J23: 1.2 | K23: =+G23*H23*I23*J23 -> 2.0571429 | L23: =M23/H7 -> 130.25767 | M23: ='1. AHU-Skid'!O25 -> 2279509.3 | N23: =E23 -> 164.72438 | P23: 2540A(304) | Q23: =(('AHU IU1'!$D$2-(40*2))*4/1000)*'AHU IU1'!$L$2 -> 10.72 | R23: =(('AHU IU1'!$E$2)*4/1000)*'AHU IU1'!$L$2 -> 26 | S23: =(('AHU IU1'!$F$2)*4/1000)*'AHU IU1'!$L$2 -> 15.44 | T23: 2664 | U23: 972
B24: 15 | C24: STRUCTUR | D24: kg | E24: 1 | F24: RP | G24: 0 | H24: =IF(F24="Rp",1/$H$7,1) -> 5.7142857e-05 | I24: 1 | J24: 1 | K24: =+G24*H24*I24*J24 -> 0 | L24: =M24/H7 -> 311.68791 | M24: ='3. AHU-Structure'!O60 -> 5454538.4 | N24: =E24 -> 1 | P24: 2540A(316) | Q24: =(('AHU IU1'!$D$2-(40*2))*4/1000)*'AHU IU1'!$L$2 -> 10.72 | R24: =(('AHU IU1'!$E$2)*4/1000)*'AHU IU1'!$L$2 -> 26 | S24: =(('AHU IU1'!$F$2)*4/1000)*'AHU IU1'!$L$2 -> 15.44 | T24: =T22-T23 -> -80 | U24: =U22-U23 -> -80
B25: FLANGE & FAN CONNECTION | P25: 4550A(304) | Q25: =(('AHU IU1'!$D$2-(50*2))*4/1000)*'AHU IU1'!$L$2 -> 10.56 | R25: =(('AHU IU1'!$E$2)*4/1000)*'AHU IU1'!$L$2 -> 26 | S25: =(('AHU IU1'!$F$2)*4/1000)*'AHU IU1'!$L$2 -> 15.44
B26: 16 | C26: Grill Flange SA | D26: m2 | E26: 0 | F26: RP | G26: 500000 | H26: =IF(F26="Rp",1/$H$7,1) -> 5.7142857e-05 | I26: 1 | J26: 1 | K26: =+G26*H26*I26*J26 -> 28.571429 | L26: =+E26*K26 -> 0 | M26: =L26*16500 -> 0 | P26: 4550A(316) | Q26: =(('AHU IU1'!$D$2-(50*2))*4/1000)*'AHU IU1'!$L$2 -> 10.56 | R26: =(('AHU IU1'!$E$2)*4/1000)*'AHU IU1'!$L$2 -> 26 | S26: =(('AHU IU1'!$F$2)*4/1000)*'AHU IU1'!$L$2 -> 15.44
B27: 17 | C27: Grill Flange RA | D27: m2 | E27: 0 | F27: RP | G27: 500000 | H27: =IF(F27="Rp",1/$H$7,1) -> 5.7142857e-05 | I27: 1 | J27: 1 | K27: =+G27*H27*I27*J27 -> 28.571429 | L27: =+E27*K27 -> 0 | M27: =L27*16500 -> 0
B28: 18 | C28: Blower Duct / Damper RA | D28: SET | E28: 0 | F28: RP | G28: ='VolDamperCost2023 RA '!S59+'VolDamperCost2023 RA '!S92 -> 801647.84 | H28: =IF(F28="Rp",1/$H$7,1) -> 5.7142857e-05 | I28: 1 | J28: 1 | K28: =+G28*H28*I28*J28 -> 45.808448 | L28: =+E28*K28 -> 0 | M28: =L28*16500 -> 0
B29: 19 | C29: Blower Duct / Damper SA | D29: SET | E29: 0 | F29: RP | G29: ='VolDamperCost2023 FA '!S59+'VolDamperCost2023 FA '!S92 -> 801647.84 | H29: =IF(F29="Rp",1/$H$7,1) -> 5.7142857e-05 | I29: 1 | J29: 1 | K29: =+G29*H29*I29*J29 -> 45.808448 | L29: =+E29*K29 -> 0 | M29: =L29*16500 -> 0 | X29: =1.26*0.4 -> 0.504 | Y29: RAG/FAG
B30: PANEL | X30: =350000/X29 -> 694444.44 | Y30: per m2
B31: 20 | C31: PANEL (PU+GI+CB) | D31: M2 | E31: =VLOOKUP($K$2,'AHU IU1'!$P$32:$R$68,3,0) -> 23.826336 | F31: USD | G31: =VLOOKUP($K$2,'AHU IU1'!$P$32:$R$68,2,0) -> 17.676994 | H31: =IF(F31="Rp",1/$H$7,1) -> 1 | I31: 1 | J31: 1.2 | K31: =+G31*H31*I31*J31 -> 21.212393 | L31: =+E31*K31 -> 505.41361 | M31: 0 | N31: =VLOOKUP($K$2,Master!O4:Z21,12,0)/1000*E31*48 -> 57.183206 | P31: PANEL
B32: 21 | C32: PANEL (PU+GI+CB) | D32: PCS | E32: 0 | F32: RP | G32: 52000 | H32: =IF(F32="Rp",1/$H$7,1) -> 5.7142857e-05 | I32: 1 | J32: 1 | K32: =+G32*H32*I32*J32 -> 2.9714286 | L32: =+E32*K32 -> 0 | M32: =L32*15000 -> 0 | Q32: =((0.45/1000*7860*30200)+(0.4/1000*7860*22000)+(15/1000*48*50000))*1 -> 211985.4
B33: DOOR | P33: 1520T(NA06) | Q33: =Q32/'AHU IU1'!$H$7 -> 12.113451 | R33: =((('AHU IU1'!$D$2-40)/1000*('AHU IU1'!$E$2-40)/1000)*2+((('AHU IU1'!$D$2-40)/1000*('AHU IU1'!$F$2-40)/1000)*2)+(('AHU IU1'!$E$2-40)/1000*('AHU IU1'!$F$2-40)/1000)*2) -> 26.2098 | X33: =1.8*0.4 -> 0.72 | Y33: RAG/FAG
B34: 22 | C34: Access Door | D34: PCS | E34: 1 | F34: USD | G34: 80 | H34: =IF(F34="Rp",1/$H$7,1) -> 1 | I34: 1.5 | J34: 1 | K34: =+G34*H34*I34*J34 -> 120 | L34: =+E34*K34 -> 120 | M34: =L34*16500 -> 1980000 | Q34: =((0.45/1000*7860*30200)+(0.4/1000*7860*22000)+(15/1000*48*50000))*1 -> 211985.4 | X34: =715000/X33 -> 993055.56 | Y34: per m2
B35: 23 | C35: MFG 125 DS50 | D35: PCS | E35: 0 | F35: RP | G35: 100000 | H35: =IF(F35="Rp",1/$H$7,1) -> 5.7142857e-05 | I35: 1 | J35: 1 | K35: =+G35*H35*I35*J35 -> 5.7142857 | L35: =+E35*K35 -> 0 | M35: =L35*16500 -> 0 | P35: 1520T(NA20) | Q35: =Q34/'AHU IU1'!$H$7 -> 12.113451 | R35: =((('AHU IU1'!$D$2-40)/1000*('AHU IU1'!$E$2-40)/1000)*2+((('AHU IU1'!$D$2-40)/1000*('AHU IU1'!$F$2-40)/1000)*2)+(('AHU IU1'!$E$2-40)/1000*('AHU IU1'!$F$2-40)/1000)*2) -> 26.2098
B36: 24 | C36: MFG 134 | D36: PCS | E36: 0 | F36: RP | G36: 0 | H36: =IF(F36="Rp",1/$H$7,1) -> 5.7142857e-05 | I36: 1 | J36: 1 | K36: =+G36*H36*I36*J36 -> 0 | L36: =+E36*K36 -> 0 | M36: =L36*16500 -> 0 | Q36: =((0.45/1000*7860*30200)+(0.4/1000*7860*22000)+(15/1000*48*50000))*1 -> 211985.4
B37: FAN & MOTOR | P37: 1540T(NA06) | Q37: =Q36/'AHU IU1'!$H$7 -> 12.113451 | R37: =((('AHU IU1'!$D$2-80)/1000*('AHU IU1'!$E$2-80)/1000)*2+((('AHU IU1'!$D$2-80)/1000*('AHU IU1'!$F$2-80)/1000)*2)+(('AHU IU1'!$E$2-80)/1000*('AHU IU1'!$F$2-80)/1000)*2) -> 25.1826
A38: AT 00/00-X | B38: 25 | C38: SYD 450 R | D38: PCS | E38: 1 | F38: USD | G38: =VLOOKUP(C38,Master!J8:K283,2,0) -> 257 | H38: =IF(F38="Rp",1/$H$7,1) -> 1 | I38: 2.5 | J38: 1 | K38: =+G38*H38*I38*J38 -> 642.5 | L38: =+E38*K38 -> 642.5 | M38: =L38*16500 -> 10601250 | N38: =VLOOKUP(C38,Master!$J$8:$L$283,3,0) -> 57 | Q38: =((0.45/1000*7860*30200)+(0.4/1000*7860*22000)+(15/1000*48*50000))*1 -> 211985.4
B39: 26 | C39: Motor 7.5kW-4P | D39: PCS | E39: 1 | F39: USD | G39: =VLOOKUP(C39,Master!$F$2:$G$67,2,0) -> 362.9 | H39: =IF(F39="Rp",1/$H$7,1) -> 1 | I39: 2 | J39: 1.2 | K39: =+G39*H39*I39*J39 -> 870.96 | L39: =+E39*K39 -> 870.96 | M39: =L39*16500 -> 14370840 | P39: 1540T(NA20) | Q39: =Q38/'AHU IU1'!$H$7 -> 12.113451 | R39: =((('AHU IU1'!$D$2-80)/1000*('AHU IU1'!$E$2-80)/1000)*2+((('AHU IU1'!$D$2-80)/1000*('AHU IU1'!$F$2-80)/1000)*2)+(('AHU IU1'!$E$2-80)/1000*('AHU IU1'!$F$2-80)/1000)*2) -> 25.1826
A40: PB | B40: 27 | C40: 2SPA212 | D40: PCS | E40: 1 | F40: RP | G40: =VLOOKUP(C40,Master!$A$29:$B$436,2,0) -> 1720000 | H40: =IF(F40="Rp",1/$H$7,1) -> 5.7142857e-05 | I40: 1 | J40: 1 | K40: =+G40*H40*I40*J40 -> 98.285714 | L40: =+E40*K40 -> 98.285714 | M40: =L40*16500 -> 1621714.3 | Q40: =((0.45/1000*7860*30200)+(0.4/1000*7860*22000)+(25/1000*48*50000))*1 -> 235985.4
A41: PM | B41: 28 | C41: 2SPA150 | D41: PCS | E41: 1 | F41: RP | G41: =VLOOKUP(C41,Master!$A$29:$B$436,2,0) -> 910000 | H41: =IF(F41="Rp",1/$H$7,1) -> 5.7142857e-05 | I41: 1 | J41: 1 | K41: =+G41*H41*I41*J41 -> 52 | L41: =+E41*K41 -> 52 | M41: =L41*16500 -> 858000 | P41: 2540Y(NA06) | Q41: =Q40/'AHU IU1'!$H$7 -> 13.48488 | R41: =((('AHU IU1'!$D$2-82)/1000*('AHU IU1'!$E$2-82)/1000)*2+((('AHU IU1'!$D$2-82)/1000*('AHU IU1'!$F$2-82)/1000)*2)+(('AHU IU1'!$E$2-82)/1000*('AHU IU1'!$F$2-82)/1000)*2) -> 25.131744
B42: 29 | C42: Bush 2517 | D42: PCS | E42: 1 | F42: RP | G42: =VLOOKUP(C42,Master!$A$4:$B$22,2,0)/2 -> 330000 | H42: =IF(F42="Rp",1/$H$7,1) -> 5.7142857e-05 | I42: 1 | J42: 1 | K42: =+G42*H42*I42*J42 -> 18.857143 | L42: =+E42*K42 -> 18.857143 | M42: =L42*16500 -> 311142.86 | Q42: =((0.45/1000*7860*30200)+(0.4/1000*7860*22000)+(25/1000*48*50000))*1 -> 235985.4
B43: 30 | C43: Bush 2012 | D43: PCS | E43: 1 | F43: RP | G43: =VLOOKUP(C43,Master!$A$4:$B$22,2,0)/2 -> 185000 | H43: =IF(F43="Rp",1/$H$7,1) -> 5.7142857e-05 | I43: 1 | J43: 1 | K43: =+G43*H43*I43*J43 -> 10.571429 | L43: =+E43*K43 -> 10.571429 | M43: =L43*16500 -> 174428.57 | P43: 2540Y(NA20) | Q43: =Q42/'AHU IU1'!$H$7 -> 13.48488 | R43: =((('AHU IU1'!$D$2-82)/1000*('AHU IU1'!$E$2-82)/1000)*2+((('AHU IU1'!$D$2-82)/1000*('AHU IU1'!$F$2-82)/1000)*2)+(('AHU IU1'!$E$2-82)/1000*('AHU IU1'!$F$2-82)/1000)*2) -> 25.131744
B44: 31 | C44: V-BELT SPA | D44: PCS | E44: 2 | F44: USD | G44: 20 | H44: =IF(F44="Rp",1/$H$7,1) -> 1 | I44: 1 | J44: 1 | K44: =+G44*H44*I44*J44 -> 20 | L44: =+E44*K44 -> 40 | M44: =L44*16500 -> 660000 | Q44: =((0.45/1000*7860*32200)+(0.4/1000*7860*24000)+(50/1000*48*50000))*1 -> 309347.4
B45: 32 | C45: RUBBER, RM 2B ORANGE | D45: PCS | E45: 0 | F45: RP | G45: 70000 | H45: =IF(F45="Rp",1/$H$7,1) -> 5.7142857e-05 | I45: 1 | J45: 1 | K45: =+G45*H45*I45*J45 -> 4 | L45: =+E45*K45 -> 0 | M45: =L45*16500 -> 0 | P45: 5060Y(NA06) | Q45: =Q44/'AHU IU1'!$H$7 -> 17.676994 | R45: =((('AHU IU1'!$D$2-134)/1000*('AHU IU1'!$E$2-134)/1000)*2+((('AHU IU1'!$D$2-134)/1000*('AHU IU1'!$F$2-134)/1000)*2)+(('AHU IU1'!$E$2-134)/1000*('AHU IU1'!$F$2-134)/1000)*2) -> 23.826336
B46: 33 | C46: Spring Mounting YDS A100-Grey | D46: PCS | E46: 0 | F46: USD | G46: 6 | H46: =IF(F46="Rp",1/$H$7,1) -> 1 | I46: 1.5 | J46: 1 | K46: =+G46*H46*I46*J46 -> 9 | L46: =+E46*K46 -> 0 | M46: =L46*16500 -> 0 | Q46: =((0.45/1000*7860*30200)+(0.4/1000*7860*22000)+(50/1000*48*50000))*1 -> 295985.4
B47: 34 | C47: Spring Mounting YDS A 160 TAN | D47: PCS | E47: 0 | F47: USD | G47: 54 | H47: =IF(F47="Rp",1/$H$7,1) -> 1 | I47: 1 | J47: 1 | K47: =+G47*H47*I47*J47 -> 54 | L47: =+E47*K47 -> 0 | M47: =L47*16500 -> 0 | P47: 5060Y(NA20) | Q47: =Q46/'AHU IU1'!$H$7 -> 16.913451 | R47: =((('AHU IU1'!$D$2-134)/1000*('AHU IU1'!$E$2-134)/1000)*2+((('AHU IU1'!$D$2-134)/1000*('AHU IU1'!$F$2-134)/1000)*2)+(('AHU IU1'!$E$2-134)/1000*('AHU IU1'!$F$2-134)/1000)*2) -> 23.826336
B48: 35 | C48: Spring Mounting YDS | D48: PCS | E48: 4 | F48: RP | G48: 250000 | H48: =IF(F48="Rp",1/$H$7,1) -> 5.7142857e-05 | I48: 1 | J48: 1 | K48: =+G48*H48*I48*J48 -> 14.285714 | L48: =+E48*K48 -> 57.142857 | M48: =L48*16500 -> 942857.14 | Q48: =((0.45/1000*7860*30200)+(0.4/1000*7860*22000)+(50/1000*48*50000))*1 -> 295985.4
B49: FILTER | P49: 5060N(NA06) | Q49: =Q48/'AHU IU1'!$H$7 -> 16.913451 | R49: =((('AHU IU1'!$D$2-117)/1000*('AHU IU1'!$E$2-117)/1000)*2+((('AHU IU1'!$D$2-117)/1000*('AHU IU1'!$F$2-117)/1000)*2)+(('AHU IU1'!$E$2-117)/1000*('AHU IU1'!$F$2-117)/1000)*2) -> 24.249534
B50: 36 | C50: Pre Filter 24x24x2 G4 | D50: PCS | E50: 2 | F50: RP | G50: 209500 | H50: =IF(F50="Rp",1/$H$7,1) -> 5.7142857e-05 | I50: 1 | J50: 1 | K50: =+G50*H50*I50*J50 -> 11.971429 | L50: =+E50*K50 -> 23.942857 | M50: =L50*16500 -> 395057.14 | Q50: =((0.45/1000*7860*30200)+(0.4/1000*7860*22000)+(50/1000*48*50000))*1 -> 295985.4
B51: 37 | C51: Pre Filter 24x12x2 | D51: PCS | E51: 3 | F51: RP | G51: 130000 | H51: =IF(F51="Rp",1/$H$7,1) -> 5.7142857e-05 | I51: 1 | J51: 1 | K51: =+G51*H51*I51*J51 -> 7.4285714 | L51: =+E51*K51 -> 22.285714 | M51: =L51*16500 -> 367714.29 | P51: 5060A(NA20) | Q51: =Q50/'AHU IU1'!$H$7 -> 16.913451 | R51: =((('AHU IU1'!$D$2-117)/1000*('AHU IU1'!$E$2-117)/1000)*2+((('AHU IU1'!$D$2-117)/1000*('AHU IU1'!$F$2-117)/1000)*2)+(('AHU IU1'!$E$2-117)/1000*('AHU IU1'!$F$2-117)/1000)*2) -> 24.249534
B52: 38 | C52: Pre Filter 20x25x1 | D52: PCS | E52: 0 | F52: RP | G52: 74500 | H52: =IF(F52="Rp",1/$H$7,1) -> 5.7142857e-05 | I52: 1 | J52: 1 | K52: =+G52*H52*I52*J52 -> 4.2571429 | L52: =+E52*K52 -> 0 | M52: =L52*16500 -> 0 | Q52: =((0.5/1000*8000*59000)+(0.5/1000*8000*59000)+(25/1000*48*50000))*1 -> 532000
B53: 39 | C53: med Filter 24"x24" (F8) | D53: PCS | E53: 0 | F53: RP | G53: 654000 | H53: =IF(F53="Rp",1/$H$7,1) -> 5.7142857e-05 | I53: 1 | J53: 1 | K53: =+G53*H53*I53*J53 -> 37.371429 | L53: =+E53*K53 -> 0 | M53: =L53*16500 -> 0 | P53: 2550T(304) | Q53: =Q52/'AHU IU1'!$H$7 -> 30.4 | R53: =((('AHU IU1'!$D$2-100)/1000*('AHU IU1'!$E$2-100)/1000)*2+((('AHU IU1'!$D$2-100)/1000*('AHU IU1'!$F$2-100)/1000)*2)+(('AHU IU1'!$E$2-100)/1000*('AHU IU1'!$F$2-100)/1000)*2) -> 24.6762
B54: 40 | C54: Med Filter 24"x12" | D54: PCS | E54: 0 | F54: RP | G54: 489500 | H54: =IF(F54="Rp",1/$H$7,1) -> 5.7142857e-05 | I54: 1 | J54: 1 | K54: =+G54*H54*I54*J54 -> 27.971429 | L54: =+E54*K54 -> 0 | M54: =L54*16500 -> 0 | Q54: =((0.5/1000*8000*59000)+(0.5/1000*8000*59000)+(25/1000*48*50000))*1 -> 532000
B55: 41 | C55: Hepa Filter 24"x24" | D55: PCS | E55: 0 | F55: RP | G55: 1500000 | H55: =IF(F55="Rp",1/$H$7,1) -> 5.7142857e-05 | I55: 1 | J55: 1 | K55: =+G55*H55*I55*J55 -> 85.714286 | L55: =+E55*K55 -> 0 | M55: =L55*16500 -> 0 | P55: 2550T(316) | Q55: =Q54/'AHU IU1'!$H$7 -> 30.4 | R55: =((('AHU IU1'!$D$2-100)/1000*('AHU IU1'!$E$2-100)/1000)*2+((('AHU IU1'!$D$2-100)/1000*('AHU IU1'!$F$2-100)/1000)*2)+(('AHU IU1'!$E$2-100)/1000*('AHU IU1'!$F$2-100)/1000)*2) -> 24.6762
B56: 42 | C56: Hepa Filter 24"x12" | D56: PCS | E56: 0 | F56: RP | G56: 1200000 | H56: =IF(F56="Rp",1/$H$7,1) -> 5.7142857e-05 | I56: 1 | J56: 1 | K56: =+G56*H56*I56*J56 -> 68.571429 | L56: =+E56*K56 -> 0 | M56: =L56*16500 -> 0 | Q56: =((0.5/1000*8000*59000)+(0.5/1000*8000*59000)+(50/1000*48*50000))*1 -> 592000
B57: 43 | C57: Carbon Filter 24"x24" (F7) | D57: PCS | E57: 0 | F57: RP | G57: 500000 | H57: =IF(F57="Rp",1/$H$7,1) -> 5.7142857e-05 | I57: 1 | J57: 1 | K57: =+G57*H57*I57*J57 -> 28.571429 | L57: =+E57*K57 -> 0 | M57: =L57*16500 -> 0
B58: 44 | C58: Carbon Filter 24"x12" | D58: PCS | E58: 0 | F58: RP | G58: 350000 | H58: =IF(F58="Rp",1/$H$7,1) -> 5.7142857e-05 | I58: 1 | J58: 1 | K58: =+G58*H58*I58*J58 -> 20 | L58: =+E58*K58 -> 0 | M58: =L58*16500 -> 0 | P58: 5070T(304) | Q58: =Q56/'AHU IU1'!$H$7 -> 33.828571 | R58: =((('AHU IU1'!$D$2-130)/1000*('AHU IU1'!$E$2-130)/1000)*2+((('AHU IU1'!$D$2-130)/1000*('AHU IU1'!$F$2-130)/1000)*2)+(('AHU IU1'!$E$2-130)/1000*('AHU IU1'!$F$2-130)/1000)*2) -> 23.9256
B59: 45 | C59: Filter Rail | D59: SET | E59: 1 | F59: RP | G59: 1000000 | H59: =IF(F59="Rp",1/$H$7,1) -> 5.7142857e-05 | I59: 1 | J59: 1 | K59: =+G59*H59*I59*J59 -> 57.142857 | L59: =+E59*K59 -> 57.142857 | M59: =L59*16500 -> 942857.14 | Q59: =((0.5/1000*8000*59000)+(0.5/1000*8000*59000)+(50/1000*48*50000))*1 -> 592000
B60: COIL | P60: 5070T(316) | Q60: =Q59/'AHU IU1'!$H$7 -> 33.828571 | R60: =((('AHU IU1'!$D$2-130)/1000*('AHU IU1'!$E$2-130)/1000)*2+((('AHU IU1'!$D$2-130)/1000*('AHU IU1'!$F$2-130)/1000)*2)+(('AHU IU1'!$E$2-130)/1000*('AHU IU1'!$F$2-130)/1000)*2) -> 23.9256
B61: 45 | C61: Coil DX | D61: set | E61: 1 | F61: RP | G61: ='CoilCost 20251027'!R313 -> 19388614 | H61: =IF(F61="Rp",1/$H$7,1) -> 5.7142857e-05 | I61: 1 | J61: 1 | K61: =+G61*H61*I61*J61 -> 1107.9208 | L61: =+E61*K61 -> 1107.9208 | M61: =L61*16500 -> 18280693 | Q61: =((0.5/1000*8000*59000)+(0.5/1000*8000*59000)+(25/1000*48*50000))*1 -> 532000
B62: 46 | C62: Drainpan SS | D62: Pcs | E62: 0 | F62: Usd | G62: =drainpan!S14 -> 50.308385 | H62: =IF(F62="Rp",1/$H$7,1) -> 1 | I62: 1 | J62: 1 | K62: =+G62*H62*I62*J62 -> 50.308385 | L62: =+E62*K62 -> 0 | M62: =L62*16500 -> 0 | P62: 2540A(304) | Q62: =Q61/'AHU IU1'!$H$7 -> 30.4 | R62: =((('AHU IU1'!$D$2-70)/1000*('AHU IU1'!$E$2-70)/1000)*2+((('AHU IU1'!$D$2-70)/1000*('AHU IU1'!$F$2-70)/1000)*2)+(('AHU IU1'!$E$2-70)/1000*('AHU IU1'!$F$2-70)/1000)*2) -> 25.4376
B63: 47 | C63: PE POAM + STRIP, POST | D63: m2 | E63: 10 | F63: RP | G63: 60000 | H63: =IF(F63="Rp",1/$H$7,1) -> 5.7142857e-05 | I63: 1 | J63: 1 | K63: =+G63*H63*I63*J63 -> 3.4285714 | L63: =+E63*K63 -> 34.285714 | M63: =L63*16500 -> 565714.29 | Q63: =((0.5/1000*8000*59000)+(0.5/1000*8000*59000)+(25/1000*48*50000))*1 -> 532000
B64: ELECTRICAL | P64: 2540A(316) | Q64: =Q63/'AHU IU1'!$H$7 -> 30.4 | R64: =((('AHU IU1'!$D$2-70)/1000*('AHU IU1'!$E$2-70)/1000)*2+((('AHU IU1'!$D$2-70)/1000*('AHU IU1'!$F$2-70)/1000)*2)+(('AHU IU1'!$E$2-70)/1000*('AHU IU1'!$F$2-70)/1000)*2) -> 25.4376
B65: 48 | C65: Control Box | D65: SET | E65: 1 | F65: RP | G65: 5000000 | H65: =IF(F65="Rp",1/$H$7,1) -> 5.7142857e-05 | I65: 1 | J65: 1 | K65: =+G65*H65*I65*J65 -> 285.71429 | L65: =+E65*K65 -> 285.71429 | M65: =L65*16500 -> 4714285.7 | Q65: =((0.5/1000*8000*59000)+(0.5/1000*8000*59000)+(45/1000*48*50000))*1 -> 580000
B66: 49 | C66: Controller | D66: SET | E66: 1 | F66: RP | G66: 3500000 | H66: =IF(F66="Rp",1/$H$7,1) -> 5.7142857e-05 | I66: 1 | J66: 1 | K66: =+G66*H66*I66*J66 -> 200 | L66: =+E66*K66 -> 200 | M66: =L66*16500 -> 3300000 | P66: 4550A(304) | Q66: =Q65/'AHU IU1'!$H$7 -> 33.142857 | R66: =((('AHU IU1'!$D$2-90)/1000*('AHU IU1'!$E$2-90)/1000)*2+((('AHU IU1'!$D$2-90)/1000*('AHU IU1'!$F$2-90)/1000)*2)+(('AHU IU1'!$E$2-90)/1000*('AHU IU1'!$F$2-90)/1000)*2) -> 24.9288
B67: 50 | C67: Starter | D67: SET | E67: 0 | F67: RP | G67: 0 | H67: =IF(F67="Rp",1/$H$7,1) -> 5.7142857e-05 | I67: 1 | J67: 1 | K67: =+G67*H67*I67*J67 -> 0 | L67: =+E67*K67 -> 0 | M67: =L67*16500 -> 0 | Q67: =((0.5/1000*8000*59000)+(0.5/1000*8000*59000)+(45/1000*48*50000))*1 -> 580000
B68: 51 | C68: Terminal Block | D68: SET | E68: 0 | F68: RP | G68: 0 | H68: =IF(F68="Rp",1/$H$7,1) -> 5.7142857e-05 | I68: 1 | J68: 1 | K68: =+G68*H68*I68*J68 -> 0 | L68: =+E68*K68 -> 0 | M68: =L68*16500 -> 0 | P68: 4550A(316) | Q68: =Q67/'AHU IU1'!$H$7 -> 33.142857 | R68: =((('AHU IU1'!$D$2-90)/1000*('AHU IU1'!$E$2-90)/1000)*2+((('AHU IU1'!$D$2-90)/1000*('AHU IU1'!$F$2-90)/1000)*2)+(('AHU IU1'!$E$2-90)/1000*('AHU IU1'!$F$2-90)/1000)*2) -> 24.9288
B69: 52 | C69: Cable Bush | D69: SET | E69: 0 | F69: RP | G69: 0 | H69: =IF(F69="Rp",1/$H$7,1) -> 5.7142857e-05 | I69: 1 | J69: 1 | K69: =+G69*H69*I69*J69 -> 0 | L69: =+E69*K69 -> 0 | M69: =L69*16500 -> 0
B70: 53 | C70: Cable NYAF | D70: SET | E70: 0 | F70: RP | G70: 0 | H70: =IF(F70="Rp",1/$H$7,1) -> 5.7142857e-05 | I70: 1 | J70: 1 | K70: =+G70*H70*I70*J70 -> 0 | L70: =+E70*K70 -> 0 | M70: =L70*16500 -> 0
B71: 54 | C71: Terminal Ring/Fork/Socket/Insulation | D71: SET | E71: 0 | F71: RP | G71: 0 | H71: =IF(F71="Rp",1/$H$7,1) -> 5.7142857e-05 | I71: 1 | J71: 1 | K71: =+G71*H71*I71*J71 -> 0 | L71: =+E71*K71 -> 0 | M71: =L71*16500 -> 0
B72: 55 | C72: Cable Wrap | D72: SET | E72: 0 | F72: RP | G72: 0 | H72: =IF(F72="Rp",1/$H$7,1) -> 5.7142857e-05 | I72: 1 | J72: 1 | K72: =+G72*H72*I72*J72 -> 0 | L72: =+E72*K72 -> 0 | M72: =L72*16500 -> 0
B73: LABEL & PACKING
B74: 56 | C74: Label | D74: SET | E74: 1 | F74: RP | G74: 50000 | H74: =IF(F74="Rp",1/$H$7,1) -> 5.7142857e-05 | I74: 1 | J74: 1 | K74: =+G74*H74*I74*J74 -> 2.8571429 | L74: =+E74*K74 -> 2.8571429 | M74: =L74*16500 -> 47142.857
B75: 57 | C75: Packing | D75: SET | E75: 1 | F75: RP | G75: 50000 | H75: =IF(F75="Rp",1/$H$7,1) -> 5.7142857e-05 | I75: 1 | J75: 1 | K75: =+G75*H75*I75*J75 -> 2.8571429 | L75: =+E75*K75 -> 2.8571429 | M75: =L75*16500 -> 47142.857
B76: ETC
B77: 58 | C77: Coating | D77: PCS | E77: 0 | F77: RP | G77: 0 | H77: =IF(F77="Rp",1/$H$7,1) -> 5.7142857e-05 | I77: 1 | J77: 1.2 | K77: =+G77*H77*I77*J77 -> 0 | L77: =+E77*K77 -> 0 | M77: =L77*16500 -> 0
B78: 59 | C78: DPG Magnehelic | D78: PCS | E78: 0 | F78: USD | G78: =VLOOKUP(C78,Master!AC16:AD17,2,0) -> 106.66667 | H78: =IF(F78="Rp",1/$H$7,1) -> 1 | I78: 1.55 | J78: 1 | K78: =+G78*H78*I78*J78 -> 165.33333 | L78: =+E78*K78 -> 0 | M78: =L78*16500 -> 0
B79: 60 | C79: View Port | D79: PCS | E79: 0 | F79: USD | G79: 10 | H79: =IF(F79="Rp",1/$H$7,1) -> 1 | I79: 2 | J79: 1 | K79: =+G79*H79*I79*J79 -> 20 | L79: =+E79*K79 -> 0 | M79: =L79*16500 -> 0
A80: UVC | B80: 61 | C80: ESL 80W x 843mmL | D80: PCS | E80: 0 | F80: USD | G80: 41 | H80: =IF(F80="Rp",1/$H$7,1) -> 1 | I80: 1.55 | J80: 1 | K80: =+G80*H80*I80*J80 -> 63.55 | L80: =+E80*K80 -> 0 | M80: =L80*16500 -> 0
B81: 62 | C81: LED Lamp ZKLED-EX-401E | D81: PCS | E81: 0 | F81: USD | G81: 10 | H81: =IF(F81="Rp",1/$H$7,1) -> 1 | I81: 2 | J81: 1 | K81: =+G81*H81*I81*J81 -> 20 | L81: =+E81*K81 -> 0 | M81: =L81*16500 -> 0
B82: 63 | C82: FASTENER | D82: LOT | E82: 1 | F82: RP | G82: 2000000 | H82: =IF(F82="Rp",1/$H$7,1) -> 5.7142857e-05 | I82: 1 | J82: 1 | K82: =+G82*H82*I82*J82 -> 114.28571 | L82: =+E82*K82 -> 114.28571 | M82: =L82*16500 -> 1885714.3
B83: 64 | C83: Electrical Heater | D83: Set | E83: 0 | F83: USD | G83: =23.62 -> 23.62 | H83: =IF(F83="Rp",1/$H$7,1) -> 1 | I83: 2.5 | J83: 1 | K83: =+G83*H83*I83*J83 -> 59.05 | L83: =+E83*K83 -> 0 | M83: =L83*16500 -> 0
B84: 65 | C84: PALLET | D84: LOT | E84: 1 | F84: RP | G84: 1000000 | H84: =IF(F84="Rp",1/$H$7,1) -> 5.7142857e-05 | I84: 1 | J84: 1 | K84: =+G84*H84*I84*J84 -> 57.142857 | L84: =+E84*K84 -> 57.142857 | M84: =L84*16500 -> 942857.14
B85: OPERATION
B86: 66 | C86: OPERATING SUPPLY | D86: LOT | E86: 0.15 | F86: USD | G86: =SUM(L9:L85) -> 5711.3651 | H86: =IF(F86="Rp",1/$H$7,1) -> 1 | I86: 1 | J86: 1 | K86: =+G86*H86*I86*J86 -> 5711.3651 | L86: =+E86*K86 -> 856.70476 | M86: =L86*16500 -> 14135629
L87: =SUM(L9:L86)*1.01 -> 6633.7505 | M87: =L87*H7 -> 1.1609063e+08
J89: Margin | K89: 0.35 | L89: =L87/(1-K89) -> 10205.77 | M89: =L89*H7 -> 1.7860098e+08
M90: =ROUNDUP(M89,-5) -> 178700000
M93: =L87*H7 -> 1.1609063e+08
M94: =ROUNDUP(M93,-3) -> 116091000

Sheet VolDamperCost2023 RA 
B1: ThermalTrue® | BB1: 11111111111111111111111111111111111111111111111111111111111111111111111111111111111111111111111111111111111111111111111111111111111111111111111111111111111111111111111111111111111111111111111111111111111111111111111111111111111111111111111111111111111111111111111111111111111111111111111111111111111111111111111111111111111111111111111111111111111111111111111111111111111111111111111111111111111111111111111111111111111111111111111111111111111111111111111111111111111111111111111111111111111111111111111111111111111111111111111111111111111111
B2: Project: | C2: Yudi
B3: Date: | C3: =TODAY() -> 46089
B4: Rp/USD: | C4: =+S43 -> 17500
B5: Material CostList Volume Damper PS125
B6: PickList | C6: P/Ninternal | D6: Parts List : Frame | E6: UW | F6: UC(Rp) | G6: FOB | H6: LF | I6: Fx | J6: UC | L6: Cy | M6: FOB | N6: LF | O6: Fx | P6: UC | R6: Rp | S6: 1
B7: SPHC | C7: 0101-04-000-0 | D7: SPHC (Hot rolled) 1.0mm x 4' x 8' x7700kG/m3 | E7: 7700 | F7: =+P7 -> 18000 | L7: Rp | M7: 18000 | N7: 1 | O7: =VLOOKUP(L7,$R$6:$S$12,2,FALSE) -> 1 | P7: =+M7*N7*O7 -> 18000 | R7: USD | S7: 17500
B8: SGCC | C8: 0101-02-000-0 | D8: SGCC (GI) 1.0mm x 4' x 8' x 8030kG/m3 | E8: 8030 | F8: =+P8 -> 30000 | L8: Rp | M8: 30000 | N8: 1 | O8: =VLOOKUP(L8,$R$6:$S$12,2,FALSE) -> 1 | P8: =+M8*N8*O8 -> 30000 | R8: Euro | S8: 16079.99
B9: SUS304 | C9: 0101-05-000-0 | D9: Stainless Stl (SUS304) 1.0mm x 4' x 8' x 7800kG/m3 | E9: 7800 | F9: =+P9 -> 55000 | L9: Rp | M9: 55000 | N9: 1 | O9: =VLOOKUP(L9,$R$6:$S$12,2,FALSE) -> 1 | P9: =+M9*N9*O9 -> 55000 | R9: RM | S9: 3429.69
B10: SUS36L | C10: 0101-06-000-0 | D10: Stainless Stl (SUS316L) 1.0mm x 4' x 8' x 8000kG/m3 | E10: 8000 | F10: =+P10 -> 55000 | L10: Rp | M10: 55000 | N10: 1 | O10: =VLOOKUP(L10,$R$6:$S$12,2,FALSE) -> 1 | P10: =+M10*N10*O10 -> 55000 | R10: Rmb | S10: 2192.36
B11: Al6065 | C11: 0101-07-000-0 | D11: Aluminium 6065 1.0mm x 4' x 8' x 2720kG/m3 | E11: 2720 | F11: =+P11 -> 83085 | L11: Rp | M11: 83085 | N11: 1 | O11: =VLOOKUP(L11,$R$6:$S$12,2,FALSE) -> 1 | P11: =+M11*N11*O11 -> 83085 | R11: S$ | S11: 11262.76
B12: ET6065 | C12: 0102-00-000-0 | D12: Aluminium Extrusion 6065-T5, NA | E12: 1 | F12: =+P12 -> 78000 | L12: Rp | M12: 78000 | N12: 1 | O12: =VLOOKUP(L12,$R$6:$S$12,2,FALSE) -> 1 | P12: =+M12*N12*O12 -> 78000 | R12: Rs | S12: 183.43
B13: SH5037 | D13: Damper Frame : Horizontal, T/B Profile -34.4T x 125W | E13: 1.032 | F13: =+P13 -> 86114.208 | G13: =3.2*E13 -> 3.3024 | H13: 1.5 | I13: =+S$7 -> 17500 | J13: =+G13*H13*I13 -> 86688 | L13: Rp | M13: =+E13*(((10430500/25)/6)*1.2) -> 86114.208 | N13: 1 | O13: =VLOOKUP(L13,$R$6:$S$12,2,FALSE) -> 1 | P13: =+M13*N13*O13 -> 86114.208
B14: SH5038 | D14: Damper Frame : Vertical, L/R Profile - 34.4T x 125W | E14: 1.4 | F14: =+P14 -> 109200 | G14: =3.2*E14 -> 4.48 | H14: 1.5 | I14: =+S$7 -> 17500 | J14: =+G14*H14*I14 -> 117600 | L14: Rp | M14: =+E14*M$12 -> 109200 | N14: 1 | O14: =VLOOKUP(L14,$R$6:$S$12,2,FALSE) -> 1 | P14: =+M14*N14*O14 -> 109200
B15: SH5039 | D15: Damper Frame : Vertical, Center Profile - 34.4T x 125W | E15: 1.759 | F15: =+P15 -> 214624.38 | G15: =3.2*E15 -> 5.6288 | H15: 1.5 | I15: =+S$7 -> 17500 | J15: =+G15*H15*I15 -> 147756 | L15: Rp | M15: =+E15*((14641800/20)/6) -> 214624.38 | N15: 1 | O15: =VLOOKUP(L15,$R$6:$S$12,2,FALSE) -> 1 | P15: =+M15*N15*O15 -> 214624.38
B16: SH5040 | D16: Damper, Leaf : Flat Blade Profile - 15.7T x 108W | E16: 0.85 | F16: =+P16 -> 69353.625 | G16: =3.2*E16 -> 2.72 | H16: 1.5 | I16: =+S$7 -> 17500 | J16: =+G16*H16*I16 -> 71400 | L16: Rp | M16: =+E16*(((17950350/55)/6)*1.5) -> 69353.625 | N16: 1 | O16: =VLOOKUP(L16,$R$6:$S$12,2,FALSE) -> 1 | P16: =+M16*N16*O16 -> 69353.625
B17: GA100 | D17: Damper, Gasket : 200m/roll (密封胶条） | E17: =7.47/200 -> 0.03735 | F17: =+P17 -> 2454.75 | G17: 0.1 | H17: 1.5 | I17: =+S$7 -> 17500 | J17: =+G17*H17*I17 -> 2625 | L17: USD | M17: =((1636500/5)/200)/17500 -> 0.093514286 | N17: 1.5 | O17: =VLOOKUP(L17,$R$6:$S$12,2,FALSE) -> 17500 | P17: =+M17*N17*O17 -> 2454.75
B18: AC004 | D18: Damper, Gear Housing Set : PA (齿轮） | E18: 0.12 | F18: =+P18 -> 20355 | G18: 0.8 | H18: 1.5 | I18: =+S$7 -> 17500 | J18: =+G18*H18*I18 -> 21000 | L18: USD | M18: =(16284000/1200)/17500 -> 0.77542857 | N18: 1.5 | O18: =VLOOKUP(L18,$R$6:$S$12,2,FALSE) -> 17500 | P18: =+M18*N18*O18 -> 20355
B19: S60 | D19: - Spacer | E19: 0.005
B20: CPS931 | D20: - Gear Cover | E20: 0.06
B21: CPS932 | D21: - Gear | E21: 0.04
B22: CPS933 | D22: - Blade/Gear Nylon Bush | E22: 0.005
B23: CPS934 | D23: - Blade/Gear Nylon Plug | E23: 0.01
B24: AC003 | D24: Damper, Handle : (铝执手) | E24: 0.37 | F24: =+P24 -> 117990 | G24: 4.4 | H24: 1.5 | I24: =+S$7 -> 17500 | J24: =+G24*H24*I24 -> 115500 | L24: USD | M24: =(11799000/150)/17500 -> 4.4948571 | N24: 1.5 | O24: =VLOOKUP(L24,$R$6:$S$12,2,FALSE) -> 17500 | P24: =+M24*N24*O24 -> 117990
B25: AC003.1 | D25: - Handle Base | E25: 0.13
B26: AC003.2 | D26: - Handle | E26: 0.11
B27: AC003.3 | D27: - Handle Turning Plug | E27: 0.07
B28: AC003.4 | D28: - Handle Lock Nut | E28: 0.05
B29: PMS80 | D29: Damper, Actuator Base : 90W x 150L | E29: 0.715 | F29: =+P29 -> 94500 | L29: USD | M29: 3.6 | N29: 1.5 | O29: =VLOOKUP(L29,$R$6:$S$12,2,FALSE) -> 17500 | P29: =+M29*N29*O29 -> 94500
B30: WN06 | C30: 0712-01-002-4 | D30: Nut, Wing M06 | E30: 0.008 | F30: =+P30 -> 4000 | L30: Rp | M30: 4000 | N30: 1 | O30: =VLOOKUP(L30,$R$6:$S$12,2,FALSE) -> 1 | P30: =+M30*N30*O30 -> 4000
B31: HB0620 | C31: 0701-03-003-4 | D31: Bolt, Hex M06 x 20 | E31: 0.002 | F31: =+P31 -> 1890 | L31: Rp | M31: 1890 | N31: 1 | O31: =VLOOKUP(L31,$R$6:$S$12,2,FALSE) -> 1 | P31: =+M31*N31*O31 -> 1890
B32: HB0820 | C32: 0701-04-003-4 | D32: Bolt, Hex M08 x 20 | E32: 0.011 | F32: =+P32 -> 3180 | L32: Rp | M32: 3180 | N32: 1 | O32: =VLOOKUP(L32,$R$6:$S$12,2,FALSE) -> 1 | P32: =+M32*N32*O32 -> 3180
B33: RB10 | D33: Ring Bush 10mm | E33: 0.005 | F33: =+P33 -> 100 | L33: Rp | M33: 100 | N33: 1 | O33: =VLOOKUP(L33,$R$6:$S$12,2,FALSE) -> 1 | P33: =+M33*N33*O33 -> 100
B34: SR05 | D34: Snap Ring #5 | E34: 0.002 | F34: =+P34 -> 100 | L34: Rp | M34: 100 | N34: 1 | O34: =VLOOKUP(L34,$R$6:$S$12,2,FALSE) -> 1 | P34: =+M34*N34*O34 -> 100
B35: 2Nm | D35: Actuator 2Nm, 70sec : 0.5m2 FA | E35: 0.5 | L35: USD
B36: 5Nm | D36: Actuator 5Nm, 90sec : 1.0m2 FA | E36: 0.5 | L36: USD
B37: 10Nm | D37: Actuator 10Nm, 100sec : 2.0m2 FA | E37: 0.5 | L37: USD
B38: 20Nm | D38: Actuator 20Nm, 120sec : 4.0m2 FA | E38: 0.9 | L38: USD
B39: 30Nm | D39: Actuator 30Nm, 150sec : 6.0m2 FA | E39: 1.4 | L39: USD
B40: 40Nm | D40: Actuator 40Nm, 180sec : 8.0m2 FA | E40: 1.4 | L40: USD
B41: Aluminium Profile VolumeDamper Cost Estimator
B42: W | C42: H | D42: <=== ENTER | E42: SELECTED ===> | P42: W | Q42: H | R42: 43088
B43: =B70 -> 500 | C43: =C70 -> 410 | D43: 1. Requested Opening Size : mmW x mmH | E43: a. Final Opening Size : mmW x mmH | P43: =+B43 -> 500 | Q43: =P44*100+10 -> 410 | R43: Rp/USD | S43: =+S$7 -> 17500
B44: =B71 -> 0 | D44: 2. Mode of Actuation : Manual=0, Motorized=1 | E44: b. No. of Damper Leaf : (Nx100) mmH / No. of Vertical Center Profile | P44: =ROUNDDOWN(C43/100,0) -> 4 | Q44: =IF(P43<=1400,0,IF(AND(P43>1400,P43<=2100),1,2)) -> 0 | R44: Rp/Euro | S44: =+S$8 -> 16079.99
E45: c. No. of Damper Leaf / Damper Leaf Length | P45: =P44*(Q44+1) -> 4 | Q45: =(P43-Q44*34.3)/(Q44+1) -> 500 | R45: Rp/RM | S45: =+S$9 -> 3429.69
E46: d. Recommended Actuator type : m2 x Nm | P46: =Q43/1000*P43/1000 -> 0.205 | Q46: =IF(P46<0.5,"2Nm",IF(AND(P46>0.5,P46<1),"5Nm",IF(AND(P46>1,P46<2),"10Nm",IF(AND(P46>2,P46<4),"20Nm",IF(AND(P46>4,P46<6),"30Nm",IF(AND(P46>6,P46<8),"40Nm","NA")))))) -> 2Nm | R46: Rp/Rmb | S46: =+S$10 -> 2192.36
R47: Rp/S$ | S47: =+S$11 -> 11262.76
B48: PickList | C48: P/Ninternal | D48: Item | E48: Dimension | J48: Usage | P48: Unit Weight | R48: Unit Cost
E49: UoM | F49: ODmm | G49: Tmm | H49: Wmm | I49: Lmm | J49: CF | K49: V/A/L | L49: n | M49: WF | N49: Npc | O49: Qty | P49: kGUoM | Q49: UW | R49: UC (Rp) | S49: Total(Rp)
B50: SH5037 | D50: =VLOOKUP($B50,$B$7:$S$40,3,FALSE) -> Damper Frame : Horizontal, T/B Profile -34.4T x 125W | E50: m | I50: =P43+34.4*2 -> 568.8 | J50: 1 | K50: =IF(F50>0,22/28*((F50/1000)^2-(F50/1000-2*G50/1000)^2)*H50/1000,IF(G50>0,G50/1000*H50/1000*I50/1000, IF(H50>0,H50/1000*I50/1000, IF(I50=0,1,I50/1000)))) -> 0.5688 | L50: =J50*K50 -> 0.5688 | M50: 1.05 | N50: 2 | O50: =L50*M50*N50 -> 1.19448 | P50: =IF($J50=1,VLOOKUP($B50,$B$7:$S$40,4,FALSE),1) -> 1.032 | Q50: =O50*P50/M50 -> 1.1740032 | R50: =VLOOKUP($B50,$B$7:$S$40,5,FALSE) -> 86114.208 | S50: =+O50*R50 -> 102861.7
B51: SH5038 | D51: =VLOOKUP($B51,$B$7:$S$40,3,FALSE) -> Damper Frame : Vertical, L/R Profile - 34.4T x 125W | E51: m | I51: =Q43 -> 410 | J51: 1 | K51: =IF(F51>0,22/28*((F51/1000)^2-(F51/1000-2*G51/1000)^2)*H51/1000,IF(G51>0,G51/1000*H51/1000*I51/1000, IF(H51>0,H51/1000*I51/1000, IF(I51=0,1,I51/1000)))) -> 0.41 | L51: =J51*K51 -> 0.41 | M51: 1.05 | N51: 2 | O51: =L51*M51*N51 -> 0.861 | P51: =IF($J51=1,VLOOKUP($B51,$B$7:$S$40,4,FALSE),1) -> 1.4 | Q51: =O51*P51/M51 -> 1.148 | R51: =VLOOKUP($B51,$B$7:$S$40,5,FALSE) -> 109200 | S51: =+O51*R51 -> 94021.2
B52: SH5039 | D52: =VLOOKUP($B52,$B$7:$S$40,3,FALSE) -> Damper Frame : Vertical, Center Profile - 34.4T x 125W | E52: m | I52: =Q43 -> 410 | J52: 1 | K52: =IF(F52>0,22/28*((F52/1000)^2-(F52/1000-2*G52/1000)^2)*H52/1000,IF(G52>0,G52/1000*H52/1000*I52/1000, IF(H52>0,H52/1000*I52/1000, IF(I52=0,1,I52/1000)))) -> 0.41 | L52: =J52*K52 -> 0.41 | M52: 1.05 | N52: =+Q44 -> 0 | O52: =L52*M52*N52 -> 0 | P52: =IF($J52=1,VLOOKUP($B52,$B$7:$S$40,4,FALSE),1) -> 1.759 | Q52: =O52*P52/M52 -> 0 | R52: =VLOOKUP($B52,$B$7:$S$40,5,FALSE) -> 214624.38 | S52: =+O52*R52 -> 0
B53: SH5040 | D53: =VLOOKUP($B53,$B$7:$S$40,3,FALSE) -> Damper, Leaf : Flat Blade Profile - 15.7T x 108W | E53: m | I53: =+Q45 -> 500 | J53: 1 | K53: =IF(F53>0,22/28*((F53/1000)^2-(F53/1000-2*G53/1000)^2)*H53/1000,IF(G53>0,G53/1000*H53/1000*Q45/1000, IF(H53>0,H53/1000*Q45/1000, IF(Q45=0,1,Q45/1000)))) -> 0.5 | L53: =J53*K53 -> 0.5 | M53: 1.05 | N53: =+P45 -> 4 | O53: =L53*M53*N53 -> 2.1 | P53: =IF($J53=1,VLOOKUP($B53,$B$7:$S$40,4,FALSE),1) -> 0.85 | Q53: =O53*P53/M53 -> 1.7 | R53: =VLOOKUP($B53,$B$7:$S$40,5,FALSE) -> 69353.625 | S53: =+O53*R53 -> 145642.61
B54: GA100 | D54: =VLOOKUP($B54,$B$7:$S$40,3,FALSE) -> Damper, Gasket : 200m/roll (密封胶条） | E54: m | I54: =Q45 -> 500 | J54: 1 | K54: =IF(F54>0,22/28*((F54/1000)^2-(F54/1000-2*G54/1000)^2)*H54/1000,IF(G54>0,G54/1000*H54/1000*I54/1000, IF(H54>0,H54/1000*I54/1000, IF(I54=0,1,I54/1000)))) -> 0.5 | L54: =J54*K54 -> 0.5 | M54: 1.05 | N54: =(N53*2)+((P46+1)*2) -> 10.41 | O54: =L54*M54*N54 -> 5.46525 | P54: =IF($J54=1,VLOOKUP($B54,$B$7:$S$40,4,FALSE),1) -> 0.03735 | Q54: =O54*P54/M54 -> 0.19440675 | R54: =VLOOKUP($B54,$B$7:$S$40,5,FALSE) -> 2454.75 | S54: =+O54*R54 -> 13415.822
B55: PMS80 | D55: =VLOOKUP($B55,$B$7:$S$40,3,FALSE) -> Damper, Actuator Base : 90W x 150L | E55: m | I55: 150 | J55: 1 | K55: =IF(F55>0,22/28*((F55/1000)^2-(F55/1000-2*G55/1000)^2)*H55/1000,IF(G55>0,G55/1000*H55/1000*I55/1000, IF(H55>0,H55/1000*I55/1000, IF(I55=0,1,I55/1000)))) -> 0.15 | L55: =J55*K55 -> 0.15 | M55: 1 | N55: =IF(B44=1,1,0) -> 0 | O55: =L55*M55*N55 -> 0 | P55: =IF($J55=1,VLOOKUP($B55,$B$7:$S$40,4,FALSE),1) -> 0.715 | Q55: =O55*P55/M55 -> 0 | R55: =VLOOKUP($B55,$B$7:$S$40,5,FALSE) -> 94500 | S55: =+O55*R55 -> 0
B56: AC004 | D56: =VLOOKUP($B56,$B$7:$S$40,3,FALSE) -> Damper, Gear Housing Set : PA (齿轮） | E56: Set | J56: 1 | K56: =IF(F56>0,22/28*((F56/1000)^2-(F56/1000-2*G56/1000)^2)*H56/1000,IF(G56>0,G56/1000*H56/1000*I56/1000, IF(H56>0,H56/1000*I56/1000, IF(I56=0,1,I56/1000)))) -> 1 | L56: =J56*K56 -> 1 | M56: 1 | N56: =+N53 -> 4 | O56: =L56*M56*N56 -> 4 | P56: =IF($J56=1,VLOOKUP($B56,$B$7:$S$40,4,FALSE),1) -> 0.12 | Q56: =O56*P56/M56 -> 0.48 | R56: =VLOOKUP($B56,$B$7:$S$40,5,FALSE) -> 20355 | S56: =+O56*R56 -> 81420
B57: AC003 | D57: =VLOOKUP($B57,$B$7:$S$40,3,FALSE) -> Damper, Handle : (铝执手) | E57: Set | J57: 1 | K57: =IF(F57>0,22/28*((F57/1000)^2-(F57/1000-2*G57/1000)^2)*H57/1000,IF(G57>0,G57/1000*H57/1000*I57/1000, IF(H57>0,H57/1000*I57/1000, IF(I57=0,1,I57/1000)))) -> 1 | L57: =J57*K57 -> 1 | M57: 1 | N57: =IF(B44=0,1,0) -> 1 | O57: =L57*M57*N57 -> 1 | P57: =IF($J57=1,VLOOKUP($B57,$B$7:$S$40,4,FALSE),1) -> 0.37 | Q57: =O57*P57/M57 -> 0.37 | R57: =VLOOKUP($B57,$B$7:$S$40,5,FALSE) -> 117990 | S57: =+O57*R57 -> 117990
B58: =+Q$46 -> 2Nm | D58: =VLOOKUP($B58,$B$7:$S$40,3,FALSE) -> Actuator 2Nm, 70sec : 0.5m2 FA | E58: Set | J58: 1 | K58: =IF(F58>0,22/28*((F58/1000)^2-(F58/1000-2*G58/1000)^2)*H58/1000,IF(G58>0,G58/1000*H58/1000*I58/1000, IF(H58>0,H58/1000*I58/1000, IF(I58=0,1,I58/1000)))) -> 1 | L58: =J58*K58 -> 1 | M58: 1 | N58: =IF(B44=1,1,0) -> 0 | O58: =L58*M58*N58 -> 0 | P58: =IF($J58=1,VLOOKUP($B58,$B$7:$S$40,4,FALSE),1) -> 0.5 | Q58: =O58*P58/M58 -> 0 | R58: =VLOOKUP($B58,$B$7:$S$40,5,FALSE) -> 0 | S58: =+O58*R58 -> 0
E59: Unit Weight / Unit Cost | Q59: =SUM(Q50:Q58) -> 5.0664099 | S59: =SUM(S50:S58) -> 555351.33 | T59: =+S59/S92 -> 2.254808
E60: Gross Contribution | R60: 0.4 | S60: =+S61-S59 -> 370234.22
E61: Unit Price (Rp) | S61: =+S59/(1-R60) -> 925585.56 | T61: =ROUNDUP(S61,-5) -> 1000000
H63: Class | I63: Section | J63: FA(m2) | K63: USD/m2 | L63: FOB | M63: LF | N63: Rp/USD | S63: UC
E64: Arosio Cost | H64: 2 | I64: =Q44+1 -> 1 | J64: =P43/1000*Q43/1000 -> 0.205 | K64: =IF(I64=1,117,IF(I64=2,217,IF(I64=3,315,"NA"))) -> 117 | L64: =+J64*K64 -> 23.985 | M64: 1.8 | N64: =+S43 -> 17500 | S64: =+L64*M64*N64 -> 755527.5
H65: 3 | I65: =+I64 -> 1 | J65: =+J64 -> 0.205 | K65: =IF(I65=1,135,IF(I65=2,250,IF(I65=3,362,"NA"))) -> 135 | L65: =+J65*K65 -> 27.675 | M65: 1.8 | N65: =+N64 -> 17500 | S65: =+L65*M65*N65 -> 871762.5
H66: 4 | I66: =+I64 -> 1 | J66: =+J64 -> 0.205 | K66: =IF(I66=1,310,"NA") -> 310 | L66: =+J66*K66 -> 63.55 | M66: 1.8 | N66: =+N64 -> 17500 | S66: =+L66*M66*N66 -> 2001825
B68: Sheet Metal VolumeDamper Cost Estimator
B69: W | C69: H | D69: <=== ENTER | E69: SELECTED ===> | P69: W | Q69: H | R69: 43088
B70: 500 | C70: 410 | D70: 1. Requested Opening Size : mmW x mmH | E70: a. Final Opening Size : mmW x mmH | P70: =+B70 -> 500 | Q70: =P71*100+10 -> 410 | R70: Rp/USD | S70: =+S$7 -> 17500
B71: 0 | D71: 2. Mode of Actuation : Manual=0, Motorized=1 | E71: b. No. of Damper Leaf : (Nx100) mmH / No. of Vertical Center Profile | P71: =ROUNDDOWN(C70/100,0) -> 4 | Q71: =IF(P70<=1400,0,IF(AND(P70>1400,P70<=2100),1,2)) -> 0 | R71: Rp/Euro | S71: =+S$8 -> 16079.99
E72: c. No. of Damper Leaf / Damper Leaf Length | P72: =P71*(Q71+1) -> 4 | Q72: =(P70-Q71*34.3)/(Q71+1) -> 500 | R72: Rp/RM | S72: =+S$9 -> 3429.69
E73: d. Recommended Actuator type : m2 x Nm | P73: =Q70/1000*P70/1000 -> 0.205 | Q73: =IF(P73<0.5,"2Nm",IF(AND(P73>0.5,P73<1),"5Nm",IF(AND(P73>1,P73<2),"10Nm",IF(AND(P73>2,P73<4),"20Nm",IF(AND(P73>4,P73<6),"30Nm",IF(AND(P73>6,P73<8),"40Nm","NA")))))) -> 2Nm | R73: Rp/Rmb | S73: =+S$10 -> 2192.36
R74: Rp/S$ | S74: =+S$11 -> 11262.76
B75: PickList | C75: P/Ninternal | D75: Item | E75: Dimension | J75: Usage | P75: Unit Weight | R75: Unit Cost
E76: UoM | F76: ODmm | G76: Tmm | H76: Wmm | I76: Lmm | J76: CF | K76: V/A/L | L76: n | M76: WF | N76: Npc | O76: Qty | P76: kGUoM | Q76: UW | R76: UC (Rp) | S76: Total(Rp)
B77: Al6065 | D77: Damper Frame, Vertical L/R | E77: kG | G77: 1 | H77: 176.5 | I77: =+Q70+30*2 -> 470 | J77: =VLOOKUP($B77,$B$7:$S$40,4,FALSE) -> 2720 | K77: =IF(F77>0,22/28*((F77/1000)^2-(F77/1000-2*G77/1000)^2)*H77/1000,IF(G77>0,G77/1000*H77/1000*I77/1000, IF(H77>0,H77/1000*I77/1000, IF(I77=0,1,I77/1000)))) -> 8.2955e-05 | L77: =J77*K77 -> 0.2256376 | M77: 1.1 | N77: 2 | O77: =L77*M77*N77 -> 0.49640272 | P77: =IF($J77=1,VLOOKUP($B77,$B$7:$S$40,4,FALSE),1) -> 1 | Q77: =O77*P77/M77 -> 0.4512752 | R77: =VLOOKUP($B77,$B$7:$S$40,5,FALSE) -> 83085 | S77: =+O77*R77 -> 41243.62
B78: Al6065 | D78: Damper Frame, Horizontal T/B | E78: kG | G78: 1 | H78: 176.5 | I78: =+P70 -> 500 | J78: =VLOOKUP($B78,$B$7:$S$40,4,FALSE) -> 2720 | K78: =IF(F78>0,22/28*((F78/1000)^2-(F78/1000-2*G78/1000)^2)*H78/1000,IF(G78>0,G78/1000*H78/1000*I78/1000, IF(H78>0,H78/1000*I78/1000, IF(I78=0,1,I78/1000)))) -> 8.825e-05 | L78: =J78*K78 -> 0.24004 | M78: 1.1 | N78: 2 | O78: =L78*M78*N78 -> 0.528088 | P78: =IF($J78=1,VLOOKUP($B78,$B$7:$S$40,4,FALSE),1) -> 1 | Q78: =O78*P78/M78 -> 0.48008 | R78: =VLOOKUP($B78,$B$7:$S$40,5,FALSE) -> 83085 | S78: =+O78*R78 -> 43876.191
B79: Al6065 | D79: Damper Frame, Vertical Center | E79: kG | G79: 1 | H79: 176.5 | I79: =+Q70 -> 410 | J79: =VLOOKUP($B79,$B$7:$S$40,4,FALSE) -> 2720 | K79: =IF(F79>0,22/28*((F79/1000)^2-(F79/1000-2*G79/1000)^2)*H79/1000,IF(G79>0,G79/1000*H79/1000*I79/1000, IF(H79>0,H79/1000*I79/1000, IF(I79=0,1,I79/1000)))) -> 7.2365e-05 | L79: =J79*K79 -> 0.1968328 | M79: 1.1 | N79: =IF(P$70>1000,1,0) -> 0 | O79: =L79*M79*N79 -> 0 | P79: =IF($J79=1,VLOOKUP($B79,$B$7:$S$40,4,FALSE),1) -> 1 | Q79: =O79*P79/M79 -> 0 | R79: =VLOOKUP($B79,$B$7:$S$40,5,FALSE) -> 83085 | S79: =+O79*R79 -> 0
B80: Al6065 | D80: Damper Blade, Horizontal | E80: kG | G80: 1 | H80: 123.2 | I80: =+Q72 -> 500 | J80: =VLOOKUP($B80,$B$7:$S$40,4,FALSE) -> 2720 | K80: =IF(F80>0,22/28*((F80/1000)^2-(F80/1000-2*G80/1000)^2)*H80/1000,IF(G80>0,G80/1000*H80/1000*I80/1000, IF(H80>0,H80/1000*I80/1000, IF(I80=0,1,I80/1000)))) -> 6.16e-05 | L80: =J80*K80 -> 0.167552 | M80: 1.1 | N80: =+P$71 -> 4 | O80: =L80*M80*N80 -> 0.7372288 | P80: =IF($J80=1,VLOOKUP($B80,$B$7:$S$40,4,FALSE),1) -> 1 | Q80: =O80*P80/M80 -> 0.670208 | R80: =VLOOKUP($B80,$B$7:$S$40,5,FALSE) -> 83085 | S80: =+O80*R80 -> 61252.655
B81: Al6065 | D81: Stopper Blade, Horizontal | E81: kG | G81: 1 | H81: 33.3 | I81: =+Q72 -> 500 | J81: =VLOOKUP($B81,$B$7:$S$40,4,FALSE) -> 2720 | K81: =IF(F81>0,22/28*((F81/1000)^2-(F81/1000-2*G81/1000)^2)*H81/1000,IF(G81>0,G81/1000*H81/1000*I81/1000, IF(H81>0,H81/1000*I81/1000, IF(I81=0,1,I81/1000)))) -> 1.665e-05 | L81: =J81*K81 -> 0.045288 | M81: 1.1 | N81: 2 | O81: =L81*M81*N81 -> 0.0996336 | P81: =IF($J81=1,VLOOKUP($B81,$B$7:$S$40,4,FALSE),1) -> 1 | Q81: =O81*P81/M81 -> 0.090576 | R81: =VLOOKUP($B81,$B$7:$S$40,5,FALSE) -> 83085 | S81: =+O81*R81 -> 8278.0577
B82: Al6065 | D82: Stopper Box Adjustment | E82: kG | G82: 1 | H82: 90 | I82: 156.5 | J82: =VLOOKUP($B82,$B$7:$S$40,4,FALSE) -> 2720 | K82: =IF(F82>0,22/28*((F82/1000)^2-(F82/1000-2*G82/1000)^2)*H82/1000,IF(G82>0,G82/1000*H82/1000*I82/1000, IF(H82>0,H82/1000*I82/1000, IF(I82=0,1,I82/1000)))) -> 1.4085e-05 | L82: =J82*K82 -> 0.0383112 | M82: 1.1 | N82: 1 | O82: =L82*M82*N82 -> 0.04214232 | P82: =IF($J82=1,VLOOKUP($B82,$B$7:$S$40,4,FALSE),1) -> 1 | Q82: =O82*P82/M82 -> 0.0383112 | R82: =VLOOKUP($B82,$B$7:$S$40,5,FALSE) -> 83085 | S82: =+O82*R82 -> 3501.3947
B83: Al6065 | D83: Turning Arm#1 | E83: kG | G83: 3 | H83: 25 | I83: 60 | J83: =VLOOKUP($B83,$B$7:$S$40,4,FALSE) -> 2720 | K83: =IF(F83>0,22/28*((F83/1000)^2-(F83/1000-2*G83/1000)^2)*H83/1000,IF(G83>0,G83/1000*H83/1000*I83/1000, IF(H83>0,H83/1000*I83/1000, IF(I83=0,1,I83/1000)))) -> 4.5e-06 | L83: =J83*K83 -> 0.01224 | M83: 1.1 | N83: =P$71-2 -> 2 | O83: =L83*M83*N83 -> 0.026928 | P83: =IF($J83=1,VLOOKUP($B83,$B$7:$S$40,4,FALSE),1) -> 1 | Q83: =O83*P83/M83 -> 0.02448 | R83: =VLOOKUP($B83,$B$7:$S$40,5,FALSE) -> 83085 | S83: =+O83*R83 -> 2237.3129
B84: Al6065 | D84: Turning Arm#2 | E84: kG | G84: 3 | H84: 25 | I84: 140 | J84: =VLOOKUP($B84,$B$7:$S$40,4,FALSE) -> 2720 | K84: =IF(F84>0,22/28*((F84/1000)^2-(F84/1000-2*G84/1000)^2)*H84/1000,IF(G84>0,G84/1000*H84/1000*I84/1000, IF(H84>0,H84/1000*I84/1000, IF(I84=0,1,I84/1000)))) -> 1.05e-05 | L84: =J84*K84 -> 0.02856 | M84: 1.1 | N84: 1 | O84: =L84*M84*N84 -> 0.031416 | P84: =IF($J84=1,VLOOKUP($B84,$B$7:$S$40,4,FALSE),1) -> 1 | Q84: =O84*P84/M84 -> 0.02856 | R84: =VLOOKUP($B84,$B$7:$S$40,5,FALSE) -> 83085 | S84: =+O84*R84 -> 2610.1984
B85: Al6065 | D85: Turning Arm#3 | E85: kG | G85: 3 | H85: 25 | I85: =100*(P$71-1)+15*2 -> 330 | J85: =VLOOKUP($B85,$B$7:$S$40,4,FALSE) -> 2720 | K85: =IF(F85>0,22/28*((F85/1000)^2-(F85/1000-2*G85/1000)^2)*H85/1000,IF(G85>0,G85/1000*H85/1000*I85/1000, IF(H85>0,H85/1000*I85/1000, IF(I85=0,1,I85/1000)))) -> 2.475e-05 | L85: =J85*K85 -> 0.06732 | M85: 1.1 | N85: 1 | O85: =L85*M85*N85 -> 0.074052 | P85: =IF($J85=1,VLOOKUP($B85,$B$7:$S$40,4,FALSE),1) -> 1 | Q85: =O85*P85/M85 -> 0.06732 | R85: =VLOOKUP($B85,$B$7:$S$40,5,FALSE) -> 83085 | S85: =+O85*R85 -> 6152.6104
B86: Al6065 | D86: Shaft 10mmOD | E86: kG | F86: 10 | G86: 5 | H86: =+$P$70+40*2 -> 580 | J86: =VLOOKUP($B86,$B$7:$S$40,4,FALSE) -> 2720 | K86: =IF(F86>0,22/28*((F86/1000)^2-(F86/1000-2*G86/1000)^2)*H86/1000,IF(G86>0,G86/1000*H86/1000*I86/1000, IF(H86>0,H86/1000*I86/1000, IF(I86=0,1,I86/1000)))) -> 4.5571429e-05 | L86: =J86*K86 -> 0.12395429 | M86: 1.1 | N86: =+P$71 -> 4 | O86: =L86*M86*N86 -> 0.54539886 | P86: =IF($J86=1,VLOOKUP($B86,$B$7:$S$40,4,FALSE),1) -> 1 | Q86: =O86*P86/M86 -> 0.49581714 | R86: =VLOOKUP($B86,$B$7:$S$40,5,FALSE) -> 83085 | S86: =+O86*R86 -> 45314.464
B87: WN06 | D87: Wing Nut M6 | E87: Pc | J87: 1 | K87: =IF(F87>0,22/28*((F87/1000)^2-(F87/1000-2*G87/1000)^2)*H87/1000,IF(G87>0,G87/1000*H87/1000*I87/1000, IF(H87>0,H87/1000*I87/1000, IF(I87=0,1,I87/1000)))) -> 1 | L87: =J87*K87 -> 1 | M87: 1 | N87: 1 | O87: =L87*M87*N87 -> 1 | P87: =IF($J87=1,VLOOKUP($B87,$B$7:$S$40,4,FALSE),1) -> 0.008 | Q87: =O87*P87/M87 -> 0.008 | R87: =VLOOKUP($B87,$B$7:$S$40,5,FALSE) -> 4000 | S87: =+O87*R87 -> 4000
B88: HB0620 | D88: Hex Bolt M6 x 20 | E88: Pc | J88: 1 | K88: =IF(F88>0,22/28*((F88/1000)^2-(F88/1000-2*G88/1000)^2)*H88/1000,IF(G88>0,G88/1000*H88/1000*I88/1000, IF(H88>0,H88/1000*I88/1000, IF(I88=0,1,I88/1000)))) -> 1 | L88: =J88*K88 -> 1 | M88: 1 | N88: 1 | O88: =L88*M88*N88 -> 1 | P88: =IF($J88=1,VLOOKUP($B88,$B$7:$S$40,4,FALSE),1) -> 0.002 | Q88: =O88*P88/M88 -> 0.002 | R88: =VLOOKUP($B88,$B$7:$S$40,5,FALSE) -> 1890 | S88: =+O88*R88 -> 1890
B89: HB0820 | D89: Bush 3/8" | E89: Pc | J89: 1 | K89: =IF(F89>0,22/28*((F89/1000)^2-(F89/1000-2*G89/1000)^2)*H89/1000,IF(G89>0,G89/1000*H89/1000*I89/1000, IF(H89>0,H89/1000*I89/1000, IF(I89=0,1,I89/1000)))) -> 1 | L89: =J89*K89 -> 1 | M89: 1 | N89: =P$71*2 -> 8 | O89: =L89*M89*N89 -> 8 | P89: =IF($J89=1,VLOOKUP($B89,$B$7:$S$40,4,FALSE),1) -> 0.011 | Q89: =O89*P89/M89 -> 0.088 | R89: =VLOOKUP($B89,$B$7:$S$40,5,FALSE) -> 3180 | S89: =+O89*R89 -> 25440
B90: RB10 | D90: Hex Bolt M8 x 20 | E90: Pc | J90: 1 | K90: =IF(F90>0,22/28*((F90/1000)^2-(F90/1000-2*G90/1000)^2)*H90/1000,IF(G90>0,G90/1000*H90/1000*I90/1000, IF(H90>0,H90/1000*I90/1000, IF(I90=0,1,I90/1000)))) -> 1 | L90: =J90*K90 -> 1 | M90: 1 | N90: 1 | O90: =L90*M90*N90 -> 1 | P90: =IF($J90=1,VLOOKUP($B90,$B$7:$S$40,4,FALSE),1) -> 0.005 | Q90: =O90*P90/M90 -> 0.005 | R90: =VLOOKUP($B90,$B$7:$S$40,5,FALSE) -> 100 | S90: =+O90*R90 -> 100
B91: SR05 | D91: Snap Ring #5 | E91: Pc | J91: 1 | K91: =IF(F91>0,22/28*((F91/1000)^2-(F91/1000-2*G91/1000)^2)*H91/1000,IF(G91>0,G91/1000*H91/1000*I91/1000, IF(H91>0,H91/1000*I91/1000, IF(I91=0,1,I91/1000)))) -> 1 | L91: =J91*K91 -> 1 | M91: 1 | N91: =P$71 -> 4 | O91: =L91*M91*N91 -> 4 | P91: =IF($J91=1,VLOOKUP($B91,$B$7:$S$40,4,FALSE),1) -> 0.002 | Q91: =O91*P91/M91 -> 0.008 | R91: =VLOOKUP($B91,$B$7:$S$40,5,FALSE) -> 100 | S91: =+O91*R91 -> 400
E92: Unit Weight / Unit Cost | Q92: =SUM(Q77:Q91) -> 2.4576275 | S92: =SUM(S77:S91) -> 246296.5 | T92: 1
E93: Gross Contribution | R93: 0.4 | S93: =+S94-S92 -> 164197.67
E94: Unit Price (Rp) | S94: =+S92/(1-R93) -> 410494.17
S95: =ROUNDUP(S94,-5) -> 500000

Sheet VolDamperCost2023 FA 
B1: ThermalTrue® | BB1: 11111111111111111111111111111111111111111111111111111111111111111111111111111111111111111111111111111111111111111111111111111111111111111111111111111111111111111111111111111111111111111111111111111111111111111111111111111111111111111111111111111111111111111111111111111111111111111111111111111111111111111111111111111111111111111111111111111111111111111111111111111111111111111111111111111111111111111111111111111111111111111111111111111111111111111111111111111111111111111111111111111111111111111111111111111111111111111111111111111111111111
B2: Project: | C2: Yudi
B3: Date: | C3: =TODAY() -> 46089
B4: Rp/USD: | C4: =+S43 -> 17500
B5: Material CostList Volume Damper PS125
B6: PickList | C6: P/Ninternal | D6: Parts List : Frame | E6: UW | F6: UC(Rp) | G6: FOB | H6: LF | I6: Fx | J6: UC | L6: Cy | M6: FOB | N6: LF | O6: Fx | P6: UC | R6: Rp | S6: 1
B7: SPHC | C7: 0101-04-000-0 | D7: SPHC (Hot rolled) 1.0mm x 4' x 8' x7700kG/m3 | E7: 7700 | F7: =+P7 -> 18000 | L7: Rp | M7: 18000 | N7: 1 | O7: =VLOOKUP(L7,$R$6:$S$12,2,FALSE) -> 1 | P7: =+M7*N7*O7 -> 18000 | R7: USD | S7: 17500
B8: SGCC | C8: 0101-02-000-0 | D8: SGCC (GI) 1.0mm x 4' x 8' x 8030kG/m3 | E8: 8030 | F8: =+P8 -> 30000 | L8: Rp | M8: 30000 | N8: 1 | O8: =VLOOKUP(L8,$R$6:$S$12,2,FALSE) -> 1 | P8: =+M8*N8*O8 -> 30000 | R8: Euro | S8: 16079.99
B9: SUS304 | C9: 0101-05-000-0 | D9: Stainless Stl (SUS304) 1.0mm x 4' x 8' x 7800kG/m3 | E9: 7800 | F9: =+P9 -> 55000 | L9: Rp | M9: 55000 | N9: 1 | O9: =VLOOKUP(L9,$R$6:$S$12,2,FALSE) -> 1 | P9: =+M9*N9*O9 -> 55000 | R9: RM | S9: 3429.69
B10: SUS36L | C10: 0101-06-000-0 | D10: Stainless Stl (SUS316L) 1.0mm x 4' x 8' x 8000kG/m3 | E10: 8000 | F10: =+P10 -> 55000 | L10: Rp | M10: 55000 | N10: 1 | O10: =VLOOKUP(L10,$R$6:$S$12,2,FALSE) -> 1 | P10: =+M10*N10*O10 -> 55000 | R10: Rmb | S10: 2192.36
B11: Al6065 | C11: 0101-07-000-0 | D11: Aluminium 6065 1.0mm x 4' x 8' x 2720kG/m3 | E11: 2720 | F11: =+P11 -> 83085 | L11: Rp | M11: 83085 | N11: 1 | O11: =VLOOKUP(L11,$R$6:$S$12,2,FALSE) -> 1 | P11: =+M11*N11*O11 -> 83085 | R11: S$ | S11: 11262.76
B12: ET6065 | C12: 0102-00-000-0 | D12: Aluminium Extrusion 6065-T5, NA | E12: 1 | F12: =+P12 -> 78000 | L12: Rp | M12: 78000 | N12: 1 | O12: =VLOOKUP(L12,$R$6:$S$12,2,FALSE) -> 1 | P12: =+M12*N12*O12 -> 78000 | R12: Rs | S12: 183.43
B13: SH5037 | D13: Damper Frame : Horizontal, T/B Profile -34.4T x 125W | E13: 1.032 | F13: =+P13 -> 86114.208 | G13: =3.2*E13 -> 3.3024 | H13: 1.5 | I13: =+S$7 -> 17500 | J13: =+G13*H13*I13 -> 86688 | L13: Rp | M13: =+E13*(((10430500/25)/6)*1.2) -> 86114.208 | N13: 1 | O13: =VLOOKUP(L13,$R$6:$S$12,2,FALSE) -> 1 | P13: =+M13*N13*O13 -> 86114.208
B14: SH5038 | D14: Damper Frame : Vertical, L/R Profile - 34.4T x 125W | E14: 1.4 | F14: =+P14 -> 109200 | G14: =3.2*E14 -> 4.48 | H14: 1.5 | I14: =+S$7 -> 17500 | J14: =+G14*H14*I14 -> 117600 | L14: Rp | M14: =+E14*M$12 -> 109200 | N14: 1 | O14: =VLOOKUP(L14,$R$6:$S$12,2,FALSE) -> 1 | P14: =+M14*N14*O14 -> 109200
B15: SH5039 | D15: Damper Frame : Vertical, Center Profile - 34.4T x 125W | E15: 1.759 | F15: =+P15 -> 214624.38 | G15: =3.2*E15 -> 5.6288 | H15: 1.5 | I15: =+S$7 -> 17500 | J15: =+G15*H15*I15 -> 147756 | L15: Rp | M15: =+E15*((14641800/20)/6) -> 214624.38 | N15: 1 | O15: =VLOOKUP(L15,$R$6:$S$12,2,FALSE) -> 1 | P15: =+M15*N15*O15 -> 214624.38
B16: SH5040 | D16: Damper, Leaf : Flat Blade Profile - 15.7T x 108W | E16: 0.85 | F16: =+P16 -> 69353.625 | G16: =3.2*E16 -> 2.72 | H16: 1.5 | I16: =+S$7 -> 17500 | J16: =+G16*H16*I16 -> 71400 | L16: Rp | M16: =+E16*(((17950350/55)/6)*1.5) -> 69353.625 | N16: 1 | O16: =VLOOKUP(L16,$R$6:$S$12,2,FALSE) -> 1 | P16: =+M16*N16*O16 -> 69353.625
B17: GA100 | D17: Damper, Gasket : 200m/roll (密封胶条） | E17: =7.47/200 -> 0.03735 | F17: =+P17 -> 2454.75 | G17: 0.1 | H17: 1.5 | I17: =+S$7 -> 17500 | J17: =+G17*H17*I17 -> 2625 | L17: USD | M17: =((1636500/5)/200)/17500 -> 0.093514286 | N17: 1.5 | O17: =VLOOKUP(L17,$R$6:$S$12,2,FALSE) -> 17500 | P17: =+M17*N17*O17 -> 2454.75
B18: AC004 | D18: Damper, Gear Housing Set : PA (齿轮） | E18: 0.12 | F18: =+P18 -> 20355 | G18: 0.8 | H18: 1.5 | I18: =+S$7 -> 17500 | J18: =+G18*H18*I18 -> 21000 | L18: USD | M18: =(16284000/1200)/17500 -> 0.77542857 | N18: 1.5 | O18: =VLOOKUP(L18,$R$6:$S$12,2,FALSE) -> 17500 | P18: =+M18*N18*O18 -> 20355
B19: S60 | D19: - Spacer | E19: 0.005
B20: CPS931 | D20: - Gear Cover | E20: 0.06
B21: CPS932 | D21: - Gear | E21: 0.04
B22: CPS933 | D22: - Blade/Gear Nylon Bush | E22: 0.005
B23: CPS934 | D23: - Blade/Gear Nylon Plug | E23: 0.01
B24: AC003 | D24: Damper, Handle : (铝执手) | E24: 0.37 | F24: =+P24 -> 117990 | G24: 4.4 | H24: 1.5 | I24: =+S$7 -> 17500 | J24: =+G24*H24*I24 -> 115500 | L24: USD | M24: =(11799000/150)/17500 -> 4.4948571 | N24: 1.5 | O24: =VLOOKUP(L24,$R$6:$S$12,2,FALSE) -> 17500 | P24: =+M24*N24*O24 -> 117990
B25: AC003.1 | D25: - Handle Base | E25: 0.13
B26: AC003.2 | D26: - Handle | E26: 0.11
B27: AC003.3 | D27: - Handle Turning Plug | E27: 0.07
B28: AC003.4 | D28: - Handle Lock Nut | E28: 0.05
B29: PMS80 | D29: Damper, Actuator Base : 90W x 150L | E29: 0.715 | F29: =+P29 -> 94500 | L29: USD | M29: 3.6 | N29: 1.5 | O29: =VLOOKUP(L29,$R$6:$S$12,2,FALSE) -> 17500 | P29: =+M29*N29*O29 -> 94500
B30: WN06 | C30: 0712-01-002-4 | D30: Nut, Wing M06 | E30: 0.008 | F30: =+P30 -> 4000 | L30: Rp | M30: 4000 | N30: 1 | O30: =VLOOKUP(L30,$R$6:$S$12,2,FALSE) -> 1 | P30: =+M30*N30*O30 -> 4000
B31: HB0620 | C31: 0701-03-003-4 | D31: Bolt, Hex M06 x 20 | E31: 0.002 | F31: =+P31 -> 1890 | L31: Rp | M31: 1890 | N31: 1 | O31: =VLOOKUP(L31,$R$6:$S$12,2,FALSE) -> 1 | P31: =+M31*N31*O31 -> 1890
B32: HB0820 | C32: 0701-04-003-4 | D32: Bolt, Hex M08 x 20 | E32: 0.011 | F32: =+P32 -> 3180 | L32: Rp | M32: 3180 | N32: 1 | O32: =VLOOKUP(L32,$R$6:$S$12,2,FALSE) -> 1 | P32: =+M32*N32*O32 -> 3180
B33: RB10 | D33: Ring Bush 10mm | E33: 0.005 | F33: =+P33 -> 100 | L33: Rp | M33: 100 | N33: 1 | O33: =VLOOKUP(L33,$R$6:$S$12,2,FALSE) -> 1 | P33: =+M33*N33*O33 -> 100
B34: SR05 | D34: Snap Ring #5 | E34: 0.002 | F34: =+P34 -> 100 | L34: Rp | M34: 100 | N34: 1 | O34: =VLOOKUP(L34,$R$6:$S$12,2,FALSE) -> 1 | P34: =+M34*N34*O34 -> 100
B35: 2Nm | D35: Actuator 2Nm, 70sec : 0.5m2 FA | E35: 0.5 | L35: USD
B36: 5Nm | D36: Actuator 5Nm, 90sec : 1.0m2 FA | E36: 0.5 | L36: USD
B37: 10Nm | D37: Actuator 10Nm, 100sec : 2.0m2 FA | E37: 0.5 | L37: USD
B38: 20Nm | D38: Actuator 20Nm, 120sec : 4.0m2 FA | E38: 0.9 | L38: USD
B39: 30Nm | D39: Actuator 30Nm, 150sec : 6.0m2 FA | E39: 1.4 | L39: USD
B40: 40Nm | D40: Actuator 40Nm, 180sec : 8.0m2 FA | E40: 1.4 | L40: USD
B41: Aluminium Profile VolumeDamper Cost Estimator
B42: W | C42: H | D42: <=== ENTER | E42: SELECTED ===> | P42: W | Q42: H | R42: 43088
B43: =B70 -> 500 | C43: =C70 -> 410 | D43: 1. Requested Opening Size : mmW x mmH | E43: a. Final Opening Size : mmW x mmH | P43: =+B43 -> 500 | Q43: =P44*100+10 -> 410 | R43: Rp/USD | S43: =+S$7 -> 17500
B44: =B71 -> 0 | D44: 2. Mode of Actuation : Manual=0, Motorized=1 | E44: b. No. of Damper Leaf : (Nx100) mmH / No. of Vertical Center Profile | P44: =ROUNDDOWN(C43/100,0) -> 4 | Q44: =IF(P43<=1400,0,IF(AND(P43>1400,P43<=2100),1,2)) -> 0 | R44: Rp/Euro | S44: =+S$8 -> 16079.99
E45: c. No. of Damper Leaf / Damper Leaf Length | P45: =P44*(Q44+1) -> 4 | Q45: =(P43-Q44*34.3)/(Q44+1) -> 500 | R45: Rp/RM | S45: =+S$9 -> 3429.69
E46: d. Recommended Actuator type : m2 x Nm | P46: =Q43/1000*P43/1000 -> 0.205 | Q46: =IF(P46<0.5,"2Nm",IF(AND(P46>0.5,P46<1),"5Nm",IF(AND(P46>1,P46<2),"10Nm",IF(AND(P46>2,P46<4),"20Nm",IF(AND(P46>4,P46<6),"30Nm",IF(AND(P46>6,P46<8),"40Nm","NA")))))) -> 2Nm | R46: Rp/Rmb | S46: =+S$10 -> 2192.36
R47: Rp/S$ | S47: =+S$11 -> 11262.76
B48: PickList | C48: P/Ninternal | D48: Item | E48: Dimension | J48: Usage | P48: Unit Weight | R48: Unit Cost
E49: UoM | F49: ODmm | G49: Tmm | H49: Wmm | I49: Lmm | J49: CF | K49: V/A/L | L49: n | M49: WF | N49: Npc | O49: Qty | P49: kGUoM | Q49: UW | R49: UC (Rp) | S49: Total(Rp)
B50: SH5037 | D50: =VLOOKUP($B50,$B$7:$S$40,3,FALSE) -> Damper Frame : Horizontal, T/B Profile -34.4T x 125W | E50: m | I50: =P43+34.4*2 -> 568.8 | J50: 1 | K50: =IF(F50>0,22/28*((F50/1000)^2-(F50/1000-2*G50/1000)^2)*H50/1000,IF(G50>0,G50/1000*H50/1000*I50/1000, IF(H50>0,H50/1000*I50/1000, IF(I50=0,1,I50/1000)))) -> 0.5688 | L50: =J50*K50 -> 0.5688 | M50: 1.05 | N50: 2 | O50: =L50*M50*N50 -> 1.19448 | P50: =IF($J50=1,VLOOKUP($B50,$B$7:$S$40,4,FALSE),1) -> 1.032 | Q50: =O50*P50/M50 -> 1.1740032 | R50: =VLOOKUP($B50,$B$7:$S$40,5,FALSE) -> 86114.208 | S50: =+O50*R50 -> 102861.7
B51: SH5038 | D51: =VLOOKUP($B51,$B$7:$S$40,3,FALSE) -> Damper Frame : Vertical, L/R Profile - 34.4T x 125W | E51: m | I51: =Q43 -> 410 | J51: 1 | K51: =IF(F51>0,22/28*((F51/1000)^2-(F51/1000-2*G51/1000)^2)*H51/1000,IF(G51>0,G51/1000*H51/1000*I51/1000, IF(H51>0,H51/1000*I51/1000, IF(I51=0,1,I51/1000)))) -> 0.41 | L51: =J51*K51 -> 0.41 | M51: 1.05 | N51: 2 | O51: =L51*M51*N51 -> 0.861 | P51: =IF($J51=1,VLOOKUP($B51,$B$7:$S$40,4,FALSE),1) -> 1.4 | Q51: =O51*P51/M51 -> 1.148 | R51: =VLOOKUP($B51,$B$7:$S$40,5,FALSE) -> 109200 | S51: =+O51*R51 -> 94021.2
B52: SH5039 | D52: =VLOOKUP($B52,$B$7:$S$40,3,FALSE) -> Damper Frame : Vertical, Center Profile - 34.4T x 125W | E52: m | I52: =Q43 -> 410 | J52: 1 | K52: =IF(F52>0,22/28*((F52/1000)^2-(F52/1000-2*G52/1000)^2)*H52/1000,IF(G52>0,G52/1000*H52/1000*I52/1000, IF(H52>0,H52/1000*I52/1000, IF(I52=0,1,I52/1000)))) -> 0.41 | L52: =J52*K52 -> 0.41 | M52: 1.05 | N52: =+Q44 -> 0 | O52: =L52*M52*N52 -> 0 | P52: =IF($J52=1,VLOOKUP($B52,$B$7:$S$40,4,FALSE),1) -> 1.759 | Q52: =O52*P52/M52 -> 0 | R52: =VLOOKUP($B52,$B$7:$S$40,5,FALSE) -> 214624.38 | S52: =+O52*R52 -> 0
B53: SH5040 | D53: =VLOOKUP($B53,$B$7:$S$40,3,FALSE) -> Damper, Leaf : Flat Blade Profile - 15.7T x 108W | E53: m | I53: =+Q45 -> 500 | J53: 1 | K53: =IF(F53>0,22/28*((F53/1000)^2-(F53/1000-2*G53/1000)^2)*H53/1000,IF(G53>0,G53/1000*H53/1000*Q45/1000, IF(H53>0,H53/1000*Q45/1000, IF(Q45=0,1,Q45/1000)))) -> 0.5 | L53: =J53*K53 -> 0.5 | M53: 1.05 | N53: =+P45 -> 4 | O53: =L53*M53*N53 -> 2.1 | P53: =IF($J53=1,VLOOKUP($B53,$B$7:$S$40,4,FALSE),1) -> 0.85 | Q53: =O53*P53/M53 -> 1.7 | R53: =VLOOKUP($B53,$B$7:$S$40,5,FALSE) -> 69353.625 | S53: =+O53*R53 -> 145642.61
B54: GA100 | D54: =VLOOKUP($B54,$B$7:$S$40,3,FALSE) -> Damper, Gasket : 200m/roll (密封胶条） | E54: m | I54: =Q45 -> 500 | J54: 1 | K54: =IF(F54>0,22/28*((F54/1000)^2-(F54/1000-2*G54/1000)^2)*H54/1000,IF(G54>0,G54/1000*H54/1000*I54/1000, IF(H54>0,H54/1000*I54/1000, IF(I54=0,1,I54/1000)))) -> 0.5 | L54: =J54*K54 -> 0.5 | M54: 1.05 | N54: =(N53*2)+((P46+1)*2) -> 10.41 | O54: =L54*M54*N54 -> 5.46525 | P54: =IF($J54=1,VLOOKUP($B54,$B$7:$S$40,4,FALSE),1) -> 0.03735 | Q54: =O54*P54/M54 -> 0.19440675 | R54: =VLOOKUP($B54,$B$7:$S$40,5,FALSE) -> 2454.75 | S54: =+O54*R54 -> 13415.822
B55: PMS80 | D55: =VLOOKUP($B55,$B$7:$S$40,3,FALSE) -> Damper, Actuator Base : 90W x 150L | E55: m | I55: 150 | J55: 1 | K55: =IF(F55>0,22/28*((F55/1000)^2-(F55/1000-2*G55/1000)^2)*H55/1000,IF(G55>0,G55/1000*H55/1000*I55/1000, IF(H55>0,H55/1000*I55/1000, IF(I55=0,1,I55/1000)))) -> 0.15 | L55: =J55*K55 -> 0.15 | M55: 1 | N55: =IF(B44=1,1,0) -> 0 | O55: =L55*M55*N55 -> 0 | P55: =IF($J55=1,VLOOKUP($B55,$B$7:$S$40,4,FALSE),1) -> 0.715 | Q55: =O55*P55/M55 -> 0 | R55: =VLOOKUP($B55,$B$7:$S$40,5,FALSE) -> 94500 | S55: =+O55*R55 -> 0
B56: AC004 | D56: =VLOOKUP($B56,$B$7:$S$40,3,FALSE) -> Damper, Gear Housing Set : PA (齿轮） | E56: Set | J56: 1 | K56: =IF(F56>0,22/28*((F56/1000)^2-(F56/1000-2*G56/1000)^2)*H56/1000,IF(G56>0,G56/1000*H56/1000*I56/1000, IF(H56>0,H56/1000*I56/1000, IF(I56=0,1,I56/1000)))) -> 1 | L56: =J56*K56 -> 1 | M56: 1 | N56: =+N53 -> 4 | O56: =L56*M56*N56 -> 4 | P56: =IF($J56=1,VLOOKUP($B56,$B$7:$S$40,4,FALSE),1) -> 0.12 | Q56: =O56*P56/M56 -> 0.48 | R56: =VLOOKUP($B56,$B$7:$S$40,5,FALSE) -> 20355 | S56: =+O56*R56 -> 81420
B57: AC003 | D57: =VLOOKUP($B57,$B$7:$S$40,3,FALSE) -> Damper, Handle : (铝执手) | E57: Set | J57: 1 | K57: =IF(F57>0,22/28*((F57/1000)^2-(F57/1000-2*G57/1000)^2)*H57/1000,IF(G57>0,G57/1000*H57/1000*I57/1000, IF(H57>0,H57/1000*I57/1000, IF(I57=0,1,I57/1000)))) -> 1 | L57: =J57*K57 -> 1 | M57: 1 | N57: =IF(B44=0,1,0) -> 1 | O57: =L57*M57*N57 -> 1 | P57: =IF($J57=1,VLOOKUP($B57,$B$7:$S$40,4,FALSE),1) -> 0.37 | Q57: =O57*P57/M57 -> 0.37 | R57: =VLOOKUP($B57,$B$7:$S$40,5,FALSE) -> 117990 | S57: =+O57*R57 -> 117990
B58: =+Q$46 -> 2Nm | D58: =VLOOKUP($B58,$B$7:$S$40,3,FALSE) -> Actuator 2Nm, 70sec : 0.5m2 FA | E58: Set | J58: 1 | K58: =IF(F58>0,22/28*((F58/1000)^2-(F58/1000-2*G58/1000)^2)*H58/1000,IF(G58>0,G58/1000*H58/1000*I58/1000, IF(H58>0,H58/1000*I58/1000, IF(I58=0,1,I58/1000)))) -> 1 | L58: =J58*K58 -> 1 | M58: 1 | N58: =IF(B44=1,1,0) -> 0 | O58: =L58*M58*N58 -> 0 | P58: =IF($J58=1,VLOOKUP($B58,$B$7:$S$40,4,FALSE),1) -> 0.5 | Q58: =O58*P58/M58 -> 0 | R58: =VLOOKUP($B58,$B$7:$S$40,5,FALSE) -> 0 | S58: =+O58*R58 -> 0
E59: Unit Weight / Unit Cost | Q59: =SUM(Q50:Q58) -> 5.0664099 | S59: =SUM(S50:S58) -> 555351.33 | T59: =+S59/S92 -> 2.254808
E60: Gross Contribution | R60: 0.4 | S60: =+S61-S59 -> 370234.22
E61: Unit Price (Rp) | S61: =+S59/(1-R60) -> 925585.56 | T61: =ROUNDUP(S61,-5) -> 1000000
H63: Class | I63: Section | J63: FA(m2) | K63: USD/m2 | L63: FOB | M63: LF | N63: Rp/USD | S63: UC
E64: Arosio Cost | H64: 2 | I64: =Q44+1 -> 1 | J64: =P43/1000*Q43/1000 -> 0.205 | K64: =IF(I64=1,117,IF(I64=2,217,IF(I64=3,315,"NA"))) -> 117 | L64: =+J64*K64 -> 23.985 | M64: 1.8 | N64: =+S43 -> 17500 | S64: =+L64*M64*N64 -> 755527.5
H65: 3 | I65: =+I64 -> 1 | J65: =+J64 -> 0.205 | K65: =IF(I65=1,135,IF(I65=2,250,IF(I65=3,362,"NA"))) -> 135 | L65: =+J65*K65 -> 27.675 | M65: 1.8 | N65: =+N64 -> 17500 | S65: =+L65*M65*N65 -> 871762.5
H66: 4 | I66: =+I64 -> 1 | J66: =+J64 -> 0.205 | K66: =IF(I66=1,310,"NA") -> 310 | L66: =+J66*K66 -> 63.55 | M66: 1.8 | N66: =+N64 -> 17500 | S66: =+L66*M66*N66 -> 2001825
B68: Sheet Metal VolumeDamper Cost Estimator
B69: W | C69: H | D69: <=== ENTER | E69: SELECTED ===> | P69: W | Q69: H | R69: 43088
B70: 500 | C70: 410 | D70: 1. Requested Opening Size : mmW x mmH | E70: a. Final Opening Size : mmW x mmH | P70: =+B70 -> 500 | Q70: =P71*100+10 -> 410 | R70: Rp/USD | S70: =+S$7 -> 17500
B71: 0 | D71: 2. Mode of Actuation : Manual=0, Motorized=1 | E71: b. No. of Damper Leaf : (Nx100) mmH / No. of Vertical Center Profile | P71: =ROUNDDOWN(C70/100,0) -> 4 | Q71: =IF(P70<=1400,0,IF(AND(P70>1400,P70<=2100),1,2)) -> 0 | R71: Rp/Euro | S71: =+S$8 -> 16079.99
E72: c. No. of Damper Leaf / Damper Leaf Length | P72: =P71*(Q71+1) -> 4 | Q72: =(P70-Q71*34.3)/(Q71+1) -> 500 | R72: Rp/RM | S72: =+S$9 -> 3429.69
E73: d. Recommended Actuator type : m2 x Nm | P73: =Q70/1000*P70/1000 -> 0.205 | Q73: =IF(P73<0.5,"2Nm",IF(AND(P73>0.5,P73<1),"5Nm",IF(AND(P73>1,P73<2),"10Nm",IF(AND(P73>2,P73<4),"20Nm",IF(AND(P73>4,P73<6),"30Nm",IF(AND(P73>6,P73<8),"40Nm","NA")))))) -> 2Nm | R73: Rp/Rmb | S73: =+S$10 -> 2192.36
R74: Rp/S$ | S74: =+S$11 -> 11262.76
B75: PickList | C75: P/Ninternal | D75: Item | E75: Dimension | J75: Usage | P75: Unit Weight | R75: Unit Cost
E76: UoM | F76: ODmm | G76: Tmm | H76: Wmm | I76: Lmm | J76: CF | K76: V/A/L | L76: n | M76: WF | N76: Npc | O76: Qty | P76: kGUoM | Q76: UW | R76: UC (Rp) | S76: Total(Rp)
B77: Al6065 | D77: Damper Frame, Vertical L/R | E77: kG | G77: 1 | H77: 176.5 | I77: =+Q70+30*2 -> 470 | J77: =VLOOKUP($B77,$B$7:$S$40,4,FALSE) -> 2720 | K77: =IF(F77>0,22/28*((F77/1000)^2-(F77/1000-2*G77/1000)^2)*H77/1000,IF(G77>0,G77/1000*H77/1000*I77/1000, IF(H77>0,H77/1000*I77/1000, IF(I77=0,1,I77/1000)))) -> 8.2955e-05 | L77: =J77*K77 -> 0.2256376 | M77: 1.1 | N77: 2 | O77: =L77*M77*N77 -> 0.49640272 | P77: =IF($J77=1,VLOOKUP($B77,$B$7:$S$40,4,FALSE),1) -> 1 | Q77: =O77*P77/M77 -> 0.4512752 | R77: =VLOOKUP($B77,$B$7:$S$40,5,FALSE) -> 83085 | S77: =+O77*R77 -> 41243.62
B78: Al6065 | D78: Damper Frame, Horizontal T/B | E78: kG | G78: 1 | H78: 176.5 | I78: =+P70 -> 500 | J78: =VLOOKUP($B78,$B$7:$S$40,4,FALSE) -> 2720 | K78: =IF(F78>0,22/28*((F78/1000)^2-(F78/1000-2*G78/1000)^2)*H78/1000,IF(G78>0,G78/1000*H78/1000*I78/1000, IF(H78>0,H78/1000*I78/1000, IF(I78=0,1,I78/1000)))) -> 8.825e-05 | L78: =J78*K78 -> 0.24004 | M78: 1.1 | N78: 2 | O78: =L78*M78*N78 -> 0.528088 | P78: =IF($J78=1,VLOOKUP($B78,$B$7:$S$40,4,FALSE),1) -> 1 | Q78: =O78*P78/M78 -> 0.48008 | R78: =VLOOKUP($B78,$B$7:$S$40,5,FALSE) -> 83085 | S78: =+O78*R78 -> 43876.191
B79: Al6065 | D79: Damper Frame, Vertical Center | E79: kG | G79: 1 | H79: 176.5 | I79: =+Q70 -> 410 | J79: =VLOOKUP($B79,$B$7:$S$40,4,FALSE) -> 2720 | K79: =IF(F79>0,22/28*((F79/1000)^2-(F79/1000-2*G79/1000)^2)*H79/1000,IF(G79>0,G79/1000*H79/1000*I79/1000, IF(H79>0,H79/1000*I79/1000, IF(I79=0,1,I79/1000)))) -> 7.2365e-05 | L79: =J79*K79 -> 0.1968328 | M79: 1.1 | N79: =IF(P$70>1000,1,0) -> 0 | O79: =L79*M79*N79 -> 0 | P79: =IF($J79=1,VLOOKUP($B79,$B$7:$S$40,4,FALSE),1) -> 1 | Q79: =O79*P79/M79 -> 0 | R79: =VLOOKUP($B79,$B$7:$S$40,5,FALSE) -> 83085 | S79: =+O79*R79 -> 0
B80: Al6065 | D80: Damper Blade, Horizontal | E80: kG | G80: 1 | H80: 123.2 | I80: =+Q72 -> 500 | J80: =VLOOKUP($B80,$B$7:$S$40,4,FALSE) -> 2720 | K80: =IF(F80>0,22/28*((F80/1000)^2-(F80/1000-2*G80/1000)^2)*H80/1000,IF(G80>0,G80/1000*H80/1000*I80/1000, IF(H80>0,H80/1000*I80/1000, IF(I80=0,1,I80/1000)))) -> 6.16e-05 | L80: =J80*K80 -> 0.167552 | M80: 1.1 | N80: =+P$71 -> 4 | O80: =L80*M80*N80 -> 0.7372288 | P80: =IF($J80=1,VLOOKUP($B80,$B$7:$S$40,4,FALSE),1) -> 1 | Q80: =O80*P80/M80 -> 0.670208 | R80: =VLOOKUP($B80,$B$7:$S$40,5,FALSE) -> 83085 | S80: =+O80*R80 -> 61252.655
B81: Al6065 | D81: Stopper Blade, Horizontal | E81: kG | G81: 1 | H81: 33.3 | I81: =+Q72 -> 500 | J81: =VLOOKUP($B81,$B$7:$S$40,4,FALSE) -> 2720 | K81: =IF(F81>0,22/28*((F81/1000)^2-(F81/1000-2*G81/1000)^2)*H81/1000,IF(G81>0,G81/1000*H81/1000*I81/1000, IF(H81>0,H81/1000*I81/1000, IF(I81=0,1,I81/1000)))) -> 1.665e-05 | L81: =J81*K81 -> 0.045288 | M81: 1.1 | N81: 2 | O81: =L81*M81*N81 -> 0.0996336 | P81: =IF($J81=1,VLOOKUP($B81,$B$7:$S$40,4,FALSE),1) -> 1 | Q81: =O81*P81/M81 -> 0.090576 | R81: =VLOOKUP($B81,$B$7:$S$40,5,FALSE) -> 83085 | S81: =+O81*R81 -> 8278.0577
B82: Al6065 | D82: Stopper Box Adjustment | E82: kG | G82: 1 | H82: 90 | I82: 156.5 | J82: =VLOOKUP($B82,$B$7:$S$40,4,FALSE) -> 2720 | K82: =IF(F82>0,22/28*((F82/1000)^2-(F82/1000-2*G82/1000)^2)*H82/1000,IF(G82>0,G82/1000*H82/1000*I82/1000, IF(H82>0,H82/1000*I82/1000, IF(I82=0,1,I82/1000)))) -> 1.4085e-05 | L82: =J82*K82 -> 0.0383112 | M82: 1.1 | N82: 1 | O82: =L82*M82*N82 -> 0.04214232 | P82: =IF($J82=1,VLOOKUP($B82,$B$7:$S$40,4,FALSE),1) -> 1 | Q82: =O82*P82/M82 -> 0.0383112 | R82: =VLOOKUP($B82,$B$7:$S$40,5,FALSE) -> 83085 | S82: =+O82*R82 -> 3501.3947
B83: Al6065 | D83: Turning Arm#1 | E83: kG | G83: 3 | H83: 25 | I83: 60 | J83: =VLOOKUP($B83,$B$7:$S$40,4,FALSE) -> 2720 | K83: =IF(F83>0,22/28*((F83/1000)^2-(F83/1000-2*G83/1000)^2)*H83/1000,IF(G83>0,G83/1000*H83/1000*I83/1000, IF(H83>0,H83/1000*I83/1000, IF(I83=0,1,I83/1000)))) -> 4.5e-06 | L83: =J83*K83 -> 0.01224 | M83: 1.1 | N83: =P$71-2 -> 2 | O83: =L83*M83*N83 -> 0.026928 | P83: =IF($J83=1,VLOOKUP($B83,$B$7:$S$40,4,FALSE),1) -> 1 | Q83: =O83*P83/M83 -> 0.02448 | R83: =VLOOKUP($B83,$B$7:$S$40,5,FALSE) -> 83085 | S83: =+O83*R83 -> 2237.3129
B84: Al6065 | D84: Turning Arm#2 | E84: kG | G84: 3 | H84: 25 | I84: 140 | J84: =VLOOKUP($B84,$B$7:$S$40,4,FALSE) -> 2720 | K84: =IF(F84>0,22/28*((F84/1000)^2-(F84/1000-2*G84/1000)^2)*H84/1000,IF(G84>0,G84/1000*H84/1000*I84/1000, IF(H84>0,H84/1000*I84/1000, IF(I84=0,1,I84/1000)))) -> 1.05e-05 | L84: =J84*K84 -> 0.02856 | M84: 1.1 | N84: 1 | O84: =L84*M84*N84 -> 0.031416 | P84: =IF($J84=1,VLOOKUP($B84,$B$7:$S$40,4,FALSE),1) -> 1 | Q84: =O84*P84/M84 -> 0.02856 | R84: =VLOOKUP($B84,$B$7:$S$40,5,FALSE) -> 83085 | S84: =+O84*R84 -> 2610.1984
B85: Al6065 | D85: Turning Arm#3 | E85: kG | G85: 3 | H85: 25 | I85: =100*(P$71-1)+15*2 -> 330 | J85: =VLOOKUP($B85,$B$7:$S$40,4,FALSE) -> 2720 | K85: =IF(F85>0,22/28*((F85/1000)^2-(F85/1000-2*G85/1000)^2)*H85/1000,IF(G85>0,G85/1000*H85/1000*I85/1000, IF(H85>0,H85/1000*I85/1000, IF(I85=0,1,I85/1000)))) -> 2.475e-05 | L85: =J85*K85 -> 0.06732 | M85: 1.1 | N85: 1 | O85: =L85*M85*N85 -> 0.074052 | P85: =IF($J85=1,VLOOKUP($B85,$B$7:$S$40,4,FALSE),1) -> 1 | Q85: =O85*P85/M85 -> 0.06732 | R85: =VLOOKUP($B85,$B$7:$S$40,5,FALSE) -> 83085 | S85: =+O85*R85 -> 6152.6104
B86: Al6065 | D86: Shaft 10mmOD | E86: kG | F86: 10 | G86: 5 | H86: =+$P$70+40*2 -> 580 | J86: =VLOOKUP($B86,$B$7:$S$40,4,FALSE) -> 2720 | K86: =IF(F86>0,22/28*((F86/1000)^2-(F86/1000-2*G86/1000)^2)*H86/1000,IF(G86>0,G86/1000*H86/1000*I86/1000, IF(H86>0,H86/1000*I86/1000, IF(I86=0,1,I86/1000)))) -> 4.5571429e-05 | L86: =J86*K86 -> 0.12395429 | M86: 1.1 | N86: =+P$71 -> 4 | O86: =L86*M86*N86 -> 0.54539886 | P86: =IF($J86=1,VLOOKUP($B86,$B$7:$S$40,4,FALSE),1) -> 1 | Q86: =O86*P86/M86 -> 0.49581714 | R86: =VLOOKUP($B86,$B$7:$S$40,5,FALSE) -> 83085 | S86: =+O86*R86 -> 45314.464
B87: WN06 | D87: Wing Nut M6 | E87: Pc | J87: 1 | K87: =IF(F87>0,22/28*((F87/1000)^2-(F87/1000-2*G87/1000)^2)*H87/1000,IF(G87>0,G87/1000*H87/1000*I87/1000, IF(H87>0,H87/1000*I87/1000, IF(I87=0,1,I87/1000)))) -> 1 | L87: =J87*K87 -> 1 | M87: 1 | N87: 1 | O87: =L87*M87*N87 -> 1 | P87: =IF($J87=1,VLOOKUP($B87,$B$7:$S$40,4,FALSE),1) -> 0.008 | Q87: =O87*P87/M87 -> 0.008 | R87: =VLOOKUP($B87,$B$7:$S$40,5,FALSE) -> 4000 | S87: =+O87*R87 -> 4000
B88: HB0620 | D88: Hex Bolt M6 x 20 | E88: Pc | J88: 1 | K88: =IF(F88>0,22/28*((F88/1000)^2-(F88/1000-2*G88/1000)^2)*H88/1000,IF(G88>0,G88/1000*H88/1000*I88/1000, IF(H88>0,H88/1000*I88/1000, IF(I88=0,1,I88/1000)))) -> 1 | L88: =J88*K88 -> 1 | M88: 1 | N88: 1 | O88: =L88*M88*N88 -> 1 | P88: =IF($J88=1,VLOOKUP($B88,$B$7:$S$40,4,FALSE),1) -> 0.002 | Q88: =O88*P88/M88 -> 0.002 | R88: =VLOOKUP($B88,$B$7:$S$40,5,FALSE) -> 1890 | S88: =+O88*R88 -> 1890
B89: HB0820 | D89: Bush 3/8" | E89: Pc | J89: 1 | K89: =IF(F89>0,22/28*((F89/1000)^2-(F89/1000-2*G89/1000)^2)*H89/1000,IF(G89>0,G89/1000*H89/1000*I89/1000, IF(H89>0,H89/1000*I89/1000, IF(I89=0,1,I89/1000)))) -> 1 | L89: =J89*K89 -> 1 | M89: 1 | N89: =P$71*2 -> 8 | O89: =L89*M89*N89 -> 8 | P89: =IF($J89=1,VLOOKUP($B89,$B$7:$S$40,4,FALSE),1) -> 0.011 | Q89: =O89*P89/M89 -> 0.088 | R89: =VLOOKUP($B89,$B$7:$S$40,5,FALSE) -> 3180 | S89: =+O89*R89 -> 25440
B90: RB10 | D90: Hex Bolt M8 x 20 | E90: Pc | J90: 1 | K90: =IF(F90>0,22/28*((F90/1000)^2-(F90/1000-2*G90/1000)^2)*H90/1000,IF(G90>0,G90/1000*H90/1000*I90/1000, IF(H90>0,H90/1000*I90/1000, IF(I90=0,1,I90/1000)))) -> 1 | L90: =J90*K90 -> 1 | M90: 1 | N90: 1 | O90: =L90*M90*N90 -> 1 | P90: =IF($J90=1,VLOOKUP($B90,$B$7:$S$40,4,FALSE),1) -> 0.005 | Q90: =O90*P90/M90 -> 0.005 | R90: =VLOOKUP($B90,$B$7:$S$40,5,FALSE) -> 100 | S90: =+O90*R90 -> 100
B91: SR05 | D91: Snap Ring #5 | E91: Pc | J91: 1 | K91: =IF(F91>0,22/28*((F91/1000)^2-(F91/1000-2*G91/1000)^2)*H91/1000,IF(G91>0,G91/1000*H91/1000*I91/1000, IF(H91>0,H91/1000*I91/1000, IF(I91=0,1,I91/1000)))) -> 1 | L91: =J91*K91 -> 1 | M91: 1 | N91: =P$71 -> 4 | O91: =L91*M91*N91 -> 4 | P91: =IF($J91=1,VLOOKUP($B91,$B$7:$S$40,4,FALSE),1) -> 0.002 | Q91: =O91*P91/M91 -> 0.008 | R91: =VLOOKUP($B91,$B$7:$S$40,5,FALSE) -> 100 | S91: =+O91*R91 -> 400
E92: Unit Weight / Unit Cost | Q92: =SUM(Q77:Q91) -> 2.4576275 | S92: =SUM(S77:S91) -> 246296.5 | T92: 1
E93: Gross Contribution | R93: 0.4 | S93: =+S94-S92 -> 164197.67
E94: Unit Price (Rp) | S94: =+S92/(1-R93) -> 410494.17
S95: =ROUNDUP(S94,-5) -> 500000

Sheet drainpan
A1: x | B1: xx
D2: D | E2: 1000 | F2: Ømm | G2: mmT | H2: mmL | I2: mmW | J2: kg/m3 | K2: N(pc) | L2: Qty/Unit | M2: Unit/Set | N2: WF | O2: Rp/USD | P2: 17500 | Q2: U/P | R2: LF | S2: Total
D3: W | E3: 500
D4: H | E4: 50
B5: Drain Pan 1 | D5: Matl | E5: Uom | O5: Qty/Set | P5: Fx | S5: USD
C6: Structure | W6: 304
B7: 1 | C7: Bottom plate | D7: SS304 | E7: kg | G7: 1.5 | H7: =+E3+(E4*2)+20 -> 620 | I7: =+E2+(E4*2)+20 -> 1120 | J7: 8027 | K7: 1 | L7: =G7/1000*H7/1000*I7/1000*J7*K7 -> 8.3609232 | M7: 1 | N7: 1.5 | O7: =L7*M7*N7 -> 12.541385 | P7: Rp | Q7: 50000 | R7: 1 | S7: =IF(P7="Rp",O7*Q7/$P$2*R7,O7*Q7*R7) -> 35.832528 | T7: =S7*P$2 -> 627069.24 | U7: =SUM(T7:T11) -> 880396.74 | W7: mmT | X7: mmL | Y7: mmP | Z7: kg | AA7: kg/m3 | AB7: harga/lembar | AC7: harga/kg
B8: 2 | C8: Omega plate | D8: SS304 | E8: kg | G8: 1.5 | H8: 500 | I8: 200 | J8: 8027 | K8: 2 | L8: =G8/1000*H8/1000*I8/1000*J8*K8 -> 2.4081 | M8: 1 | N8: 1.5 | O8: =L8*M8*N8 -> 3.61215 | P8: Rp | Q8: 50000 | R8: 1 | S8: =IF(P8="Rp",O8*Q8/$P$2*R8,O8*Q8*R8) -> 10.320429 | T8: =S8*P$2 -> 180607.5 | W8: 1.5 | X8: 1200 | Y8: 2400 | Z8: 34.56 | AA8: 8000 | AB8: 1500000 | AC8: =AB8/Z8 -> 43402.778
B9: 3 | C9: Outlet pipe | D9: BS | E9: pcs | G9: 1.25 | H9: 200 | K9: 1 | L9: =+H9/1000 -> 0.2 | M9: 1 | N9: 1.25 | O9: =L9*M9*N9 -> 0.25 | P9: Rp | Q9: 40000 | R9: 1 | S9: =IF(P9="Rp",O9*Q9/$P$2*R9,O9*Q9*R9) -> 0.57142857 | T9: =S9*P$2 -> 10000
B10: 4 | C10: PE foam 10mm | D10: PE | E10: mm | H10: =H7+H8 -> 1120 | I10: =I7 -> 1120 | K10: 1 | L10: =+H10/1000*I10/1000 -> 1.2544 | M10: 1 | N10: 1.25 | O10: =L10*M10*N10 -> 1.568 | P10: Rp | Q10: 40000 | R10: 1 | S10: =IF(P10="Rp",O10*Q10/$P$2*R10,O10*Q10*R10) -> 3.584 | T10: =S10*P$2 -> 62720
B12: 5 | C12: Operating Supply | G12: 0 | S12: =SUM(S7:S11)*G12 -> 0 | T12: =S12*P$2 -> 0
Q14: U/C | S14: =SUM(S6:S12) -> 50.308385 | T14: =SUM(T6:T12) -> 880396.74
G15: 0.15 | H15: =300000/6 -> 50000 | I15: =+G15*H15 -> 7500 | Q15: UP | R15: 0.5 | S15: =+S14/(1-R15) -> 100.61677
S17: =S15*P2 -> 1760793.5 | T17: =ROUNDUP(S17,-5) -> 1800000

Sheet 1. AHU-Skid
B1: TDM50-040x040 | C1: H | D1: W | E1: D
B2: Section 1 | C2: 1420 | D2: 1930 | E2: 1625 | G2: SA | H2: LPS | I2: =I3*1000 -> 748.03194 | K2: Qc | L2: kW | M2: 148.55 | O2: 3/8''DX 457FH x 733FL x 6R x 12FPI x 9NC
B3: Section 2 | H3: CMS | I3: =I4/3600 -> 0.74803194 | L3: Btu/h | M3: =M2*3412 -> 506852.6
H4: CMH | I4: =I5*1.699 -> 2692.915 | L4: Hp | M4: =M3/10000 -> 50.68526
H5: CFM | I5: 1585 | K5: Qs | L5: kW | M5: 93.55
G6: RA | H6: LPS | I6: =I7*1000 -> 4530.6667 | L6: Btu/h | M6: =M5*3412 -> 319192.6
H7: CMS | I7: =I8/3600 -> 4.5306667 | L7: Hp | M7: =M6/10000 -> 31.91926
B8: Skid 1 | D8: =D2 -> 1930 | E8: =E2 -> 1625 | H8: CMH | I8: =I9*1.699 -> 16310.4
B9: Skid 2 | D9: =D3 -> 0 | E9: =E3 -> 0 | H9: CFM | I9: 9600
B12: VD1 | C12: 810 | D12: 1100
B13: VD2 | C13: 310 | D13: 800
B14: RA Opening | C14: =C2-100 -> 1320 | D14: =D2-100 -> 1830
B15: SA Opening | C15: =C3-100 -> -100 | D15: =D3-100 -> -100
C17: T | D17: L | E17: W | F17: MX | G17: UoM | H17: Qty/Pc | I17: WF | J17: Qty | K17: N | L17: U/W(kG) | M17: Rp/Uom | N17: kG | O17: Rp
A18: =B8 -> Skid 1 | B18: UNP100-304 L/R (D) | C18: 3 | D18: =100+100+100 -> 300 | E18: =E8 -> 1625 | F18: 7860 | G18: kG | H18: =C18/1000*D18/1000*E18/1000*F18 -> 11.49525 | I18: 1.15 | J18: =H18*I18 -> 13.219537 | K18: 2 | L18: 1 | M18: 30000 | N18: =H18*K18*L18 -> 22.9905 | O18: =J18*K18*M18 -> 793172.25
B19: UNP100-304 F/B (W) | C19: 3 | D19: =100+100+100 -> 300 | E19: =D8 -> 1930 | F19: 7860 | G19: kG | H19: =C19/1000*D19/1000*E19/1000*F19 -> 13.65282 | I19: 1.15 | J19: =H19*I19 -> 15.700743 | K19: 2 | L19: 1 | M19: 30000 | N19: =H19*K19*L19 -> 27.30564 | O19: =J19*K19*M19 -> 942044.58
B20: C40-180-40-Center Support (W) | C20: 2 | D20: =180+40+40 -> 260 | E20: =D8 -> 1930 | F20: 7860 | G20: kG | H20: =C20/1000*D20/1000*E20/1000*F20 -> 7.888296 | I20: 1.15 | J20: =H20*I20 -> 9.0715404 | K20: 2 | L20: 1 | M20: 30000 | N20: =H20*K20*L20 -> 15.776592 | O20: =J20*K20*M20 -> 544292.42
A22: =B9 -> Skid 2 | B22: UNP100-304 L/R (D) | C22: 3 | D22: =100+100+100 -> 300 | E22: =E9 -> 0 | F22: 7860 | G22: kG | H22: =C22/1000*D22/1000*E22/1000*F22 -> 0 | I22: 1.15 | J22: =H22*I22 -> 0 | K22: 2 | L22: 1 | M22: 30000 | N22: =H22*K22*L22 -> 0 | O22: =J22*K22*M22 -> 0
B23: UNP100-304 F/B (W) | C23: 3 | D23: =100+100+100 -> 300 | E23: =D9 -> 0 | F23: 7860 | G23: kG | H23: =C23/1000*D23/1000*E23/1000*F23 -> 0 | I23: 1.15 | J23: =H23*I23 -> 0 | K23: 2 | L23: 1 | M23: 30000 | N23: =H23*K23*L23 -> 0 | O23: =J23*K23*M23 -> 0
B24: C40-180-40-Center Support (W) | C24: 2 | D24: =180+40+40 -> 260 | E24: =D9 -> 0 | F24: 7860 | G24: kG | H24: =C24/1000*D24/1000*E24/1000*F24 -> 0 | I24: 1.15 | J24: =H24*I24 -> 0 | K24: 2 | L24: 1 | M24: 30000 | N24: =H24*K24*L24 -> 0 | O24: =J24*K24*M24 -> 0
N25: =SUM(N18:N24) -> 66.072732 | O25: =SUM(O18:O24) -> 2279509.3

Sheet 2. AHU-Frame & Panel
B1: TDM50-040x040 | C1: H | D1: W | E1: D
B2: Section 1 | C2: 1420 | D2: 1930 | E2: 1625 | G2: SA | H2: LPS | I2: =I3*1000 -> 1444.4444 | K2: Qc | L2: kW | M2: 148.55 | O2: 3/8''DX 762FH x 1038FL x 6R x 12FPI x 22NC
B3: Section 2 | H3: CMS | I3: =I4/3600 -> 1.4444444 | L3: Btu/h | M3: =M2*3412 -> 506852.6
H4: CMH | I4: 5200 | L4: Hp | M4: =M3/10000 -> 50.68526
H5: CFM | I5: =I4/1.699 -> 3060.6239 | K5: Qs | L5: kW | M5: 93.55
G6: RA | H6: LPS | I6: =I7*1000 -> 4530.6667 | L6: Btu/h | M6: =M5*3412 -> 319192.6
H7: CMS | I7: =I8/3600 -> 4.5306667 | L7: Hp | M7: =M6/10000 -> 31.91926
B8: Skid 1 | D8: =D2 -> 1930 | E8: =E2 -> 1625 | H8: CMH | I8: =I9*1.699 -> 16310.4
B9: Skid 2 | D9: =D3 -> 0 | E9: =E3 -> 0 | H9: CFM | I9: 9600
B12: VD1 | C12: 810 | D12: 1100
B13: VD2 | C13: 310 | D13: 800
B14: RA Opening | C14: =C2-100 -> 1320 | D14: =D2-100 -> 1830
B15: SA Opening | C15: =C3-100 -> -100 | D15: =D3-100 -> -100
C17: T | D17: L | E17: W | F17: MX | G17: UoM | H17: Qty/Pc | I17: WF | J17: Qty | K17: N | L17: U/W(kG) | M17: Rp/Uom | N17: kG | O17: Rp
A18: =B2 -> Section 1 | B18: Cornerpiece | F18: =0.42476+0.15 -> 0.57476 | G18: Pc | H18: 8 | I18: 1 | J18: =H18*I18 -> 8 | K18: 1 | L18: =F18 -> 0.57476 | M18: =18.1*2*2500 -> 90500 | N18: =H18*K18*L18 -> 4.59808 | O18: =J18*K18*M18 -> 724000
B19: Omega Joint | F19: 0.036 | G19: Pc | H19: 8 | I19: 1 | J19: =H19*I19 -> 8 | K19: 1 | L19: =F19 -> 0.036 | M19: =2.9*2*2500 -> 14500 | N19: =H19*K19*L19 -> 0.288 | O19: =J19*K19*M19 -> 116000
B20: Pentapost Assy H: DS5056 (PTTBP160-50-5800-LB20) | E20: =C2 -> 1420 | F20: =11.596551724138/6 -> 1.9327586 | G20: m | H20: =E20/1000 -> 1.42 | I20: 1.05 | J20: =H20*I20 -> 1.491 | K20: 4 | L20: =F20 -> 1.9327586 | M20: 175000 | N20: =H20*K20*L20 -> 10.978069 | O20: =J20*K20*M20 -> 1043700
B21: Pentapost Assy W: DS5056 (PTTBP160-50-5800-LB20) | E21: =D2 -> 1930 | F21: =11.596551724138/6 -> 1.9327586 | G21: m | H21: =E21/1000 -> 1.93 | I21: 1.05 | J21: =H21*I21 -> 2.0265 | K21: 4 | L21: =F21 -> 1.9327586 | M21: 175000 | N21: =H21*K21*L21 -> 14.920897 | O21: =J21*K21*M21 -> 1418550
B22: Pentapost Assy D: DS5056 (PTTBP160-50-5800-LB20) | E22: =E2 -> 1625 | F22: =11.596551724138/6 -> 1.9327586 | G22: m | H22: =E22/1000 -> 1.625 | I22: 1.05 | J22: =H22*I22 -> 1.70625 | K22: 4 | L22: =F22 -> 1.9327586 | M22: 175000 | N22: =H22*K22*L22 -> 12.562931 | O22: =J22*K22*M22 -> 1194375
B23: Interpost Assy H: DS5040 (PTTBP270-50-5800-LB20) | E23: =E20 -> 1420 | F23: =8.094/6 -> 1.349 | G23: m | H23: =E23/1000 -> 1.42 | I23: 1.05 | J23: =H23*I23 -> 1.491 | K23: 2 | L23: =F23 -> 1.349 | M23: 132000 | N23: =H23*K23*L23 -> 3.83116 | O23: =J23*K23*M23 -> 393624
B24: Interpost Assy W: DS5040 (PTTBP270-50-5800-LB20) | E24: =E21 -> 1930 | F24: =8.094/6 -> 1.349 | G24: m | H24: =E24/1000 -> 1.93 | I24: 1.05 | J24: =H24*I24 -> 2.0265 | K24: 2 | L24: =F24 -> 1.349 | M24: 132000 | N24: =H24*K24*L24 -> 5.20714 | O24: =J24*K24*M24 -> 534996
B25: Interpost Assy D: DS5040 (PTTBP270-50-5800-LB20) | E25: =E22 -> 1625 | F25: =8.094/6 -> 1.349 | G25: m | H25: =E25/1000 -> 1.625 | I25: 1.05 | J25: =H25*I25 -> 1.70625 | K25: 2 | L25: =F25 -> 1.349 | M25: 132000 | N25: =H25*K25*L25 -> 4.38425 | O25: =J25*K25*M25 -> 450450
B26: Panel Clip 15mm - Pentapost H: DS50 (PBP-100000-5800-LB20) | E26: =E20 -> 1420 | F26: 0.227 | G26: m | H26: =E26/1000 -> 1.42 | I26: 1.05 | J26: =H26*I26 -> 1.491 | K26: =K20*2 -> 8 | L26: =F26 -> 0.227 | M26: =4.48333333333333/4.1*1.35*16500 -> 24357.622 | N26: =H26*K26*L26 -> 2.57872 | O26: =J26*K26*M26 -> 290537.71
B27: Panel Clip 15mm - Pentapost W: DS50 (PBP-100000-5800-LB20) | E27: =E21 -> 1930 | F27: 0.227 | G27: m | H27: =E27/1000 -> 1.93 | I27: 1.05 | J27: =H27*I27 -> 2.0265 | K27: =K21*2 -> 8 | L27: =F27 -> 0.227 | M27: =4.48333333333333/4.1*1.35*16500 -> 24357.622 | N27: =H27*K27*L27 -> 3.50488 | O27: =J27*K27*M27 -> 394885.77
B28: Panel Clip 15mm - Pentapost D: DS50 (PBP-100000-5800-LB20) | E28: =E22 -> 1625 | F28: 0.227 | G28: m | H28: =E28/1000 -> 1.625 | I28: 1.05 | J28: =H28*I28 -> 1.70625 | K28: =K22*2 -> 8 | L28: =F28 -> 0.227 | M28: =4.48333333333333/4.1*1.35*16500 -> 24357.622 | N28: =H28*K28*L28 -> 2.951 | O28: =J28*K28*M28 -> 332481.54
B29: Panel Clip 15mm - Interpost H: DS50 (PBP-100000-5800-LB20) | E29: =E23 -> 1420 | F29: 0.227 | G29: m | H29: =E29/1000 -> 1.42 | I29: 1.05 | J29: =H29*I29 -> 1.491 | K29: =K23*2 -> 4 | L29: =F29 -> 0.227 | M29: =4.48333333333333/4.1*1.35*16500 -> 24357.622 | N29: =H29*K29*L29 -> 1.28936 | O29: =J29*K29*M29 -> 145268.86
B30: Panel Clip 15mm - Interpost W: DS50 (PBP-100000-5800-LB20) | E30: =E24 -> 1930 | F30: 0.227 | G30: m | H30: =E30/1000 -> 1.93 | I30: 1.05 | J30: =H30*I30 -> 2.0265 | K30: =K24*2 -> 4 | L30: =F30 -> 0.227 | M30: =4.48333333333333/4.1*1.35*16500 -> 24357.622 | N30: =H30*K30*L30 -> 1.75244 | O30: =J30*K30*M30 -> 197442.88
B31: Panel Clip 15mm - Interpost D: DS50 (PBP-100000-5800-LB20) | E31: =E25 -> 1625 | F31: 0.227 | G31: m | H31: =E31/1000 -> 1.625 | I31: 1.05 | J31: =H31*I31 -> 1.70625 | K31: =K25*2 -> 4 | L31: =F31 -> 0.227 | M31: =4.48333333333333/4.1*1.35*16500 -> 24357.622 | N31: =H31*K31*L31 -> 1.4755 | O31: =J31*K31*M31 -> 166240.77
B32: Gasket - Pentapost (H): 3mmT x 18mmW x 9mL | E32: =E20 -> 1420 | F32: 0.00135 | G32: m | H32: =E32/1000 -> 1.42 | I32: 1.05 | J32: =H32*I32 -> 1.491 | K32: =K26 -> 8 | L32: =J32*K32 -> 11.928 | M32: =4.6/4.1*1.35*16500 -> 24991.463 | N32: =H32*K32*L32 -> 135.50208 | O32: =J32*K32*M32 -> 298098.18
B33: Gasket - Pentapost (W): 3mmT x 18mmW x 9mL | E33: =E21 -> 1930 | F33: 0.00135 | G33: m | H33: =E33/1000 -> 1.93 | I33: 1.05 | J33: =H33*I33 -> 2.0265 | K33: =K27 -> 8 | L33: =J33*K33 -> 16.212 | M33: =4.6/4.1*1.35*16500 -> 24991.463 | N33: =H33*K33*L33 -> 250.31328 | O33: =J33*K33*M33 -> 405161.6
B34: Gasket - Pentapost (D): 3mmT x 18mmW x 9mL | E34: =E22 -> 1625 | F34: 0.00135 | G34: m | H34: =E34/1000 -> 1.625 | I34: 1.05 | J34: =H34*I34 -> 1.70625 | K34: =K28 -> 8 | L34: =J34*K34 -> 13.65 | M34: =4.6/4.1*1.35*16500 -> 24991.463 | N34: =H34*K34*L34 -> 177.45 | O34: =J34*K34*M34 -> 341133.48
B35: Gasket - Interpost (H): 3mmT x 18mmW x 9mL | E35: =E23 -> 1420 | F35: 0.00135 | G35: m | H35: =E35/1000 -> 1.42 | I35: 1.05 | J35: =H35*I35 -> 1.491 | K35: =K29 -> 4 | L35: =J35*K35 -> 5.964 | M35: =4.6/4.1*1.35*16500 -> 24991.463 | N35: =H35*K35*L35 -> 33.87552 | O35: =J35*K35*M35 -> 149049.09
B36: Gasket - Interpost (W): 3mmT x 18mmW x 9mL | E36: =E24 -> 1930 | F36: 0.00135 | G36: m | H36: =E36/1000 -> 1.93 | I36: 1.05 | J36: =H36*I36 -> 2.0265 | K36: =K30 -> 4 | L36: =J36*K36 -> 8.106 | M36: =4.6/4.1*1.35*16500 -> 24991.463 | N36: =H36*K36*L36 -> 62.57832 | O36: =J36*K36*M36 -> 202580.8
B37: Gasket - Interpost (D): 3mmT x 18mmW x 9mL | E37: =E25 -> 1625 | F37: 0.00135 | G37: m | H37: =E37/1000 -> 1.625 | I37: 1.05 | J37: =H37*I37 -> 1.70625 | K37: =K31 -> 4 | L37: =J37*K37 -> 6.825 | M37: =4.6/4.1*1.35*16500 -> 24991.463 | N37: =H37*K37*L37 -> 44.3625 | O37: =J37*K37*M37 -> 170566.74
B38: Rubber Insert - Pentapost (H): 1 roll = 200M | E38: =E26 -> 1420 | F38: 0.00135 | G38: m | H38: =E38/1000 -> 1.42 | I38: 1.05 | J38: =H38*I38 -> 1.491 | K38: =K32 -> 8 | L38: =J38*K38 -> 11.928 | M38: 9000 | N38: =H38*K38*L38 -> 135.50208 | O38: =J38*K38*M38 -> 107352
B39: Rubber Insert - Pentapost (W): 1 roll = 200M | E39: =E27 -> 1930 | F39: 0.00135 | G39: m | H39: =E39/1000 -> 1.93 | I39: 1.05 | J39: =H39*I39 -> 2.0265 | K39: =K33 -> 8 | L39: =J39*K39 -> 16.212 | M39: 9000 | N39: =H39*K39*L39 -> 250.31328 | O39: =J39*K39*M39 -> 145908
B40: Rubber Insert - Pentapost (D): 1 roll = 200M | E40: =E28 -> 1625 | F40: 0.00135 | G40: m | H40: =E40/1000 -> 1.625 | I40: 1.05 | J40: =H40*I40 -> 1.70625 | K40: =K34 -> 8 | L40: =J40*K40 -> 13.65 | M40: 9000 | N40: =H40*K40*L40 -> 177.45 | O40: =J40*K40*M40 -> 122850
B41: Rubber Insert - Interpost (H): 1 roll = 200M | E41: =E29 -> 1420 | F41: 0.00135 | G41: m | H41: =E41/1000 -> 1.42 | I41: 1.05 | J41: =H41*I41 -> 1.491 | K41: =K35 -> 4 | L41: =J41*K41 -> 5.964 | M41: 9000 | N41: =H41*K41*L41 -> 33.87552 | O41: =J41*K41*M41 -> 53676
B42: Rubber Insert - Interpost (W): 1 roll = 200M | E42: =E30 -> 1930 | F42: 0.00135 | G42: m | H42: =E42/1000 -> 1.93 | I42: 1.05 | J42: =H42*I42 -> 2.0265 | K42: =K36 -> 4 | L42: =J42*K42 -> 8.106 | M42: 9000 | N42: =H42*K42*L42 -> 62.57832 | O42: =J42*K42*M42 -> 72954
B43: Rubber Insert - Interpost (D): 1 roll = 200M | E43: =E31 -> 1625 | F43: 0.00135 | G43: m | H43: =E43/1000 -> 1.625 | I43: 1.05 | J43: =H43*I43 -> 1.70625 | K43: =K37 -> 4 | L43: =J43*K43 -> 6.825 | M43: 9000 | N43: =H43*K43*L43 -> 44.3625 | O43: =J43*K43*M43 -> 61425
B44: Front Panel: Inner/Outer Liner (H x W) | C44: 0.55 | D44: =C2 -> 1420 | E44: =D2 -> 1930 | F44: 7860 | G44: kG | H44: =C44/1000*D44/1000*E44/1000*F44 -> 11.847614 | I44: 1.15 | J44: =H44*I44 -> 13.624756 | K44: 2 | L44: 1 | M44: 32000 | N44: =H44*K44*L44 -> 23.695228 | O44: =J44*K44*M44 -> 871984.38
B45: Front Panel: PU | C45: 50 | D45: =D44 -> 1420 | E45: =E44 -> 1930 | F45: 40 | G45: kG | H45: =C45/1000*D45/1000*E45/1000*F45 -> 5.4812 | I45: 1.1 | J45: =H45*I45 -> 6.02932 | K45: 1 | L45: 1 | M45: 50000 | N45: =H45*K45*L45 -> 5.4812 | O45: =J45*K45*M45 -> 301466
B46: Back Panel: Inner/Outer Liner (H x W) | C46: 0.55 | D46: =D44 -> 1420 | E46: =E44 -> 1930 | F46: 7860 | G46: kG | H46: =C46/1000*D46/1000*E46/1000*F46 -> 11.847614 | I46: 1.15 | J46: =H46*I46 -> 13.624756 | K46: 2 | L46: 1 | M46: 32000 | N46: =H46*K46*L46 -> 23.695228 | O46: =J46*K46*M46 -> 871984.38
B47: Back Panel: PU | C47: 50 | D47: =D44 -> 1420 | E47: =E44 -> 1930 | F47: 40 | G47: kG | H47: =C47/1000*D47/1000*E47/1000*F47 -> 5.4812 | I47: 1.1 | J47: =H47*I47 -> 6.02932 | K47: 1 | L47: 1 | M47: 50000 | N47: =H47*K47*L47 -> 5.4812 | O47: =J47*K47*M47 -> 301466
B48: Top Panel: Inner/Outer Liner (W x D) | C48: 0.55 | D48: =D2 -> 1930 | E48: =E2 -> 1625 | F48: 7860 | G48: kG | H48: =C48/1000*D48/1000*E48/1000*F48 -> 13.558009 | I48: 1.15 | J48: =H48*I48 -> 15.59171 | K48: 2 | L48: 1 | M48: 32000 | N48: =H48*K48*L48 -> 27.116018 | O48: =J48*K48*M48 -> 997869.44
B49: Top Panel: PU | C49: 50 | D49: =D48 -> 1930 | E49: =E48 -> 1625 | F49: 40 | G49: kG | H49: =C49/1000*D49/1000*E49/1000*F49 -> 6.2725 | I49: 1.1 | J49: =H49*I49 -> 6.89975 | K49: 1 | L49: 1 | M49: 50000 | N49: =H49*K49*L49 -> 6.2725 | O49: =J49*K49*M49 -> 344987.5
B50: Bottom Panel: Inner/Outer Liner (W x D) | C50: 0.55 | D50: =D48 -> 1930 | E50: =E48 -> 1625 | F50: 7860 | G50: kG | H50: =C50/1000*D50/1000*E50/1000*F50 -> 13.558009 | I50: 1.15 | J50: =H50*I50 -> 15.59171 | K50: 2 | L50: 1 | M50: 32000 | N50: =H50*K50*L50 -> 27.116018 | O50: =J50*K50*M50 -> 997869.44
B51: Bottom Panel: PU | C51: 50 | D51: =D48 -> 1930 | E51: =E48 -> 1625 | F51: 40 | G51: kG | H51: =C51/1000*D51/1000*E51/1000*F51 -> 6.2725 | I51: 1.1 | J51: =H51*I51 -> 6.89975 | K51: 1 | L51: 1 | M51: 50000 | N51: =H51*K51*L51 -> 6.2725 | O51: =J51*K51*M51 -> 344987.5
B52: LH Panel: Inner/Outer Liner (H x D) | C52: 0.55 | D52: =C2 -> 1420 | E52: =E2 -> 1625 | F52: 7860 | G52: kG | H52: =C52/1000*D52/1000*E52/1000*F52 -> 9.9753225 | I52: 1.15 | J52: =H52*I52 -> 11.471621 | K52: 2 | L52: 1 | M52: 32000 | N52: =H52*K52*L52 -> 19.950645 | O52: =J52*K52*M52 -> 734183.74
B53: LH Panel: PU | C53: 50 | D53: =D52 -> 1420 | E53: =E52 -> 1625 | F53: 40 | G53: kG | H53: =C53/1000*D53/1000*E53/1000*F53 -> 4.615 | I53: 1.1 | J53: =H53*I53 -> 5.0765 | K53: 1 | L53: 1 | M53: 50000 | N53: =H53*K53*L53 -> 4.615 | O53: =J53*K53*M53 -> 253825
B54: RH Panel: Inner/Outer Liner (H x D) | C54: 0.55 | D54: =D52 -> 1420 | E54: =E52 -> 1625 | F54: 7860 | G54: kG | H54: =C54/1000*D54/1000*E54/1000*F54 -> 9.9753225 | I54: 1.15 | J54: =H54*I54 -> 11.471621 | K54: 2 | L54: 1 | M54: 32000 | N54: =H54*K54*L54 -> 19.950645 | O54: =J54*K54*M54 -> 734183.74
B55: RH Panel: PU | C55: 50 | D55: =D52 -> 1420 | E55: =E52 -> 1625 | F55: 40 | G55: kG | H55: =C55/1000*D55/1000*E55/1000*F55 -> 4.615 | I55: 1.1 | J55: =H55*I55 -> 5.0765 | K55: 1 | L55: 1 | M55: 50000 | N55: =H55*K55*L55 -> 4.615 | O55: =J55*K55*M55 -> 253825
N56: =H56*K56*L56 -> 0 | O56: =J56*K56*M56 -> 0
A57: =B3 -> Section 2 | B57: Cornerpiece | F57: =0.42476+0.15 -> 0.57476 | G57: Pc | H57: 8 | I57: 1 | J57: =H57*I57 -> 8 | K57: 0 | L57: =F57 -> 0.57476 | M57: =18.1*2*2500 -> 90500 | N57: =H57*K57*L57 -> 0 | O57: =J57*K57*M57 -> 0
B58: Omega Joint | F58: 0.036 | G58: Pc | H58: 8 | I58: 1 | J58: =H58*I58 -> 8 | K58: 0 | L58: =F58 -> 0.036 | M58: =2.9*2*2500 -> 14500 | N58: =H58*K58*L58 -> 0 | O58: =J58*K58*M58 -> 0
B59: Pentapost Assy H: DS5056 (PTTBP160-50-5800-LB20) | E59: =C3 -> 0 | F59: =11.596551724138/6 -> 1.9327586 | G59: m | H59: =E59/1000 -> 0 | I59: 1.05 | J59: =H59*I59 -> 0 | K59: 4 | L59: =F59 -> 1.9327586 | M59: 175000 | N59: =H59*K59*L59 -> 0 | O59: =J59*K59*M59 -> 0
B60: Pentapost Assy W: DS5056 (PTTBP160-50-5800-LB20) | E60: =D3 -> 0 | F60: =11.596551724138/6 -> 1.9327586 | G60: m | H60: =E60/1000 -> 0 | I60: 1.05 | J60: =H60*I60 -> 0 | K60: 4 | L60: =F60 -> 1.9327586 | M60: 175000 | N60: =H60*K60*L60 -> 0 | O60: =J60*K60*M60 -> 0
B61: Pentapost Assy D: DS5056 (PTTBP160-50-5800-LB20) | E61: =E3 -> 0 | F61: =11.596551724138/6 -> 1.9327586 | G61: m | H61: =E61/1000 -> 0 | I61: 1.05 | J61: =H61*I61 -> 0 | K61: 4 | L61: =F61 -> 1.9327586 | M61: 175000 | N61: =H61*K61*L61 -> 0 | O61: =J61*K61*M61 -> 0
B62: Interpost Assy H: DS5040 (PTTBP270-50-5800-LB20) | E62: =E59 -> 0 | F62: =8.094/6 -> 1.349 | G62: m | H62: =E62/1000 -> 0 | I62: 1.05 | J62: =H62*I62 -> 0 | K62: 2 | L62: =F62 -> 1.349 | M62: 132000 | N62: =H62*K62*L62 -> 0 | O62: =J62*K62*M62 -> 0
B63: Interpost Assy W: DS5040 (PTTBP270-50-5800-LB20) | E63: =E60 -> 0 | F63: =8.094/6 -> 1.349 | G63: m | H63: =E63/1000 -> 0 | I63: 1.05 | J63: =H63*I63 -> 0 | K63: 2 | L63: =F63 -> 1.349 | M63: 132000 | N63: =H63*K63*L63 -> 0 | O63: =J63*K63*M63 -> 0
B64: Interpost Assy D: DS5040 (PTTBP270-50-5800-LB20) | E64: =E61 -> 0 | F64: =8.094/6 -> 1.349 | G64: m | H64: =E64/1000 -> 0 | I64: 1.05 | J64: =H64*I64 -> 0 | K64: 2 | L64: =F64 -> 1.349 | M64: 132000 | N64: =H64*K64*L64 -> 0 | O64: =J64*K64*M64 -> 0
B65: Panel Clip 15mm - Pentapost H: DS50 (PBP-100000-5800-LB20) | E65: =E59 -> 0 | F65: 0.227 | G65: m | H65: =E65/1000 -> 0 | I65: 1.05 | J65: =H65*I65 -> 0 | K65: =K59*2 -> 8 | L65: =F65 -> 0.227 | M65: =4.48333333333333/4.1*1.35*16500 -> 24357.622 | N65: =H65*K65*L65 -> 0 | O65: =J65*K65*M65 -> 0
B66: Panel Clip 15mm - Pentapost W: DS50 (PBP-100000-5800-LB20) | E66: =E60 -> 0 | F66: 0.227 | G66: m | H66: =E66/1000 -> 0 | I66: 1.05 | J66: =H66*I66 -> 0 | K66: =K60*2 -> 8 | L66: =F66 -> 0.227 | M66: =4.48333333333333/4.1*1.35*16500 -> 24357.622 | N66: =H66*K66*L66 -> 0 | O66: =J66*K66*M66 -> 0
B67: Panel Clip 15mm - Pentapost D: DS50 (PBP-100000-5800-LB20) | E67: =E61 -> 0 | F67: 0.227 | G67: m | H67: =E67/1000 -> 0 | I67: 1.05 | J67: =H67*I67 -> 0 | K67: =K61*2 -> 8 | L67: =F67 -> 0.227 | M67: =4.48333333333333/4.1*1.35*16500 -> 24357.622 | N67: =H67*K67*L67 -> 0 | O67: =J67*K67*M67 -> 0
B68: Panel Clip 15mm - Interpost H: DS50 (PBP-100000-5800-LB20) | E68: =E62 -> 0 | F68: 0.227 | G68: m | H68: =E68/1000 -> 0 | I68: 1.05 | J68: =H68*I68 -> 0 | K68: =K62*2 -> 4 | L68: =F68 -> 0.227 | M68: =4.48333333333333/4.1*1.35*16500 -> 24357.622 | N68: =H68*K68*L68 -> 0 | O68: =J68*K68*M68 -> 0
B69: Panel Clip 15mm - Interpost W: DS50 (PBP-100000-5800-LB20) | E69: =E63 -> 0 | F69: 0.227 | G69: m | H69: =E69/1000 -> 0 | I69: 1.05 | J69: =H69*I69 -> 0 | K69: =K63*2 -> 4 | L69: =F69 -> 0.227 | M69: =4.48333333333333/4.1*1.35*16500 -> 24357.622 | N69: =H69*K69*L69 -> 0 | O69: =J69*K69*M69 -> 0
B70: Panel Clip 15mm - Interpost D: DS50 (PBP-100000-5800-LB20) | E70: =E64 -> 0 | F70: 0.227 | G70: m | H70: =E70/1000 -> 0 | I70: 1.05 | J70: =H70*I70 -> 0 | K70: =K64*2 -> 4 | L70: =F70 -> 0.227 | M70: =4.48333333333333/4.1*1.35*16500 -> 24357.622 | N70: =H70*K70*L70 -> 0 | O70: =J70*K70*M70 -> 0
B71: Gasket - Pentapost (H): 3mmT x 18mmW x 9mL | E71: =E59 -> 0 | F71: 0.00135 | G71: m | H71: =E71/1000 -> 0 | I71: 1.05 | J71: =H71*I71 -> 0 | K71: =K65 -> 8 | L71: =J71*K71 -> 0 | M71: =4.6/4.1*1.35*16500 -> 24991.463 | N71: =H71*K71*L71 -> 0 | O71: =J71*K71*M71 -> 0
B72: Gasket - Pentapost (W): 3mmT x 18mmW x 9mL | E72: =E60 -> 0 | F72: 0.00135 | G72: m | H72: =E72/1000 -> 0 | I72: 1.05 | J72: =H72*I72 -> 0 | K72: =K66 -> 8 | L72: =J72*K72 -> 0 | M72: =4.6/4.1*1.35*16500 -> 24991.463 | N72: =H72*K72*L72 -> 0 | O72: =J72*K72*M72 -> 0
B73: Gasket - Pentapost (D): 3mmT x 18mmW x 9mL | E73: =E61 -> 0 | F73: 0.00135 | G73: m | H73: =E73/1000 -> 0 | I73: 1.05 | J73: =H73*I73 -> 0 | K73: =K67 -> 8 | L73: =J73*K73 -> 0 | M73: =4.6/4.1*1.35*16500 -> 24991.463 | N73: =H73*K73*L73 -> 0 | O73: =J73*K73*M73 -> 0
B74: Gasket - Interpost (H): 3mmT x 18mmW x 9mL | E74: =E62 -> 0 | F74: 0.00135 | G74: m | H74: =E74/1000 -> 0 | I74: 1.05 | J74: =H74*I74 -> 0 | K74: =K68 -> 4 | L74: =J74*K74 -> 0 | M74: =4.6/4.1*1.35*16500 -> 24991.463 | N74: =H74*K74*L74 -> 0 | O74: =J74*K74*M74 -> 0
B75: Gasket - Interpost (W): 3mmT x 18mmW x 9mL | E75: =E63 -> 0 | F75: 0.00135 | G75: m | H75: =E75/1000 -> 0 | I75: 1.05 | J75: =H75*I75 -> 0 | K75: =K69 -> 4 | L75: =J75*K75 -> 0 | M75: =4.6/4.1*1.35*16500 -> 24991.463 | N75: =H75*K75*L75 -> 0 | O75: =J75*K75*M75 -> 0
B76: Gasket - Interpost (D): 3mmT x 18mmW x 9mL | E76: =E64 -> 0 | F76: 0.00135 | G76: m | H76: =E76/1000 -> 0 | I76: 1.05 | J76: =H76*I76 -> 0 | K76: =K70 -> 4 | L76: =J76*K76 -> 0 | M76: =4.6/4.1*1.35*16500 -> 24991.463 | N76: =H76*K76*L76 -> 0 | O76: =J76*K76*M76 -> 0
B77: Rubber Insert - Pentapost (H): 1 roll = 200M | E77: =E65 -> 0 | F77: 0.00135 | G77: m | H77: =E77/1000 -> 0 | I77: 1.05 | J77: =H77*I77 -> 0 | K77: =K71 -> 8 | L77: =J77*K77 -> 0 | M77: 9000 | N77: =H77*K77*L77 -> 0 | O77: =J77*K77*M77 -> 0
B78: Rubber Insert - Pentapost (W): 1 roll = 200M | E78: =E66 -> 0 | F78: 0.00135 | G78: m | H78: =E78/1000 -> 0 | I78: 1.05 | J78: =H78*I78 -> 0 | K78: =K72 -> 8 | L78: =J78*K78 -> 0 | M78: 9000 | N78: =H78*K78*L78 -> 0 | O78: =J78*K78*M78 -> 0
B79: Rubber Insert - Pentapost (D): 1 roll = 200M | E79: =E67 -> 0 | F79: 0.00135 | G79: m | H79: =E79/1000 -> 0 | I79: 1.05 | J79: =H79*I79 -> 0 | K79: =K73 -> 8 | L79: =J79*K79 -> 0 | M79: 9000 | N79: =H79*K79*L79 -> 0 | O79: =J79*K79*M79 -> 0
B80: Rubber Insert - Interpost (H): 1 roll = 200M | E80: =E68 -> 0 | F80: 0.00135 | G80: m | H80: =E80/1000 -> 0 | I80: 1.05 | J80: =H80*I80 -> 0 | K80: =K74 -> 4 | L80: =J80*K80 -> 0 | M80: 9000 | N80: =H80*K80*L80 -> 0 | O80: =J80*K80*M80 -> 0
B81: Rubber Insert - Interpost (W): 1 roll = 200M | E81: =E69 -> 0 | F81: 0.00135 | G81: m | H81: =E81/1000 -> 0 | I81: 1.05 | J81: =H81*I81 -> 0 | K81: =K75 -> 4 | L81: =J81*K81 -> 0 | M81: 9000 | N81: =H81*K81*L81 -> 0 | O81: =J81*K81*M81 -> 0
B82: Rubber Insert - Interpost (D): 1 roll = 200M | E82: =E70 -> 0 | F82: 0.00135 | G82: m | H82: =E82/1000 -> 0 | I82: 1.05 | J82: =H82*I82 -> 0 | K82: =K76 -> 4 | L82: =J82*K82 -> 0 | M82: 9000 | N82: =H82*K82*L82 -> 0 | O82: =J82*K82*M82 -> 0
B83: Front Panel: Inner/Outer Liner (H x W) | C83: 0.55 | D83: =C3 -> 0 | E83: =D3 -> 0 | F83: 7860 | G83: kG | H83: =C83/1000*D83/1000*E83/1000*F83 -> 0 | I83: 1.15 | J83: =H83*I83 -> 0 | K83: 2 | L83: 1 | M83: 32000 | N83: =H83*K83*L83 -> 0 | O83: =J83*K83*M83 -> 0
B84: Front Panel: PU | C84: 50 | D84: =D83 -> 0 | E84: =E83 -> 0 | F84: 40 | G84: kG | H84: =C84/1000*D84/1000*E84/1000*F84 -> 0 | I84: 1.1 | J84: =H84*I84 -> 0 | K84: 1 | L84: 1 | M84: 50000 | N84: =H84*K84*L84 -> 0 | O84: =J84*K84*M84 -> 0
B85: Back Panel: Inner/Outer Liner (H x W) | C85: 0.55 | D85: =D83 -> 0 | E85: =E83 -> 0 | F85: 7860 | G85: kG | H85: =C85/1000*D85/1000*E85/1000*F85 -> 0 | I85: 1.15 | J85: =H85*I85 -> 0 | K85: 2 | L85: 1 | M85: 32000 | N85: =H85*K85*L85 -> 0 | O85: =J85*K85*M85 -> 0
B86: Back Panel: PU | C86: 50 | D86: =D83 -> 0 | E86: =E83 -> 0 | F86: 40 | G86: kG | H86: =C86/1000*D86/1000*E86/1000*F86 -> 0 | I86: 1.1 | J86: =H86*I86 -> 0 | K86: 1 | L86: 1 | M86: 50000 | N86: =H86*K86*L86 -> 0 | O86: =J86*K86*M86 -> 0
B87: Top Panel: Inner/Outer Liner (W x D) | C87: 0.55 | D87: =D3 -> 0 | E87: =E9 -> 0 | F87: 7860 | G87: kG | H87: =C87/1000*D87/1000*E87/1000*F87 -> 0 | I87: 1.15 | J87: =H87*I87 -> 0 | K87: 2 | L87: 1 | M87: 32000 | N87: =H87*K87*L87 -> 0 | O87: =J87*K87*M87 -> 0
B88: Top Panel: PU | C88: 50 | D88: =D87 -> 0 | E88: =E87 -> 0 | F88: 40 | G88: kG | H88: =C88/1000*D88/1000*E88/1000*F88 -> 0 | I88: 1.1 | J88: =H88*I88 -> 0 | K88: 1 | L88: 1 | M88: 50000 | N88: =H88*K88*L88 -> 0 | O88: =J88*K88*M88 -> 0
B89: Bottom Panel: Inner/Outer Liner (W x D) | C89: 0.55 | D89: =D87 -> 0 | E89: =E87 -> 0 | F89: 7860 | G89: kG | H89: =C89/1000*D89/1000*E89/1000*F89 -> 0 | I89: 1.15 | J89: =H89*I89 -> 0 | K89: 2 | L89: 1 | M89: 32000 | N89: =H89*K89*L89 -> 0 | O89: =J89*K89*M89 -> 0
B90: Bottom Panel: PU | C90: 50 | D90: =D87 -> 0 | E90: =E87 -> 0 | F90: 40 | G90: kG | H90: =C90/1000*D90/1000*E90/1000*F90 -> 0 | I90: 1.1 | J90: =H90*I90 -> 0 | K90: 1 | L90: 1 | M90: 50000 | N90: =H90*K90*L90 -> 0 | O90: =J90*K90*M90 -> 0
B91: LH Panel: Inner/Outer Liner (H x D) | C91: 0.55 | D91: =C3 -> 0 | E91: =E3 -> 0 | F91: 7860 | G91: kG | H91: =C91/1000*D91/1000*E91/1000*F91 -> 0 | I91: 1.15 | J91: =H91*I91 -> 0 | K91: 2 | L91: 1 | M91: 32000 | N91: =H91*K91*L91 -> 0 | O91: =J91*K91*M91 -> 0
B92: LH Panel: PU | C92: 50 | D92: =D91 -> 0 | E92: =E91 -> 0 | F92: 40 | G92: kG | H92: =C92/1000*D92/1000*E92/1000*F92 -> 0 | I92: 1.1 | J92: =H92*I92 -> 0 | K92: 1 | L92: 1 | M92: 50000 | N92: =H92*K92*L92 -> 0 | O92: =J92*K92*M92 -> 0
B93: RH Panel: Inner/Outer Liner (H x D) | C93: 0.55 | D93: =D91 -> 0 | E93: =E91 -> 0 | F93: 7860 | G93: kG | H93: =C93/1000*D93/1000*E93/1000*F93 -> 0 | I93: 1.15 | J93: =H93*I93 -> 0 | K93: 2 | L93: 1 | M93: 32000 | N93: =H93*K93*L93 -> 0 | O93: =J93*K93*M93 -> 0
B94: RH Panel: PU | C94: 50 | D94: =D91 -> 0 | E94: =E91 -> 0 | F94: 40 | G94: kG | H94: =C94/1000*D94/1000*E94/1000*F94 -> 0 | I94: 1.1 | J94: =H94*I94 -> 0 | K94: 1 | L94: 1 | M94: 50000 | N94: =H94*K94*L94 -> 0 | O94: =J94*K94*M94 -> 0
N95: =H95*K95*L95 -> 0 | O95: =J95*K95*M95 -> 0
N96: =SUM(N18:N95) -> 1652.747 | O96: =SUM(O18:O95) -> 16541940

Sheet 3. AHU-Structure
B1: TDM50-040x040 | C1: H | D1: W | E1: D
B2: Section 1 | C2: 1420 | D2: 1930 | E2: 1625 | G2: SA | H2: LPS | I2: =I3*1000 -> 748.03194 | K2: Qc | L2: kW | M2: 20.31 | O2: 3/8''DX 457FH x 733FL x 6R x 12FPI x 9NC
B3: Section 2 | H3: CMS | I3: =I4/3600 -> 0.74803194 | L3: Btu/h | M3: =M2*3412 -> 69297.72
H4: CMH | I4: =I5*1.699 -> 2692.915 | L4: Hp | M4: =M3/10000 -> 6.929772
H5: CFM | I5: 1585 | K5: Qs | L5: kW | M5: 93.55
G6: RA | H6: LPS | I6: =I7*1000 -> 4530.6667 | L6: Btu/h | M6: =M5*3412 -> 319192.6
H7: CMS | I7: =I8/3600 -> 4.5306667 | L7: Hp | M7: =M6/10000 -> 31.91926
B8: Skid 1 | D8: =D2 -> 1930 | E8: =E2 -> 1625 | H8: CMH | I8: =I9*1.699 -> 16310.4
B9: Skid 2 | D9: =D3 -> 0 | E9: =E3 -> 0 | H9: CFM | I9: 9600
B12: VD1 | C12: 810 | D12: 1100
B13: VD2 | C13: 310 | D13: 800
B14: RA Opening | C14: =C2-100 -> 1320 | D14: =D2-100 -> 1830
B15: SA Opening | C15: =C2-100 -> 1320 | D15: =D2-100 -> 1830
C17: T | D17: L | E17: W | F17: MX | G17: UoM | H17: Qty/Pc | I17: WF | J17: Qty | K17: N | L17: U/W(kG) | M17: Rp/Uom | N17: kG | O17: Rp
A18: Flange | B18: Fresh air Flange (W) | C18: 1.5 | D18: =25+50+25 -> 100 | E18: 210 | F18: 7860 | G18: kG | H18: =C18/1000*D18/1000*E18/1000*F18 -> 0.24759 | I18: 1.5 | J18: =H18*I18 -> 0.371385 | K18: 0 | L18: 1 | M18: 24000 | N18: =H18*K18*L18 -> 0 | O18: =J18*K18*M18 -> 0
B19: Fresh Flange (H) | C19: 1.5 | D19: =25+50+25 -> 100 | E19: 300 | F19: 7860 | G19: kG | H19: =C19/1000*D19/1000*E19/1000*F19 -> 0.3537 | I19: 1.5 | J19: =H19*I19 -> 0.53055 | K19: 0 | L19: 1 | M19: 24000 | N19: =H19*K19*L19 -> 0 | O19: =J19*K19*M19 -> 0
B20: Return Flange (W) | C20: 1.5 | D20: =25+50+25 -> 100 | E20: =D14 -> 1830 | F20: 7860 | G20: kG | H20: =C20/1000*D20/1000*E20/1000*F20 -> 2.15757 | I20: 1.5 | J20: =H20*I20 -> 3.236355 | K20: 0 | L20: 1 | M20: 24000 | N20: =H20*K20*L20 -> 0 | O20: =J20*K20*M20 -> 0
B21: Return Flange (H) | C21: 1.5 | D21: =25+50+25 -> 100 | E21: =C14 -> 1320 | F21: 7860 | G21: kG | H21: =C21/1000*D21/1000*E21/1000*F21 -> 1.55628 | I21: 1.5 | J21: =H21*I21 -> 2.33442 | K21: 0 | L21: 1 | M21: 24000 | N21: =H21*K21*L21 -> 0 | O21: =J21*K21*M21 -> 0
B22: Intake Flange (W) | C22: 1.5 | D22: =25+50+25 -> 100 | E22: =D13 -> 800 | F22: 7860 | G22: kG | H22: =C22/1000*D22/1000*E22/1000*F22 -> 0.9432 | I22: 1.5 | J22: =H22*I22 -> 1.4148 | K22: 0 | L22: 1 | M22: 24000 | N22: =H22*K22*L22 -> 0 | O22: =J22*K22*M22 -> 0
B23: Intake Flange (H) | C23: 1.5 | D23: =25+50+25 -> 100 | E23: =C13 -> 310 | F23: 7860 | G23: kG | H23: =C23/1000*D23/1000*E23/1000*F23 -> 0.36549 | I23: 1.5 | J23: =H23*I23 -> 0.548235 | K23: 0 | L23: 1 | M23: 24000 | N23: =H23*K23*L23 -> 0 | O23: =J23*K23*M23 -> 0
B24: Supply Flange (W) | C24: 1.5 | D24: =25+50+25 -> 100 | E24: =D15 -> 1830 | F24: 7860 | G24: kG | H24: =C24/1000*D24/1000*E24/1000*F24 -> 2.15757 | I24: 1.5 | J24: =H24*I24 -> 3.236355 | K24: 2 | L24: 1 | M24: 24000 | N24: =H24*K24*L24 -> 4.31514 | O24: =J24*K24*M24 -> 155345.04
B25: Supply Flange (H) | C25: 1.5 | D25: =25+50+25 -> 100 | E25: =C15 -> 1320 | F25: 7860 | G25: kG | H25: =C25/1000*D25/1000*E25/1000*F25 -> 1.55628 | I25: 1.5 | J25: =H25*I25 -> 2.33442 | K25: 2 | L25: 1 | M25: 24000 | N25: =H25*K25*L25 -> 3.11256 | O25: =J25*K25*M25 -> 112052.16
A26: PF Rail 1-4 | B26: PF Filter Rail Support (H) | C26: 1.5 | D26: =25+50+25 -> 100 | E26: =C2-100 -> 1320 | F26: 7860 | G26: kG | H26: =C26/1000*D26/1000*E26/1000*F26 -> 1.55628 | I26: 1.15 | J26: =H26*I26 -> 1.789722 | K26: 2 | L26: 1 | M26: 24000 | N26: =H26*K26*L26 -> 3.11256 | O26: =J26*K26*M26 -> 85906.656
B27: PF Filter Rail Top/Bottom (W) | C27: 1.5 | D27: =25+50+25 -> 100 | E27: =D2-100 -> 1830 | F27: 7860 | G27: kG | H27: =C27/1000*D27/1000*E27/1000*F27 -> 2.15757 | I27: 1.15 | J27: =H27*I27 -> 2.4812055 | K27: 2 | L27: 1 | M27: 24000 | N27: =H27*K27*L27 -> 4.31514 | O27: =J27*K27*M27 -> 119097.86
B28: PF Filter Rail Center (W) | C28: 1.5 | D28: =25+50+25 -> 100 | E28: =D2-100 -> 1830 | F28: 7860 | G28: kG | H28: =C28/1000*D28/1000*E28/1000*F28 -> 2.15757 | I28: 1.15 | J28: =H28*I28 -> 2.4812055 | K28: 1 | L28: 1 | M28: 24000 | N28: =H28*K28*L28 -> 2.15757 | O28: =J28*K28*M28 -> 59548.932
A29: MPF Rail 1-4 | B29: MPF Filter Rail Support (H) | C29: 1.5 | D29: =25+50+25 -> 100 | E29: =E26 -> 1320 | F29: 7860 | G29: kG | H29: =C29/1000*D29/1000*E29/1000*F29 -> 1.55628 | I29: 1.15 | J29: =H29*I29 -> 1.789722 | K29: 2 | L29: 1 | M29: 24000 | N29: =H29*K29*L29 -> 3.11256 | O29: =J29*K29*M29 -> 85906.656
B30: MPF Filter Rail Top/Bottom | C30: 1.5 | D30: =25+25+25 -> 75 | E30: =E27 -> 1830 | F30: 7860 | G30: kG | H30: =C30/1000*D30/1000*E30/1000*F30 -> 1.6181775 | I30: 1.15 | J30: =H30*I30 -> 1.8609041 | K30: 2 | L30: 1 | M30: 24000 | N30: =H30*K30*L30 -> 3.236355 | O30: =J30*K30*M30 -> 89323.398
B31: MPF Filter Rail Center | C31: 1.5 | D31: =25+25+25 -> 75 | E31: =E28 -> 1830 | F31: 7860 | G31: kG | H31: =C31/1000*D31/1000*E31/1000*F31 -> 1.6181775 | I31: 1.15 | J31: =H31*I31 -> 1.8609041 | K31: 1 | L31: 1 | M31: 24000 | N31: =H31*K31*L31 -> 1.6181775 | O31: =J31*K31*M31 -> 44661.699
A32: PF Rail 2-1 | B32: PF Filter Rail Support (H) | C32: 1.5 | D32: =25+50+25 -> 100 | E32: =C6-100 -> -100 | F32: 7860 | G32: kG | H32: =C32/1000*D32/1000*E32/1000*F32 -> -0.1179 | I32: 1.15 | J32: =H32*I32 -> -0.135585 | K32: 0 | L32: 1 | M32: 24000 | N32: =H32*K32*L32 -> 0 | O32: =J32*K32*M32 -> 0
B33: PF Filter Rail Top/Bottom (W) | C33: 1.5 | D33: =25+50+25 -> 100 | E33: =D6-100 -> -100 | F33: 7860 | G33: kG | H33: =C33/1000*D33/1000*E33/1000*F33 -> -0.1179 | I33: 1.15 | J33: =H33*I33 -> -0.135585 | K33: 0 | L33: 1 | M33: 24000 | N33: =H33*K33*L33 -> 0 | O33: =J33*K33*M33 -> 0
B34: PF Filter Rail Center (W) | C34: 1.5 | D34: =25+50+25 -> 100 | E34: =D6-100 -> -100 | F34: 7860 | G34: kG | H34: =C34/1000*D34/1000*E34/1000*F34 -> -0.1179 | I34: 1 | J34: =H34*I34 -> -0.1179 | K34: 0 | L34: 1 | M34: 24000 | N34: =H34*K34*L34 -> 0 | O34: =J34*K34*M34 -> 0
A35: MPF Rail 2-1 | B35: MPF Filter Rail Support (H) | C35: 1.5 | D35: =25+50+25 -> 100 | E35: =E32 -> -100 | F35: 7860 | G35: kG | H35: =C35/1000*D35/1000*E35/1000*F35 -> -0.1179 | I35: 1.15 | J35: =H35*I35 -> -0.135585 | K35: 0 | L35: 1 | M35: 24000 | N35: =H35*K35*L35 -> 0 | O35: =J35*K35*M35 -> 0
B36: MPF Filter Rail Top/Bottom | C36: 1.5 | D36: =25+25+25 -> 75 | E36: =E33 -> -100 | F36: 7860 | G36: kG | H36: =C36/1000*D36/1000*E36/1000*F36 -> -0.088425 | I36: 1.15 | J36: =H36*I36 -> -0.10168875 | K36: 0 | L36: 1 | M36: 24000 | N36: =H36*K36*L36 -> 0 | O36: =J36*K36*M36 -> 0
B37: MPF Filter Rail Center | C37: 1.5 | D37: =25+25+25 -> 75 | E37: =E34 -> -100 | F37: 7860 | G37: kG | H37: =C37/1000*D37/1000*E37/1000*F37 -> -0.088425 | I37: 1 | J37: =H37*I37 -> -0.088425 | K37: 0 | L37: 1 | M37: 24000 | N37: =H37*K37*L37 -> 0 | O37: =J37*K37*M37 -> 0
A38: Drain Pan Assy | B38: Drain Pan#1 (W) | C38: 1.5 | D38: =600+100 -> 700 | E38: =D2-100+100 -> 1930 | F38: 8800 | G38: kG | H38: =C38/1000*D38/1000*E38/1000*F38 -> 17.8332 | I38: 1.15 | J38: =H38*I38 -> 20.50818 | K38: 1 | L38: 1 | M38: 55000 | N38: =H38*K38*L38 -> 17.8332 | O38: =J38*K38*M38 -> 1127949.9
B39: Drain Pan L/R Support (W) | C39: 1.5 | D39: =150+25+25 -> 200 | E39: =D2-100 -> 1830 | F39: 8800 | G39: kG | H39: =C39/1000*D39/1000*E39/1000*F39 -> 4.8312 | I39: 1.15 | J39: =H39*I39 -> 5.55588 | K39: 2 | L39: 1 | M39: 55000 | N39: =H39*K39*L39 -> 9.6624 | O39: =J39*K39*M39 -> 611146.8
B40: Drain Pan L/R Pillar | C40: 2.5 | D40: =15+50+15 -> 80 | E40: =150+15*2 -> 180 | F40: 8800 | G40: kG | H40: =C40/1000*D40/1000*E40/1000*F40 -> 0.3168 | I40: 1.15 | J40: =H40*I40 -> 0.36432 | K40: 6 | L40: 1 | M40: 55000 | N40: =H40*K40*L40 -> 1.9008 | O40: =J40*K40*M40 -> 120225.6
B41: Coil Support | C41: 2.5 | D41: =15+50+15 -> 80 | E41: =650+50*2 -> 750 | F41: 8800 | G41: kG | H41: =C41/1000*D41/1000*E41/1000*F41 -> 1.32 | I41: 1.15 | J41: =H41*I41 -> 1.518 | K41: 6 | L41: 1 | M41: 55000 | N41: =H41*K41*L41 -> 7.92 | O41: =J41*K41*M41 -> 500940
A42: Intake Rainhood | B42: Top | C42: 1.5 | D42: 300 | E42: =D13 -> 800 | F42: 7860 | G42: kG | H42: =C42/1000*D42/1000*E42/1000*F42 -> 2.8296 | I42: 1.15 | J42: =H42*I42 -> 3.25404 | K42: 1 | L42: 1 | M42: 24000 | N42: =H42*K42*L42 -> 2.8296 | O42: =J42*K42*M42 -> 78096.96
B43: Side | C43: 1.5 | D43: =150+25+25 -> 200 | E43: 300 | F43: 7860 | G43: kG | H43: =C43/1000*D43/1000*E43/1000*F43 -> 0.7074 | I43: 2.15 | J43: =H43*I43 -> 1.52091 | K43: 2 | L43: 1 | M43: 24000 | N43: =H43*K43*L43 -> 1.4148 | O43: =J43*K43*M43 -> 73003.68
A44: Fan Partition Assy 1-3 | B44: Partition (H x W) | C44: 1.5 | D44: =C2 -> 1420 | E44: =D2 -> 1930 | F44: 7860 | G44: kG | H44: =C44/1000*D44/1000*E44/1000*F44 -> 32.311674 | I44: 1.15 | J44: =H44*I44 -> 37.158425 | K44: 1 | L44: 1 | M44: 24000 | N44: =H44*K44*L44 -> 32.311674 | O44: =J44*K44*M44 -> 891802.2
B45: Base Channel-UNP125 L/R (W) | C45: 2.5 | D45: =15+25+50+25+15 -> 130 | E45: =D2 -> 1930 | F45: 7860 | G45: kG | H45: =C45/1000*D45/1000*E45/1000*F45 -> 4.930185 | I45: 1.15 | J45: =H45*I45 -> 5.6697127 | K45: 2 | L45: 1 | M45: 24000 | N45: =H45*K45*L45 -> 9.86037 | O45: =J45*K45*M45 -> 272146.21
B46: Blower/Motor Channel-UNP125 F/B | C46: 2.5 | D46: =15+25+50+25+15 -> 130 | E46: =E45*0.6 -> 1158 | F46: 7860 | G46: kG | H46: =C46/1000*D46/1000*E46/1000*F46 -> 2.958111 | I46: 2.15 | J46: =H46*I46 -> 6.3599386 | K46: 2 | L46: 1 | M46: 24000 | N46: =H46*K46*L46 -> 5.916222 | O46: =J46*K46*M46 -> 305277.06
B47: Blower Support-UNP125 L/R (D) | C47: 2.5 | D47: =25+50+25 -> 100 | E47: =E2*0.6 -> 975 | F47: 7860 | G47: kG | H47: =C47/1000*D47/1000*E47/1000*F47 -> 1.915875 | I47: 2.15 | J47: =H47*I47 -> 4.1191312 | K47: 2 | L47: 1 | M47: 24000 | N47: =H47*K47*L47 -> 3.83175 | O47: =J47*K47*M47 -> 197718.3
B48: Motor Support-UNP125 L/R (D) | C48: 2.5 | D48: =25+50+25 -> 100 | E48: =E2*0.6 -> 975 | F48: 7860 | G48: kG | H48: =C48/1000*D48/1000*E48/1000*F48 -> 1.915875 | I48: 2.15 | J48: =H48*I48 -> 4.1191312 | K48: 2 | L48: 1 | M48: 24000 | N48: =H48*K48*L48 -> 3.83175 | O48: =J48*K48*M48 -> 197718.3
B49: Motor Rail-316L | C49: 3 | D49: =20+50+50+20 -> 140 | E49: 1000 | F49: 7860 | G49: kG | H49: =C49/1000*D49/1000*E49/1000*F49 -> 3.3012 | I49: 1.15 | J49: =H49*I49 -> 3.79638 | K49: 2 | L49: 1 | M49: 24000 | N49: =H49*K49*L49 -> 6.6024 | O49: =J49*K49*M49 -> 182226.24
B50: Motor Stopper-316L | C50: 3 | D50: 50 | E50: 50 | F50: 7980 | G50: kG | H50: =C50/1000*D50/1000*E50/1000*F50 -> 0.05985 | I50: 1.15 | J50: =H50*I50 -> 0.0688275 | K50: 2 | L50: 1 | M50: 24000 | N50: =H50*K50*L50 -> 0.1197 | O50: =J50*K50*M50 -> 3303.72
B51: Treaded Shaft M12-316L | E51: 1000 | F51: 1 | G51: m | H51: =E51/1000 -> 1 | I51: 1 | J51: =H51*I51 -> 1 | K51: 2 | L51: =2*22/7*(12/2000)^2*1*8000 -> 1.8102857 | M51: =423423/6 -> 70570.5 | N51: =H51*K51*L51 -> 3.6205714 | O51: =J51*K51*M51 -> 141141 | S51: 423423 | T51: =S51/6 -> 70570.5
A52: Fan Partition Assy 2-1 | B52: Partition (H x W) | C52: 1.5 | D52: =C6 -> 0 | E52: =D6 -> 0 | F52: 8000 | G52: kG | H52: =C52/1000*D52/1000*E52/1000*F52 -> 0 | I52: 1.15 | J52: =H52*I52 -> 0 | K52: 0 | L52: 1 | M52: 55000 | N52: =H52*K52*L52 -> 0 | O52: =J52*K52*M52 -> 0
B53: Base Channel-UNP125 L/R (W) | C53: 2.5 | D53: =15+25+50+25+15 -> 130 | E53: =D6 -> 0 | F53: 8000 | G53: kG | H53: =C53/1000*D53/1000*E53/1000*F53 -> 0 | I53: 1.15 | J53: =H53*I53 -> 0 | K53: 0 | L53: 1 | M53: 55000 | N53: =H53*K53*L53 -> 0 | O53: =J53*K53*M53 -> 0
B54: Blower/Motor Channel-UNP125 F/B | C54: 2.5 | D54: =15+25+50+25+15 -> 130 | E54: =E53*0.6 -> 0 | F54: 8000 | G54: kG | H54: =C54/1000*D54/1000*E54/1000*F54 -> 0 | I54: 2.15 | J54: =H54*I54 -> 0 | K54: 0 | L54: 1 | M54: 55000 | N54: =H54*K54*L54 -> 0 | O54: =J54*K54*M54 -> 0
B55: Blower Support-UNP125 L/R (D) | C55: 2.5 | D55: =25+50+25 -> 100 | E55: =E6*0.6 -> 0 | F55: 8000 | G55: kG | H55: =C55/1000*D55/1000*E55/1000*F55 -> 0 | I55: 2.15 | J55: =H55*I55 -> 0 | K55: 0 | L55: 1 | M55: 55000 | N55: =H55*K55*L55 -> 0 | O55: =J55*K55*M55 -> 0
B56: Motor Support-UNP125 L/R (D) | C56: 2.5 | D56: =25+50+25 -> 100 | E56: =E6*0.6 -> 0 | F56: 8000 | G56: kG | H56: =C56/1000*D56/1000*E56/1000*F56 -> 0 | I56: 2.15 | J56: =H56*I56 -> 0 | K56: 0 | L56: 1 | M56: 55000 | N56: =H56*K56*L56 -> 0 | O56: =J56*K56*M56 -> 0
B57: Motor Rail-316L | C57: 3 | D57: =20+50+50+20 -> 140 | E57: 1000 | F57: 8000 | G57: kG | H57: =C57/1000*D57/1000*E57/1000*F57 -> 3.36 | I57: 1.15 | J57: =H57*I57 -> 3.864 | K57: 0 | L57: 1 | M57: 55000 | N57: =H57*K57*L57 -> 0 | O57: =J57*K57*M57 -> 0
B58: Motor Stopper-316L | C58: 3 | D58: 50 | E58: 50 | F58: 7980 | G58: kG | H58: =C58/1000*D58/1000*E58/1000*F58 -> 0.05985 | I58: 1.15 | J58: =H58*I58 -> 0.0688275 | K58: 0 | L58: 1 | M58: 55000 | N58: =H58*K58*L58 -> 0 | O58: =J58*K58*M58 -> 0
B59: Treaded Shaft M12-316L | E59: 1000 | F59: 1 | G59: m | H59: =E59/1000 -> 1 | I59: 1 | J59: =H59*I59 -> 1 | K59: 0 | L59: =2*22/7*(12/2000)^2*1*8000 -> 1.8102857 | M59: =423423/6 -> 70570.5 | N59: =H59*K59*L59 -> 0 | O59: =J59*K59*M59 -> 0 | R59: M12-316L x 6m | S59: 423423 | T59: =S59/6 -> 70570.5
N60: =SUM(N18:N59) -> 132.6353 | O60: =SUM(O18:O59) -> 5454538.4 | R60: =2*22/7*(12/2000)^2*1*8000 -> 1.8102857

Sheet CoilCost 20251027
A1: X | B1: ThermalTrue®
B2: FOREX
B3: 45522 | E3: USD | F3: 1
E4: Euro | F4: 0.92
E5: SGP | F5: 1.35
E6: RM | F6: 4.68
E7: JPY | F7: 157.48
E8: Rmb | F8: 7.27
E9: Rp | F9: 17500
B10: COIL GEOMETRY | E10: mmT-T | F10: mmR-R | G10: Fin WT | H10: LWC WT | I10: EP WT | J10: RW | K10: WF (Fin) | L10: WF (LWC) | M10: WF (EP) | N10: SF | O10: Lhp
B11: 7mm | C11: 7 | D11: 7mmOD x 12R x 21.00 (T-T) x 18.19 (R-R) x 2P | E11: 21 | F11: 18.19 | G11: 0.11 | H11: 0.28 | I11: 1.5 | J11: 226 | K11: =(J11-F11*12)/J11+1 -> 1.0341593 | L11: 1.02 | M11: 1.15 | N11: 1.0935184 | O11: =22/7*E11/2 -> 33
B12: 7mm+ | C12: 7 | D12: 7mmOD x 12R x 22.00 (T-T) x 20.00 (R-R) x 2P | E12: 22 | F12: 20 | G12: 0.11 | H12: 0.28 | I12: 1.5 | J12: 248 | K12: =(J12-F12*12)/J12+1 -> 1.0322581 | L12: 1.02 | M12: 1.15 | N12: 1.0935184 | O12: =22/7*E12/2 -> 34.571429
B13: 3/8 | C13: 9.525 | D13: 3/8" x 12R x 25.00 (T-T) x 21.65 (R-R) x 2P | E13: 25 | F13: 21.65 | G13: 0.11 | H13: 0.33 | I13: 1.5 | J13: 268 | K13: =(J13-F13*12)/J13+1 -> 1.030597 | L13: 1.02 | M13: 1.15 | N13: 1.0694057 | O13: =22/7*E13/2 -> 39.285714
B14: 3/8+ | C14: 9.525 | D14: 3/8" x 12R x 25.40 (T-T) x 22.00 (R-R) x 2P | E14: 25.4 | F14: 22 | G14: 0.11 | H14: 0.33 | I14: 1.5 | J14: =F14*12+8 -> 272 | K14: =(J14-F14*12)/J14+1 -> 1.0294118 | L14: 1.02 | M14: 1.15 | N14: 1.0694057 | O14: =22/7*E14/2 -> 39.914286
B15: 1/2 | C15: 12.7 | D15: 1/2" x 8R x 31.75 (T-T) x 27.50 (R-R) x 1P | E15: 31.75 | F15: 27.5 | G15: 0.11 | H15: 0.34 | I15: 1.5 | J15: 230 | K15: =(J15-F15*8)/J15+1 -> 1.0434783 | L15: 1.02 | M15: 1.15 | N15: 1.0639841 | O15: =22/7*E15/2 -> 49.892857
B16: 5/8 | C16: 15.875 | D16: 5/8" x 6R x 38.10 (T-T) x 33.00 (R-R) x 1P | E16: 38.1 | F16: 33 | G16: 0.12 | H16: 0.41 | I16: 1.5 | J16: 208 | K16: =(J16-F16*6)/J16+1 -> 1.0480769 | L16: 1.02 | M16: 1.15 | N16: 1.06984 | O16: =22/7*E16/2 -> 59.871429
B17: 3/4 | C17: 19.05 | D17: 3/4" x 6R x 50.00 (T-T) x 43.30 (R-R) x 1P | E17: 50 | F17: 43.3 | G17: 0.14 | H17: 0.45 | I17: 1.5 | J17: 270 | K17: =(J17-F17*6)/J17+1 -> 1.0377778 | L17: 1.02 | M17: 1.15 | N17: 1.06984 | O17: =22/7*E17/2 -> 78.571429
B18: METAL STOCK | E18: UoM | F18: MX | G18: FOB | H18: Fab/Frt | I18: LF | J18: $ U/CUoM | K18: Rp/$ | L18: Rp U/CUoM | M18: U/Wuom
B19: GI-1.0 | C19: MS0102-004-0-XX-2 | D19: SGCC (GI) 1.0mm x 4' x 8' (8.07kG/m2) | E19: kG | F19: 8080 | G19: =24000/F9 -> 1.3714286 | H19: 0 | I19: 1 | J19: =(G19+H19)*I19 -> 1.3714286 | K19: =F$9 -> 17500 | L19: =J19*K19 -> 24000 | M19: 1
B20: GI-1.2 | C20: MS0102-005-0-XX-2 | D20: SGCC (GI) 1.2mm x 4' x 8' (9.64kG/m2) | E20: kG | F20: 8080 | G20: =24000/F9 -> 1.3714286 | H20: 0 | I20: 1 | J20: =(G20+H20)*I20 -> 1.3714286 | K20: =F$9 -> 17500 | L20: =J20*K20 -> 24000 | M20: 1
B21: GI-1.5 | C21: MS0102-006-0-XX-2 | D21: SGCC (GI) 1.5mm x 4' x 8' (12.00kG/m2) | E21: kG | F21: 8080 | G21: =24000/F9 -> 1.3714286 | H21: 0 | I21: 1 | J21: =(G21+H21)*I21 -> 1.3714286 | K21: =F$9 -> 17500 | L21: =J21*K21 -> 24000 | M21: 1
B22: GI-2.0 | C22: MS0102-007-0-XX-2 | D22: SGCC (GI) 2.0mm x 4' x 8' (15.92kG/m2) | E22: kG | F22: 8080 | G22: =30000/F9 -> 1.7142857 | H22: 0 | I22: 1 | J22: =(G22+H22)*I22 -> 1.7142857 | K22: =F$9 -> 17500 | L22: =J22*K22 -> 30000 | M22: 1
B23: GI-2.5 | C23: MS0102-008-0-XX-2 | D23: SGCC (GI) 2.5mm x 4' x 8' (19.85kG/m2) | E23: kG | F23: 8080 | G23: =30000/F9 -> 1.7142857 | H23: 0 | I23: 1 | J23: =(G23+H23)*I23 -> 1.7142857 | K23: =F$9 -> 17500 | L23: =J23*K23 -> 30000 | M23: 1
B24: 304-1.0 | C24: MS0105-003-0-XX-2 | D24: SUS304 1.0mm x 4' x 8' (7.93kG/m2) | E24: kG | F24: 7930 | G24: =65000/F9 -> 3.7142857 | H24: 0 | I24: 1 | J24: =(G24+H24)*I24 -> 3.7142857 | K24: =F$9 -> 17500 | L24: =J24*K24 -> 65000 | M24: 1
B25: 304-1.2 | C25: MS0105-004-0-XX-2 | D25: SUS304 1.2mm x 4' x 8' (9.52kG/m2) | E25: kG | F25: 7930 | G25: =65000/F9 -> 3.7142857 | H25: 0 | I25: 1 | J25: =(G25+H25)*I25 -> 3.7142857 | K25: =F$9 -> 17500 | L25: =J25*K25 -> 65000 | M25: 1
B26: 304-1.5 | C26: MS0105-005-0-XX-2 | D26: SUS304 1.5mm x 4' x 8' (11.90kG/m2) | E26: kG | F26: 7930 | G26: =65000/F9 -> 3.7142857 | H26: 0 | I26: 1 | J26: =(G26+H26)*I26 -> 3.7142857 | K26: =F$9 -> 17500 | L26: =J26*K26 -> 65000 | M26: 1
B27: 316-1.0 | C27: MS0106-003-0-XX-2 | D27: SUS316L 1.0mm x 4' x 8' (7.98kG/m2) | E27: kG | F27: 7980 | G27: =90000/F9 -> 5.1428571 | H27: 0 | I27: 1 | J27: =(G27+H27)*I27 -> 5.1428571 | K27: =F$9 -> 17500 | L27: =J27*K27 -> 90000 | M27: 1
B28: 316-1.2 | C28: MS0106-004-0-XX-2 | D28: SUS316L 1.2mm x 4' x 8' (9.58kG/m2) | E28: kG | F28: 7980 | G28: =90000/F9 -> 5.1428571 | H28: 0 | I28: 1 | J28: =(G28+H28)*I28 -> 5.1428571 | K28: =F$9 -> 17500 | L28: =J28*K28 -> 90000 | M28: 1
B29: 316-1.5 | C29: MS0106-005-0-XX-2 | D29: SUS316L 1.5mm x 4' x 8' (11.97kG/m2) | E29: kG | F29: 7980 | G29: =90000/F9 -> 5.1428571 | H29: 0 | I29: 1 | J29: =(G29+H29)*I29 -> 5.1428571 | K29: =F$9 -> 17500 | L29: =J29*K29 -> 90000 | M29: 1
B30: Al-1.0 | C30: MS0107-004-0-XX-2 | D30: Al Sheet 1.2mm x 4' x 8' (3.24kG/m2) | E30: kG | F30: 2700 | G30: =75000/F9 -> 4.2857143 | H30: 0 | I30: 1 | J30: =(G30+H30)*I30 -> 4.2857143 | K30: =F$9 -> 17500 | L30: =J30*K30 -> 75000 | M30: 1
B31: Al-1.5 | C31: MS0107-005-0-XX-2 | D31: Al Sheet 1.5mm x 4' x 8' (4.05kG/m2) | E31: kG | F31: 2700 | G31: =75000/F9 -> 4.2857143 | H31: 0 | I31: 1 | J31: =(G31+H31)*I31 -> 4.2857143 | K31: =F$9 -> 17500 | L31: =J31*K31 -> 75000 | M31: 1
B32: Al-2.0 | C32: MS0107-006-0-XX-2 | D32: Al Sheet 2.0mm x 4' x 8' (5.40kG/m2) | E32: kG | F32: 2700 | G32: =75000/F9 -> 4.2857143 | H32: 0 | I32: 1 | J32: =(G32+H32)*I32 -> 4.2857143 | K32: =F$9 -> 17500 | L32: =J32*K32 -> 75000 | M32: 1
B33: Brass-1.0 | C33: MS0109-000-0-XX-2 | D33: Brass 1.0mm x 1m2 x 8650kG/m3 | E33: kG | F33: 8650 | G33: 4.3874468 | H33: 0 | I33: 1 | J33: =(G33+H33)*I33 -> 4.3874468 | K33: =F$9 -> 17500 | L33: =J33*K33 -> 76780.319 | M33: 1
B34: Brass-1.2 | C34: MS0109-001-0-XX-2 | D34: Brass 1.2mm x 1m x 2m | E34: kG | F34: 8650 | G34: 4.3874468 | H34: 0 | I34: 1 | J34: =(G34+H34)*I34 -> 4.3874468 | K34: =F$9 -> 17500 | L34: =J34*K34 -> 76780.319 | M34: 1
B35: Brass-1.5 | C35: MS0109-002-0-XX-2 | D35: Brass 1.5mm x 1m x 2m | E35: kG | F35: 8650 | G35: 4.3874468 | H35: 0 | I35: 1 | J35: =(G35+H35)*I35 -> 4.3874468 | K35: =F$9 -> 17500 | L35: =J35*K35 -> 76780.319 | M35: 1
B36: FIN STOCK | E36: UoM | F36: MX | G36: FOB | H36: Fab/Frt | I36: LF | J36: $ U/CUoM | K36: Rp/$ | L36: Rp U/CUoM | M36: U/Wuom
B37: AF-3/8 x 0.11 | C37: CS0102-001-0-XX-3 | D37: Al Fin 272mmRW : Plain 0.110mmT | E37: kG | F37: 2700 | G37: =108000/F9 -> 6.1714286 | H37: 1 | I37: 1 | J37: =(G37*H37)*I37 -> 6.1714286 | K37: =F$9 -> 17500 | L37: =J37*K37 -> 108000 | M37: 1
B38: AF-1/2 x 0.11 | C38: CS0102-002-0-XX-3 | D38: Al Fin 230mmRW : Plain 0.110mmT | E38: kG | F38: 2700 | G38: =G37 -> 6.1714286 | H38: 1 | I38: 1 | J38: =(G38*H38)*I38 -> 6.1714286 | K38: =F$9 -> 17500 | L38: =J38*K38 -> 108000 | M38: 1
B39: AF-5/8 x 0.12 | C39: CS0102-003-0-XX-3 | D39: Al Fin 208mmRW : Plain 0.120mmT | E39: kG | F39: 2700 | G39: =G37 -> 6.1714286 | H39: 1 | I39: 1 | J39: =(G39*H39)*I39 -> 6.1714286 | K39: =F$9 -> 17500 | L39: =J39*K39 -> 108000 | M39: 1
B40: AF-3/8 x 0.14 | C40: CS0102-004-0-XX-3 | D40: Al Fin 272mmRW : Plain 0.140mmT | E40: kG | F40: 2700 | G40: =G37 -> 6.1714286 | H40: 1 | I40: 1 | J40: =(G40*H40)*I40 -> 6.1714286 | K40: =F$9 -> 17500 | L40: =J40*K40 -> 108000 | M40: 1
B41: AF-1/2 x 0.14 | C41: CS0102-005-0-XX-3 | D41: Al Fin 230mmRW : Plain 0.140mmT | E41: kG | F41: 2700 | G41: =G37 -> 6.1714286 | H41: 1 | I41: 1 | J41: =(G41*H41)*I41 -> 6.1714286 | K41: =F$9 -> 17500 | L41: =J41*K41 -> 108000 | M41: 1
B42: AF-5/8 x 0.14 | C42: CS0102-006-0-XX-3 | D42: Al Fin 208mmRW : Plain 0.140mmT | E42: kG | F42: 2700 | G42: =G37 -> 6.1714286 | H42: 1 | I42: 1 | J42: =(G42*H42)*I42 -> 6.1714286 | K42: =F$9 -> 17500 | L42: =J42*K42 -> 108000 | M42: 1
B43: BF-3/8 x 0.115 | C43: CS0102-101-0-XX-3 | D43: Al Blue Fin 272mmRW : 0.115mmT | E43: kG | F43: 2700 | G43: =110000/F9 -> 6.2857143 | H43: 1 | I43: 1 | J43: =(G43*H43)*I43 -> 6.2857143 | K43: =F$9 -> 17500 | L43: =J43*K43 -> 110000 | M43: 1
B44: BF-1/2 x 0.115 | C44: CS0102-102-0-XX-3 | D44: Al Blue Fin 230mmRW : 0.115mmT | E44: kG | F44: 2700 | G44: =G43 -> 6.2857143 | H44: 1 | I44: 1 | J44: =(G44*H44)*I44 -> 6.2857143 | K44: =F$9 -> 17500 | L44: =J44*K44 -> 110000 | M44: 1
B45: BF-5/8 x 0.115 | C45: CS0102-103-0-XX-3 | D45: Al Blue Fin 208mmRW : 0.115mmT | E45: kG | F45: 2700 | G45: =G43 -> 6.2857143 | H45: 1 | I45: 1 | J45: =(G45*H45)*I45 -> 6.2857143 | K45: =F$9 -> 17500 | L45: =J45*K45 -> 110000 | M45: 1
B46: GF-3/8 x 0.115 | C46: CS0102-201-0-XX-3 | D46: Al Gold Fin 272mmRW : 0.115mmT | E46: kG | F46: 2700 | G46: =111000/F9 -> 6.3428571 | H46: 1 | I46: 1 | J46: =(G46*H46)*I46 -> 6.3428571 | K46: =F$9 -> 17500 | L46: =J46*K46 -> 111000 | M46: 1
B47: GF-1/2 x 0.115 | C47: CS0102-202-0-XX-3 | D47: Al Gold Fin 230mmRW : 0.115mmT | E47: kG | F47: 2700 | G47: =G46 -> 6.3428571 | H47: 1 | I47: 1 | J47: =(G47*H47)*I47 -> 6.3428571 | K47: =F$9 -> 17500 | L47: =J47*K47 -> 111000 | M47: 1
B48: GF-5/8 x 0.115 | C48: CS0102-203-0-XX-3 | D48: Al Gold Fin 208mmRW : 0.115mmT | E48: kG | F48: 2700 | G48: =G46 -> 6.3428571 | H48: 1 | I48: 1 | J48: =(G48*H48)*I48 -> 6.3428571 | K48: =F$9 -> 17500 | L48: =J48*K48 -> 111000 | M48: 1
B49: CF-3/8 x 0.120 | C49: CS0102-301-0-XX-3 | D49: Cu Fin 272mmRW : Plain 0.120mmT | E49: kG | F49: 8900 | G49: =321000/F9 -> 18.342857 | H49: 1 | I49: 1 | J49: =(G49*H49)*I49 -> 18.342857 | K49: =F$9 -> 17500 | L49: =J49*K49 -> 321000 | M49: 1
B50: CF-1/2 x 0.120 | C50: CS0102-302-0-XX-3 | D50: Cu Fin 230mmRW : Plain 0.120mmT | E50: kG | F50: 8900 | G50: =G49 -> 18.342857 | H50: 1 | I50: 1 | J50: =(G50*H50)*I50 -> 18.342857 | K50: =F$9 -> 17500 | L50: =J50*K50 -> 321000 | M50: 1
B51: CF-5/8 x 0.120 | C51: CS0102-303-0-XX-3 | D51: Cu Fin 208mmRW : Plain 0.120mmT | E51: kG | F51: 8900 | G51: =G49 -> 18.342857 | H51: 1 | I51: 1 | J51: =(G51*H51)*I51 -> 18.342857 | K51: =F$9 -> 17500 | L51: =J51*K51 -> 321000 | M51: 1
B52: LWC | E52: UoM | F52: MX | G52: FOB | H52: Fab/Frt | I52: LF | J52: $ U/CUoM | K52: Rp/$ | L52: Rp U/CUoM | M52: U/Wuom
B53: CuLWC-7mm x 0.30 | C53: CS0101-001-0-XX-3 | D53: Copper LWC Plain : 7.00Ø x 0.33T | E53: kG | F53: 8900 | G53: =325000/F9 -> 18.571429 | H53: 1 | I53: 1 | J53: =(G53*H53)*I53 -> 18.571429 | K53: =F$9 -> 17500 | L53: =J53*K53 -> 325000 | M53: 1
B54: CuLWC-3/8 x 0.33 | C54: CS0101-002-0-XX-3 | D54: Copper LWC Plain : 9.52Ø x 0.33T | E54: kG | F54: 8900 | G54: =G53 -> 18.571429 | H54: 1 | I54: 1 | J54: =(G54*H54)*I54 -> 18.571429 | K54: =F$9 -> 17500 | L54: =J54*K54 -> 325000 | M54: 1
B55: CuLWC-1/2 x 0.34 | C55: CS0101-003-0-XX-3 | D55: Copper LWC Plain : 12.70Ø x 0.34T | E55: kG | F55: 8900 | G55: =G53 -> 18.571429 | H55: 1 | I55: 1 | J55: =(G55*H55)*I55 -> 18.571429 | K55: =F$9 -> 17500 | L55: =J55*K55 -> 325000 | M55: 1
B56: CuLWC-5/8 x 0.41 | C56: CS0101-004-0-XX-3 | D56: Copper LWC Plain : 15.87Ø x 0.41T | E56: kG | F56: 8900 | G56: =G53 -> 18.571429 | H56: 1 | I56: 1 | J56: =(G56*H56)*I56 -> 18.571429 | K56: =F$9 -> 17500 | L56: =J56*K56 -> 325000 | M56: 1
B57: U BEND / AGC RING | E57: UoM | F57: MX | G57: FOB | H57: Fab/Frt | I57: LF | J57: $ U/CUoM | K57: Rp/$ | L57: Rp U/CUoM | M57: U/Wuom
B58: UB-3/8 | C58: CS0106-001-1-XX-2 | D58: U Bend 3/8" (25p) | E58: Pc | F58: 1 | G58: 0.28 | H58: 0 | I58: 1 | J58: =(G58+H58)*I58 -> 0.28 | K58: =F$9 -> 17500 | L58: =J58*K58 -> 4900 | M58: 0.0064294227
B59: UB-1/2 | C59: CS0106-002-1-XX-2 | D59: U Bend 1/2" (32p) | E59: Pc | F59: 1 | G59: 0.8 | H59: 0 | I59: 1 | J59: =(G59+H59)*I59 -> 0.8 | K59: =F$9 -> 17500 | L59: =J59*K59 -> 14000 | M59: 0.013891801
B60: UB-5/8 | C60: CS0106-003-1-XX-2 | D60: U Bend 5/8" (38p) | E60: Pc | F60: 1 | G60: 1.4 | H60: 0 | I60: 1 | J60: =(G60+H60)*I60 -> 1.4 | K60: =F$9 -> 17500 | L60: =J60*K60 -> 24500 | M60: 0.021442083
B61: BRAZING ALLOY | E61: UoM | F61: MX | G61: FOB | H61: Fab/Frt | I61: LF | J61: $ U/CUoM | K61: Rp/$ | L61: Rp U/CUoM | M61: U/Wuom
B62: Alloy-2% | C62: OS0301-003-0-XX-2 | D62: Brazing Rod 2% x 55Pc/kG | E62: kG | F62: 0.028431923 | G62: 42.541155 | H62: 0 | I62: 1.1 | J62: =(G62+H62)*I62 -> 46.795271 | K62: =F$9 -> 17500 | L62: =J62*K62 -> 818917.24 | M62: 1
B63: Alloy-35% | C63: OS0301-005-0-XX-2 | D63: Brazing Rod 35% x 49Pc/kG | E63: kG | F63: 0.11077789 | G63: 480.91843 | H63: 0 | I63: 1.1 | J63: =(G63+H63)*I63 -> 529.01027 | K63: =F$9 -> 17500 | L63: =J63*K63 -> 9257679.8 | M63: 1
B64: Welding | C64: OS0302-001-0-XX-2 | D64: Welding Rod : Steel RB 2.6; 5kg/packing | E64: kG | F64: 0.05 | G64: 1.3810962 | H64: 0 | I64: 1.1 | J64: =(G64+H64)*I64 -> 1.5192059 | K64: =F$9 -> 17500 | L64: =J64*K64 -> 26586.103 | M64: 1
B65: BRAZING GASES | E65: UoM | F65: MX | G65: FOB | H65: Fab/Frt | I65: LF | J65: $ U/CUoM | K65: Rp/$ | L65: Rp U/CUoM | M65: U/Wuom
B66: LPG | C66: OS0304-001-0-XX-2 | D66: Industrial Gas, LPG : 6m3/150bar | E66: Cy | F66: 0.046713474 | G66: 77.070103 | H66: 0 | I66: 1.1 | J66: =(G66+H66)*I66 -> 84.777113 | K66: =F$9 -> 17500 | L66: =J66*K66 -> 1483599.5 | M66: 0
B67: O2 | C67: OS0304-002-0-XX-2 | D67: Industrial Gas, Oxygen : 6m3/150bar | E67: Cy | F67: 0.046713474 | G67: 69.054812 | H67: 0 | I67: 1.1 | J67: =(G67+H67)*I67 -> 75.960293 | K67: =F$9 -> 17500 | L67: =J67*K67 -> 1329305.1 | M67: 0
B68: N2 | C68: OS0304-003-0-XX-2 | D68: Industrial Gas, Nitrogen : 6m3/150bar | E68: Cy | F68: 0.046713474 | G68: 86.318515 | H68: 0 | I68: 1.1 | J68: =(G68+H68)*I68 -> 94.950367 | K68: =F$9 -> 17500 | L68: =J68*K68 -> 1661631.4 | M68: 0
B69: N2-Leak Test | C69: OS0304-003-0-XX-2 | D69: Industrial Gas, Nitrogen : 6m3/150bar | E69: Cy | F69: 5 | G69: 86.318515 | H69: 0 | I69: 1.1 | J69: =(G69+H69)*I69 -> 94.950367 | K69: =F$9 -> 17500 | L69: =J69*K69 -> 1661631.4 | M69: 0
B70: COATING SUPPLIES | E70: UoM | F70: MX | G70: FOB | H70: Fab/Frt | I70: LF | J70: $ U/CUoM | K70: Rp/$ | L70: Rp U/CUoM | M70: U/Wuom | N70: $/m2R
B71: VR514 | C71: OS0201-001-0-HE-3 | D71: Heresite Phenolic VR514 (5USG Pail @ 4.442kG/USG) | E71: kG/m2 | F71: 0.0270962 | G71: =575/22 -> 26.136364 | H71: 0 | I71: 2.7 | J71: =(G71+H71)*I71 -> 70.568182 | K71: =F$9 -> 17500 | L71: =J71*K71 -> 1234943.2 | M71: =(0.59+0.67)/2 -> 0.63 | N71: =3284816.7599379/K71 -> 187.70381
B72: S440 | C72: OS0201-002-0-HE-3 | D72: Heresite Solvent S440 (Impala Super) | E72: kG/m2 | F72: 0.01304744 | G72: =27600/(5*2.8364)/16219 -> 0.11999068 | H72: 0 | I72: 1.1 | J72: =(G72+H72)*I72 -> 0.13198975 | K72: =F$9 -> 17500 | L72: =J72*K72 -> 2309.8207 | M72: 0
B73: UC5504 | C73: OS0201-003-0-HE-3 | D73: Heresite Polyurethane UC5504 | E73: kG/m2 | F73: 0.029926248 | G73: =103.17/4.442 -> 23.226024 | H73: 0 | I73: 1.95 | J73: =(G73+H73)*I73 -> 45.290747 | K73: =F$9 -> 17500 | L73: =J73*K73 -> 792588.08 | M73: 0.61 | N73: =5343674.35853061/K73 -> 305.35282
B74: S330 | C74: OS0201-004-0-HE-3 | D74: Heresite Solvent S330 | E74: kG/m2 | F74: 0.014410173 | G74: =27600/(5*2.8364)/16219 -> 0.11999068 | H74: 0 | I74: 1.1 | J74: =(G74+H74)*I74 -> 0.13198975 | K74: =F$9 -> 17500 | L74: =J74*K74 -> 2309.8207 | M74: 0
B75: WB506 | C75: OS0201-005-0-HE-3 | D75: Heresite Phenolic WB506 (5USG/4.442kG per Pail) | E75: L/m2 | F75: 0.02309094 | G75: =228/5/3.7854 -> 12.046283 | H75: 0 | I75: 1.95 | J75: =(G75+H75)*I75 -> 23.490252 | K75: =F$9 -> 17500 | L75: =J75*K75 -> 411079.41 | M75: 0.3 | N75: =2135680.44645463/K75 -> 122.03888
B76: Water | C76: - | D76: Water | E76: L/m2 | F76: 0 | G76: 0 | H76: 0 | I76: 1.1 | J76: =(G76+H76)*I76 -> 0 | K76: =F$9 -> 17500 | L76: =J76*K76 -> 0 | M76: 0
B77: Aeris AC | C77: OS0203-001-0-DM-3 | D77: Aeris AG-CPB-5 (AUD$451.52 per 5Liter) | E77: L/m2 | F77: 0.05 | G77: =451.52*9786/16219/5 -> 54.486401 | H77: 0 | I77: 1.5 | J77: =(G77+H77)*I77 -> 81.729602 | K77: =F$9 -> 17500 | L77: =J77*K77 -> 1430268 | M77: 0.3 | N77: =15823716.0625617/K77 -> 904.21235
B78: Aeris AB | C78: OS0203-002-0-DM-3 | D78: Aeris AG-CPB-5 (AUD$115.02 per 1.25Liter) | E78: L/m2 | F78: 0.0029 | G78: =115.02*9786/16219/1.25 -> 55.519365 | H78: 0 | I78: 1.5 | J78: =(G78+H78)*I78 -> 83.279047 | K78: =F$9 -> 17500 | L78: =J78*K78 -> 1457383.3 | M78: 0
B79: TiO2 | C79: OS0202-001-0-DM-3 | D79: ECRA-DMT TiO2 | E79: L/m2 | F79: 0.02309094 | G79: 30 | H79: 0 | I79: 2.7 | J79: =(G79+H79)*I79 -> 81 | K79: =F$9 -> 17500 | L79: =J79*K79 -> 1417500 | M79: 0.3 | N79: =4221180.43129144/K79 -> 241.21031
B80: Water | C80: - | D80: Water | E80: L/m2 | F80: 0 | G80: 0 | H80: 0 | I80: 1.1 | J80: =(G80+H80)*I80 -> 0 | K80: =F$9 -> 17500 | L80: =J80*K80 -> 0 | M80: 0
B81: FAB COST | E81: UoM | F81: MX | G81: FOB | H81: Fab/Frt | I81: LF | J81: $ U/CUoM | K81: Rp/$ | L81: Rp U/CUoM | M81: U/Wuom
B82: Bend | C82: SC0101-001-0-XX-2 | D82: Metal FabCharge : Shear/Bend GI < 2.0mmT, S | E82: Stroke | F82: 1 | G82: 0.092484124 | H82: 0 | I82: 1 | J82: =(G82+H82)*I82 -> 0.092484124 | K82: =F$9 -> 17500 | L82: =J82*K82 -> 1618.4722 | M82: 0
B83: Punch | C83: SC0101-016-0-XX-2 | D83: Metal FabCharge : Punch GI < 2.0mmT | E83: Stroke | F83: 1 | G83: 0.029248412 | H83: 0 | I83: 1 | J83: =(G83+H83)*I83 -> 0.029248412 | K83: =F$9 -> 17500 | L83: =J83*K83 -> 511.84722 | M83: 0
B84: Emboss | C84: SC0101-013-0-XX-2 | D84: Metal FabCharge : Emboss 3/8", 1/2", 5/8" | E84: Stroke | F84: 1 | G84: 0.061656082 | H84: 0 | I84: 1 | J84: =(G84+H84)*I84 -> 0.061656082 | K84: =F$9 -> 17500 | L84: =J84*K84 -> 1078.9814 | M84: 0
B85: AGC-3/8 | C85: CS0107-001-1-TT-2 | D85: Silicon Ring 3/8" | E85: Pc | F85: 1 | G85: 0.068068315 | H85: 0 | I85: 1 | J85: =(G85+H85)*I85 -> 0.068068315 | K85: =F$9 -> 17500 | L85: =J85*K85 -> 1191.1955 | M85: 0.000825
B86: AGC-1/2 | C86: CS0107-002-1-TT-2 | D86: Silicon Ring 1/2" | E86: Pc | F86: 1 | G86: 0.089401319 | H86: 0 | I86: 1 | J86: =(G86+H86)*I86 -> 0.089401319 | K86: =F$9 -> 17500 | L86: =J86*K86 -> 1564.5231 | M86: 0.0012
B87: AGC-5/8 | C87: CS0107-003-1-TT-2 | D87: Silicon Ring 5/8" | E87: Pc | F87: 1 | G87: 0.11353968 | H87: 0 | I87: 1 | J87: =(G87+H87)*I87 -> 0.11353968 | K87: =F$9 -> 17500 | L87: =J87*K87 -> 1986.9443 | M87: 0.0017454545
B88: HEADER | E88: UoM | F88: MX | G88: FOB | H88: Fab/Frt | I88: LF | J88: $ U/CUoM | K88: Rp/$ | L88: Rp U/CUoM | M88: U/Wuom | N88: WT
B89: BS40-3/4 | C89: CS0202-002-0-XX-2 | D89: Steel Pipe, 3/4" ANSI Sch40 (25mm) | E89: m | F89: 1 | G89: 4.392404 | H89: 0 | I89: 1.1 | J89: =(G89+H89)*I89 -> 4.8316444 | K89: =F$9 -> 17500 | L89: =J89*K89 -> 84553.776 | M89: 1.68 | N89: 2.8702
B90: BS40-1 | C90: CS0202-003-0-XX-2 | D90: Steel Pipe, 1" ANSI Sch40 (35mm) | E90: m | F90: 1 | G90: 6.3814045 | H90: 0 | I90: 1.1 | J90: =(G90+H90)*I90 -> 7.019545 | K90: =F$9 -> 17500 | L90: =J90*K90 -> 122842.04 | M90: 2.5 | N90: 3.3782
B91: BS40-1 1/4 | C91: CS0202-004-0-XX-2 | D91: Steel Pipe, 1 1/4" ANSI Sch40 (40mm) | E91: m | F91: 1 | G91: 7.3473498 | H91: 0 | I91: 1.1 | J91: =(G91+H91)*I91 -> 8.0820848 | K91: =F$9 -> 17500 | L91: =J91*K91 -> 141436.48 | M91: 3.38 | N91: 3.556
B92: BS40-1 1/2 | C92: CS0202-005-0-XX-2 | D92: Steel Pipe, 1 1/2" ANSI Sch40 (50mm) | E92: m | F92: 1 | G92: 7.4090059 | H92: 0 | I92: 1.1 | J92: =(G92+H92)*I92 -> 8.1499065 | K92: =F$9 -> 17500 | L92: =J92*K92 -> 142623.36 | M92: 4.04 | N92: 3.683
B93: BS40-2 | C93: CS0202-006-0-XX-2 | D93: Steel Pipe, 2" ANSI Sch40 (65mm) | E93: m | F93: 1 | G93: 14.633044 | H93: 0 | I93: 1.1 | J93: =(G93+H93)*I93 -> 16.096348 | K93: =F$9 -> 17500 | L93: =J93*K93 -> 281686.09 | M93: 5.43 | N93: 3.9116
B94: BS40-2 1/2 | C94: CS0202-007-0-XX-2 | D94: Steel Pipe, 2 1/2" ANSI Sch40 (75mm) | E94: m | F94: 1 | G94: 17.726124 | H94: 0 | I94: 1.1 | J94: =(G94+H94)*I94 -> 19.498736 | K94: =F$9 -> 17500 | L94: =J94*K94 -> 341227.88 | M94: 8.62 | N94: 5.1562
B95: BS40-3 | C95: CS0202-008-0-XX-2 | D95: Steel Pipe, 3" ANSI Sch40 (80mm) | E95: m | F95: 1 | G95: 18.25 | H95: 0 | I95: 1.1 | J95: =(G95+H95)*I95 -> 20.075 | K95: =F$9 -> 17500 | L95: =J95*K95 -> 351312.5 | M95: 11.27 | N95: 5.4864
B96: BS40-3 1/2 | C96: CS0202-009-0-XX-2 | D96: Steel Pipe, 3 1/2" ANSI Sch40 (100mm) | E96: m | F96: 1 | G96: 39.305753 | H96: 0 | I96: 1.1 | J96: =(G96+H96)*I96 -> 43.236328 | K96: =F$9 -> 17500 | L96: =J96*K96 -> 756635.74 | M96: 13.56 | N96: 5.7404
B97: BS40-4 | C97: CS0202-009-0-XX-2 | D97: Steel Pipe, 4" ANSI Sch40 (115mm) | E97: m | F97: 1 | G97: 20.13 | H97: 0 | I97: 1.1 | J97: =(G97+H97)*I97 -> 22.143 | K97: =F$9 -> 17500 | L97: =J97*K97 -> 387502.5 | M97: 16.06 | N97: 6.0198
B98: BS40-5 | C98: CS0202-010-0-XX-2 | D98: Steel Pipe, 5" ANSI Sch40 (140mm) | E98: m | F98: 1 | G98: 22.5 | H98: 0 | I98: 1.1 | J98: =(G98+H98)*I98 -> 24.75 | K98: =F$9 -> 17500 | L98: =J98*K98 -> 433125 | M98: 21.74 | N98: 6.5532
B99: CuCWC-7/8 | C99: CS0203-001-0-XX-2 | D99: Cu Header Pipe, 22mmOD (7/8" x 0.9T x 0.531kG/m) | E99: m | F99: 1 | G99: 8.55 | H99: 0 | I99: 1.1 | J99: =(G99+H99)*I99 -> 9.405 | K99: =F$9 -> 17500 | L99: =J99*K99 -> 164587.5 | M99: 0.531 | N99: 0.9
B100: CuCWC-1 1/8 | C100: CS0203-002-0-XX-2 | D100: Cu Header Pipe, 28mmOD (1 1/8" x 0.9T x 0.682kG/m) | E100: m | F100: 1 | G100: 6.5176645 | H100: 0 | I100: 1.1 | J100: =(G100+H100)*I100 -> 7.1694309 | K100: =F$9 -> 17500 | L100: =J100*K100 -> 125465.04 | M100: 0.682 | N100: 0.9
...

Sheet Quotation
G2: PT. UDARA JADI BERSIH
G3: Manufacture : Kawasan Sarana Terpadu, JL. Industri Cikarang, Pasirgombong, Kec. Cikarang Utara
G4: Kab. Bekasi - Jawa Barat. 17530. Phone : (021) 8935670 - 71
B8: To | C8: PT Midea | H8: QUOTATION | K8: From | L8: Rayesh
B9: Add
H10: AHU CW 3492
K11: Date | L11: =NOW() -> 46089.91
B12: Up | H12: Telp | K12: Your Ref
